Workbook

Sheet Summary
F2: BUY | G2: =IF(G11<=-15%,"BÁN",IF(G11<=-7%,"GIẢM",IF(G11<=7%,"THEO DÕI",IF(G11<15%,"THÊM","MUA")))) -> THEO DÕI | H2: =IF(H11<=-15%,"BÁN",IF(H11<=-7%,"GIẢM",IF(H11<=7%,"THEO DÕI",IF(H11<15%,"THÊM","MUA")))) -> THEO DÕI
B3: Valuation method | D3: Percentage | F3: =IF(F12<=-15%,"BÁN",IF(F12<=-7%,"GIẢM",IF(F12<=7%,"THEO DÕI",IF(F12<15%,"THÊM","MUA")))) -> THEO DÕI | G3: =IF(G12<=-15%,"BÁN",IF(G12<=-7%,"GIẢM",IF(G12<=7%,"THEO DÕI",IF(G12<15%,"THÊM","MUA")))) -> MUA | H3: =IF(H12<=-15%,"BÁN",IF(H12<=-7%,"GIẢM",IF(H12<=7%,"THEO DÕI",IF(H12<15%,"THÊM","MUA")))) -> THEO DÕI
B4: FCFF | D4: 0.7 | F4: =IF(F13<=-15%,"BÁN",IF(F13<=-7%,"GIẢM",IF(F13<=7%,"THEO DÕI",IF(F13<15%,"THÊM","MUA")))) -> THEO DÕI | G4: =IF(G13<=-15%,"BÁN",IF(G13<=-7%,"GIẢM",IF(G13<=7%,"THEO DÕI",IF(G13<15%,"THÊM","MUA")))) -> THEO DÕI | H4: =IF(H13<=-15%,"BÁN",IF(H13<=-7%,"GIẢM",IF(H13<=7%,"THEO DÕI",IF(H13<15%,"THÊM","MUA")))) -> THEO DÕI
B5: Multiple | D5: 0.3 | F5: =IF(F14<=-15%,"BÁN",IF(F14<=-7%,"GIẢM",IF(F14<=7%,"THEO DÕI",IF(F14<15%,"THÊM","MUA")))) -> THEO DÕI | G5: =IF(G14<=-15%,"BÁN",IF(G14<=-7%,"GIẢM",IF(G14<=7%,"THEO DÕI",IF(G14<15%,"THÊM","MUA")))) -> THEO DÕI | H5: =IF(H14<=-15%,"BÁN",IF(H14<=-7%,"GIẢM",IF(H14<=7%,"THEO DÕI",IF(H14<15%,"THÊM","MUA")))) -> THEO DÕI
B7: Recommendation
B8: Current price (06/06/2022) | D8: 153000
B10: Target price | D10: =D4*DCF!B41+Multiple!R38*Summary!D5 -> 191125.55
B12: Upside | D12: =(D10-D8)/D8 -> 0.24918659 | G12: Unit: VND

Sheet DATA
B1: MWG | C1: 2017 | D1: 2018 | E1: 2019 | F1: 2020 | G1: 2021
B2: Audit Committee | C2: EY | D2: EY | E2: EY | F2: EY | G2: EY
B3: Audit Opinion | C3: Unqualified opinion | D3: Unqualified opinion | E3: Unqualified opinion | F3: Unqualified opinion | G3: Unqualified opinion
B4: BALANCE SHEET
B6: A. CURRENT ASSETS | C6: 18862861 | D6: 23371995 | E6: 35011897 | F6: 37317234 | G6: 51955258
B8: I. Cash and Cash Equivalents | C8: 3410983.4 | D8: 3749550.3 | E8: 3115236.8 | F8: 7347857.4 | G8: 4142015.8
B9: 1. Cash | C9: 2189863.3 | D9: 3363717.3 | E9: 2024347.9 | F9: 2243274.5 | G9: 2606672.3
B10: 2. Cash equivalents | C10: 1221120.1 | D10: 385833 | E10: 1090888.9 | F10: 5104582.9 | G10: 1535343.5
B12: II. Short-term Financial Investment | C12: 0 | D12: 50922.5 | E12: 3137000 | F12: 8057318.8 | G12: 14236626
B13: 1. Securities available for sale | C13: 0 | D13: 0 | E13: 0 | F13: 0 | G13: 0
B14: 2. Provision for decline in value of investments in securities | C14: 0 | D14: 0 | E14: 0 | F14: 0 | G14: 0
B15: 3. Securities hold to maturity | C15: 0 | D15: 50922.5 | E15: 3137000 | F15: 8057318.8 | G15: 14236626
B17: III. Short-term Receivables | C17: 2765847.8 | D17: 1542529.7 | E17: 1815085.6 | F17: 1595251 | G17: 3162122 | J17: =IS!D3/AVERAGE(D27:E27) -> 3.8288354
B18: 1. Short-term receivables from customers | C18: 1431776.8 | D18: 369573.7 | E18: 262268.4 | F18: 196394.5 | G18: 384236.6
B19: 2. Prepaid for suppliers | C19: 117942 | D19: 21007.3 | E19: 195016.8 | F19: 287913.3 | G19: 390738.8
B20: 3. Internal short-term receivables | C20: 0 | D20: 0 | E20: 0 | F20: 0 | G20: 0
B21: 4. Receivables according to construction contract progress | C21: 0 | D21: 0 | E21: 0 | F21: 0 | G21: 0
B22: 5. Short-term loan receivable | C22: 84700 | D22: 0 | E22: 0 | F22: 80000 | G22: 961917.7
B23: 6. Other short-term receivables | C23: 1131428.9 | D23: 1151948.8 | E23: 1357800.4 | F23: 1030943.1 | G23: 1425228.9
B24: 7. Provision for short-term doubtful receivables | C24: 0 | D24: 0 | E24: 0 | F24: 0 | G24: 0
B25: 8. Assets missing pending for resolution | C25: 0 | D25: 0 | E25: 0 | F25: 0 | G25: 0
B27: IV. Inventory | C27: 12050163 | D27: 17446005 | E27: 25745428 | F27: 19422178 | G27: 29167232
B28: 1. Inventory | C28: 12309956 | D28: 17821138 | E28: 26195935 | F28: 19926364 | G28: 29850069
B29: 2. Provision for devaluation of inventory | C29: -259792.8 | D29: -375132.3 | E29: -450506.2 | F29: -504186 | G29: -682836.5
B31: V. Other Current Asset | C31: 635867.5 | D31: 582987 | E31: 1199146.1 | F31: 894629.3 | G31: 1247261.4
... B141: TOTAL EQUITY | C141: 22822664 | D141: 28122532 | E141: 41708096 | F141: 46030880 | G141: 62971405
B144: INCOME STATEMENT
B145: Audit Committee | C145: EY | D145: EY | E145: EY | F145: EY | G145: EY
B146: Audit Opinion | C146: Unqualified opinion | D146: Unqualified opinion | E146: Unqualified opinion | F146: Unqualified opinion | G146: Unqualified opinion
B148: 1. Revenue from sale of goods and services | C148: 67698541 | D148: 87738379 | E148: 1.0348505e+08 | F148: 1.0980125e+08 | G148: 1.2414153e+08
B150: 2. Deduction | C150: 1358736.5 | D150: 1222092 | E150: 1310802.7 | F150: 1255234 | G150: 1183419.6
B152: 3. Net revenue from sale of goods and services | C152: 66339804 | D152: 86516287 | E152: 102174244 | F152: 1.0854602e+08 | G152: 1.2295811e+08
B154: 4. Costs of goods sold | C154: 55198025 | D154: 71224159 | E154: 82686445 | F154: 84591522 | G154: 95325974
B156: 5. Gross profit | C156: 11141779 | D156: 15292128 | E156: 19487799 | F156: 23954497 | G156: 27632132
B158: 6. Income from financial activities | C158: 250509.8 | D158: 342083.9 | E158: 631177.9 | F158: 794121.8 | G158: 1287956
B160: 7. Expenses from financial activities | C160: 234286.6 | D160: 436573.2 | E160: 569754.8 | F160: 594151.5 | G160: 714707.2
B161: - In which: Interest expenses | C161: 233202.3 | D161: 436416.6 | E161: 568136.7 | F161: 594003.8 | G161: 674427.7
B163: 8. Share in profits of associates | C163: 0 | D163: -2101 | E163: -3473.3 | F163: -3706.9 | G163: -2210.5
B165: 9. Selling expenses | C165: 7017061.3 | D165: 9659741.2 | E165: 12437283 | F165: 15333799 | G165: 17914173
B167: 10. General and administrative expenses | C167: 1345497.4 | D167: 1761613.9 | E167: 2073782.9 | F167: 3404431.8 | G167: 3823390.1
B169: 11. Operating profit | C169: 2795443.8 | D169: 3774182.4 | E169: 5034683.4 | F169: 5412529.9 | G169: 6465606.9
... B186: 20. Net profit after tax of parent company | C186: 2205679.6 | D186: 2878724.1 | E186: 3834269.5 | F186: 3917767.8 | G186: 4898869.3
B190: CASH FLOW STATEMENT
B191: Audit Committee | C191: EY | D191: EY | E191: EY | F191: EY | G191: EY
B192: Audit Opinion | C192: Unqualified opinion | D192: Unqualified opinion | E192: Unqualified opinion | F192: Unqualified opinion | G192: Unqualified opinion
B194: I. CASH FLOWS FROM OPERATING ACTIVITIES | C194: 2663664 | D194: 2261134.5 | E194: -1286080.8 | F194: 10792429 | G194: 171390.4
B195: 1. Net profit before tax | C195: 2809312 | D195: 3786318.6 | E195: 5053447.2 | F195: 5409735.4 | G195: 6471583.8
B196: 2. Adjustments for: | C196: 0 | D196: 0 | E196: 0 | F196: 0 | G196: 0
B197: Depreciation and amortisation | C197: 689713.7 | D197: 1222868.7 | E197: 1442826.9 | F197: 2195583.1 | G197: 2920713.6
B198: Provision for decline in value of investments | C198: 125969 | D198: 126083.6 | E198: 90495.8 | F198: 58366.7 | G198: 179550.7
B199: Gain (loss) from disposal of equity investments in other entities | C199: -35336.7 | D199: -84857.3 | E199: -341194.6 | F199: -557627.1 | G199: -959323.6
B200: Gain (loss) on foreign exchange | C200: 911.8 | D200: -107.1 | E200: -27.2 | F200: -36.9 | G200: -146.7
B201: (Gain) loss on disposal of assets | C201: 0 | D201: 0 | E201: 0 | F201: 0 | G201: 0
B202: Interest expenses | C202: 233202.3 | D202: 436416.6 | E202: 568136.7 | F202: 594003.8 | G202: 674427.7
B203: Other adjustment | C203: 0 | D203: 0 | E203: 0 | F203: 0 | G203: 0
B204: Interest income | C204: 0 | D204: 0 | E204: 0 | F204: 0 | G204: 0
B205: Goodwill amortization | C205: 0 | D205: 0 | E205: 0 | F205: 0 | G205: 0
... B241: VI. Cash and cash equivalents at the end of the period | C241: 3410983.4 | D241: 3749550.3 | E241: 3115236.8 | F241: 7347857.4 | G241: 4142015.8

Sheet ASSUMPTION
A3: Statement | B3: Assumptions | C3: Explanations | G3: 2022F | H3: 2023F | I3: 2024F | J3: 2025F | K3: 2026F
A4: INCOME STATEMENT
A5: Thegioididong.com | B5: MWG has proactively reduced the number of stores, with some being converted into Dienmayxanh. It is expected that an average of 20-30 stores will be converted each year. In 2022, an estimated 30 stores will be converted, and the Thegioididong chain will add 30 new stores. The number of new openings will gradually decrease, and by 2026, the total number of stores after conversions and new openings is expected to decrease by 25. Revenue per store (overall SSSG) is forecasted to increase by 7% in 2022, then decline to 5% in 2023, 3% in 2024, and stabilize at 1.5% in the following years. | C5: Currently, both market share and growth in the phone and laptop segments have slowed and shown signs of stagnation. If Thegioididong wants to expand, it will have to take market share from other chains, leading to intense competition. In the short term, growth will mainly come from economic recovery after the pandemic. In the mid-term, growth is expected to be driven primarily by first-time buyers and high-income customer segments. Fitch forecasts that spending on electronic devices, including PCs, audio equipment, TVs, cameras, and mobile handsets, will increase by 13.8% in value compared to the previous year. The population aged 15-64 is expected to grow at a CAGR of 0.4%. Thegioididong has also diversified its product offerings by adding watches, eyewear, and other items, which have shown strong growth. With the recovery in place, revenue growth in 2022 looks promising. Thegioididong is proactively opening new stores in high-potential locations while closing underperforming stores.
A6: Đienmayxanh | B6: This year, Dienmayxanh will open 200 more stores and take on 30 Thegioididong stores that are being converted. In the following years, new store openings will drop to an average of 80–70 for 2023 and 2024, and 50 stores for 2025–2026. Dienmayxanh’s revenue will grow by an average of 2.5% per month during 2022–2023 and 1.5% for the remaining period. | C6: According to DGW, the TV, washing machine… market currently has a scale of 2.4 billion USD. Right now, in big cities, the electronics category is almost saturated and no longer attracts as many customers as before. Meanwhile, the refrigeration segment, with products like refrigerators, is expected to recover strongly in the hot season, compared to the same period last year when shopping was affected by scattered outbreaks nationwide. Dien May Xanh Mini and Supermini are new solutions to boost revenue for MWG, using smaller store spaces to reach customers in provincial and rural areas where modern, professional retail models are still “empty.” In 2022, by continuing to open DMX Supermini (operating about 1,000 stores by the end of the year), the overall ICT and CE market is still seeing slight growth. We forecast that DMX’s revenue per store per month will increase by 2.5% in 2022 and 2023, then slow to 1.5% growth in 2024–2026 due to the industry leveling off in the long term.
A7: BLUETRONICS | B7: Open an additional 30 stores in 2022 and maintain no new openings. The overall SSG (Same-store growth) will be sustained at 5-6%. | C7: Currently, MWG has 50 stores in 13 out of 25 provinces in Cambodia. The ICT and CE markets are still very promising. However, according to the leadership, Blutronics is just a stepping stone for MWG to enter new markets in the future. Blutronics currently accounts for about half of the market's revenue, equivalent to the combined revenue of all retailers in Cambodia. Mr. Hiểu Em stated that the goal is to open an additional 30 stores to cover all 25 provinces in the neighboring country, and will stop at this number. MWG plans to expand its presence in this market and proactively maintain and grow revenue for the 80 stores in the following years.
A8: TOPZONE | B8: Open 100 new stores in 2022, reach 200 stores in 2023, and continue to open about 15–20 stores steadily in the remaining period. Revenue will hit key milestones such as 1 billion USD (over 23 trillion VND) in 2023. | C8: MWG could quickly dominate the Apple product market in Vietnam in 2022/23 thanks to the large market size of Apple products, about 34,500 billion VND, with a growth potential of around 7% per year. About 50% of the market belongs to hand-carried (grey market) products, giving MWG a big advantage in expanding its market share strongly since 2021 when stricter regulations on grey market goods were enforced. For 2022, estimated revenue is around 600 million USD. By 2023, MWG expects to reach 1 billion USD and capture 40% of the market, becoming the largest Apple distributor in the region. With two models—AAR (6–8 billion VND/month) and APPR (10–15 billion VND/month)—along with the strong "Apple" trend among Vietnamese consumers, revenue growth potential is huge. From 2023 onward, MWG has not announced further plans for TopZone, so new store openings are expected to be minimal, focusing instead on stabilizing revenue.
A9: Bachhoaxanh | B9: Open more stores aggressively starting in 2023, aiming to reach a total of 5,000 stores by 2026. The average monthly revenue per store is expected to increase by 10% in 2022, 8% in 2023, and 5% from 2024 to 2026. | C9: The retail market is very promising, with long-term growth potential and no clear market leader yet. The post-pandemic recovery has had a strong impact as workers return to their jobs and household incomes gradually recover. In 2022, MWG decided to slow down new store openings and restructure the layout and backup operations of Bách Hóa Xanh stores. This change is expected to help increase average revenue per store by 10%. However, targeting traditional markets as competitors, Bách Hóa Xanh has cut costs to lower prices on many products to match market prices. The company is also running many promotions focusing on essential goods, facing high competition from major players like MSN and Nova Consumer. As a result, in the long run, revenue growth per store is expected to decline and stabilize at 5%. With plans to expand to the North from 2023, Bách Hóa Xanh aims to reach 5,000 stores by 2026. This falls short of leadership expectations, but the Northern market is currently highly competitive, with strong competition from WinMart (MSN) and traditional markets. MSN is also aggressively expanding its minimart chains, which will pose challenges for Bách Hóa Xanh, despite its strong network advantage in the South.
A10: An Khang | B10: Opened 450 new stores in 2021, with the pace of new openings gradually slowing in the following years due to pressure from competing chains. By 2026, the total number of stores is expected to surpass 2,000. Store revenue is expected to grow strongly in 2023 and 2024, with continuous increases of 10–12%. In 2025 and 2026, growth will slow slightly to 10–8%. | C10: The pharmaceutical industry is valued at $7.4 billion, with average annual pharmaceutical spending increasing by 14%. Currently, over 95% of pharmacies in Vietnam are small retail pharmacies. After the pandemic, opportunities in the pharmaceutical sector, especially in functional foods, vitamins, etc., have expanded. This is also a suitable period for the pharmacy model to grow. An Khang has been accelerating rapidly this year and by the end of the year, it could be ranked in the top 3 in the pharmaceutical industry in terms of both revenue and the number of stores. Currently, compared to Pharmacity, this chain is targeting over 5,000 stores by 2025, and FRT aims for over 2,000 stores, competing in the large chain segment. However, the pharmaceutical market is expanding, and we expect MWG to develop 2,000 An Khang stores by 2026. With two models, An Khang combined with BHX generates a revenue of 4-500 million VND per store per month, and in the independent model, it generates 700-800 million VND per store per month. We expect the average revenue per store per month in 2022 to be around 500 million VND. With a portfolio that balances both pharmaceutical and non-pharmaceutical products, the two chains are still relatively new. Additionally, An Khang has made many strategic changes, including redefining its business model, redesigning store layouts, restructuring product categories, and launching a new website. It is expected that the revenue of this chain will continue to grow in the future and may reach an average of 732 million VND per store per month.
A11: COGS (Gross profit) | B11: Overall, the gross profit margin started to increase by 0.28% from 2022, thanks to the recovery of consumer electronics, specifically from Điện Máy Xanh and Bluetronics, along with the long-term market share growth of Apple through 2026. The gross profit margin could reach nearly 23%. | C11: The pharmaceutical industry is valued at $7.4 billion, with pharmaceutical spending growing at an average of 14% per year. Currently, over 95% of pharmacies in Vietnam are small independent stores. After the pandemic, opportunities in the pharmaceutical sector have expanded, especially for functional foods, vitamins, and supplements. This is also the right time for pharmacy chains to grow. An Khang is expanding rapidly this year and could rank in the top 3 of the pharmaceutical sector by year-end in terms of both revenue and store count. Currently competing with Pharmacity—which aims to reach over 5,000 stores by 2025—and FRT, which targets over 2,000 stores, the race to expand large chains is fierce. However, the pharmaceutical market remains wide open, and we expect MWG to develop 2,000 An Khang stores by 2026. With two models—An Khang combined with Bách Hóa Xanh (generating 400–500 million VND per month) and standalone stores (700–800 million VND per month)—we estimate the average monthly revenue per store in 2022 to be 500 million VND. By balancing its product mix between medicines and non-medicine items better than its two main competitors, An Khang is also making significant strategic changes, reshaping its business model, redesigning store layouts, restructuring its product portfolio, and launching a new website. As a result, the chain’s revenue is expected to continue growing in the future, potentially reaching an average of 732 million VND per store per month.
A16: COGS/Net Revenue | B16: 14% in 2022, then gradually stabilizing at 13.5%. | C16: The business is operating stably, but the scale expansion is not growing as fast as costs.
A17: SG&A/Net revenue | B17: Declining from 3.4% to 3.1% during 2022–2026.
A18: Other revenue | B18: Average of the last two years.
A20: Financial Income | B20: There is growth due to the efficiency of short-term financial investments.
A21: Financial Expense | B21: The average rate follows previous years.
A22: Interest rate | B22: It increases over the years as MWG maintains short-term debt to support working capital needs.
A24: Other Income
A25: Other Income/Net Revenue | B25: Average of the last two years.
A26: Other Expense
A27: Other Expense/ Net Revenue | B27: Average of the last two years.
A29: BALANCE SHEET
A31: Current Assets
A32: Average Receivable Turnover | B32: There is an improvement compared to 2021, thanks to post-pandemic recovery. In the following years, it will remain at an average level.
A33: Average Day Sales of Inventory
B34: Maintained at 3.7–3.8 days during the 2022–2026 period.
A35: Advanced payments to suppliers/Net Revenue | B35: Equal to the 2021 rate.
A36: Other Receivables/Net Revenue | B36: The average of 2021 and 2020.
A38: Non-current Assets
A39: Tangible Fixed Assets | B39: New equipment and office purchases increase in line with revenue and store count.
A40: Completed Capital Construction Investment | B40: Construction in progress is transitioned to completion.
A41: Intangible Fixed Assets | B41: New purchases remain similar to 2021 and 2020.
A42: Construction in Progress | B42: Increase in line with the pace of new store openings.
A43: Depreciation of Tangible Fixed Assets | B43: Depreciation rate matches the 2021 average.
A44: Depreciation of Intangible Fixed Assets | B44: Depreciation rate is presented in the financial statements.
A45: Goodwill | B45: Depreciation follows the regulated rate.
A47: Short-term Debt
A48: Average Accounts Payable Turnover | B48: Maintained at the three-year average from 2019–2021.
A49: Deferred Revenue/Net Revenue | B49: Remains at 0.8% each year, so this rate is expected to stay unchanged.
A50: Taxes and other Payables to the State Budget/Net Revenue | B50: Equal 2021
A51: Payables to Employees/COGS | B51: Increases steadily by 0.01% per year due to macroeconomic factors post-pandemic and workforce expansion in new chains.
A52: Short-term Payables/COGS | B52: Average of the last two years.
A54: Short-term Borrowings
A55: Additional Borrowing | B55: Additional borrowing for working capital needs (based on the ratio of new inventory purchases during the year).
A56: Debt Payments | B56: Short-term debt repayment is carried out annually (aligned with the ratio of purchases and cost of goods sold).
A57: Interest Rate | B57: Compared to the average unsecured loan interest rate in 2021, there is an upward adjustment due to signs of increasing lending rates.
A59: Additional Long-term Borrowings
A60: Additional Borrowings | B60: No new long-term borrowing. In 2021, the company also no longer had any long-term debt.
A63: Owners' Equity
A64: Capital Issuance | B64: Issuing shares to pay dividends at a 1:1 ratio, with the issuance closing in June 2022, and no capital increase assumed for the following year.
A65: ESOP | B65: Issuing 19.22 million ESOP shares for employees in March 2022.
A66: Cash Dividends | B66: Paying a 10% dividend using retained earnings. | C66: MWG has been paying cash dividends quite regularly in the past, and it is expected that in the coming years, MWG will maintain the same dividend rate.
A68: WACC
A69: Risk Free rate | B69: The current yield on 10-year Vietnamese government bonds on HNX.VN
A70: Risk Premium | B70: The risk premium of the Vietnamese market according to Professor Damodaran's opinion.
A71: Tax Rate | B71: The effective tax rate of the Group.

Sheet DCF
A2: The end of fiscal year | B2: 44561
A3: Valuation date | B3: 44718
A4: Year proportion | B4: =1-(B3-B2)/365 -> 0.56986301
A5: WACC | B5: =C19 -> 0.088370364
A6: Long-term growth rate | B6: 0.02
A9: WACC | C9: 2022
A10: Risk free rate | C10: 0.04
A11: Unleveraged Beta | C11: =Beta!I8 -> 0.50223651
A12: D/E | C12: =(BS!G75+BS!G86)/BS!G92 -> 1.2094993
A13: Tax rate | C13: =IS!G41 -> 0.013408104
A14: Forecasted leveraged beta | C14: =C11*(1+(1-C13)*C12) -> 1.1015464
A15: Risk premium | C15: 0.0821
A16: Cost of equity | C16: =C10+C15*C14 -> 0.13043696
A17: Interest rate | C17: ='FI&FE'!G11 -> 0.035
A18: D/(D+E) | C18: =(BS!H75/(BS!H75+BS!H92)) -> 0.43862208
A19: WACC | C19: =C16*(1-C18)+C17*C18*(1-C13) -> 0.088370364
A21: FCFF VALUATION METHOD
A23: FCFF | C23: 2022 | D23: 2023 | E23: 2024 | F23: 2025 | G23: 2026
A24: Operating profit | C24: =IS!G18 -> 6654885.6 | D24: =IS!H18 -> 8282167.8 | E24: =IS!I18 -> 10756201 | F24: =IS!J18 -> 12949266 | G24: =IS!K18 -> 14532889
A25: Depreciation | C25: =CF!G5 -> 3323046.8 | D25: =CF!H5 -> 4045858.9 | E25: =CF!I5 -> 4995898.7 | F25: =CF!J5 -> 6130873 | G25: =CF!K5 -> 7442515.6
A26: Interest rate after tax shield | C26: =IS!G7*(1-20%) -> 714965.38 | D26: =IS!H7*(1-20%) -> 760235.14 | E26: =IS!I7*(1-20%) -> 874379.52 | F26: =IS!J7*(1-20%) -> 851920.36 | G26: =IS!K7*(1-20%) -> 967668.99
A27: CAPEX | C27: =(BS!G37+BS!G43+BS!G50)-(BS!H37+BS!H43+BS!H50) -> -6437268.3 | D27: =(BS!H37+BS!H43+BS!H50)-(BS!I37+BS!I43+BS!I50) -> -7928378.5 | E27: =(BS!I37+BS!I43+BS!I50)-(BS!J37+BS!J43+BS!J50) -> -9038857.8 | F27: =(BS!J37+BS!J43+BS!J50)-(BS!K37+BS!K43+BS!K50) -> -10034881 | G27: =(BS!K37+BS!K43+BS!K50)-(BS!L37+BS!L43+BS!L50) -> -11151571
A28: Net working capital | C28: =BS!H153 -> 2078760.3 | D28: =BS!I153 -> 5694044.5 | E28: =BS!J153 -> 3394205.3 | F28: =BS!K153 -> 3770441.3 | G28: =BS!L153 -> 4232838.5
A29: FCFF | C29: =SUM(C24:C28) -> 6334389.8 | D29: =SUM(D24:D28) -> 10853928 | E29: =SUM(E24:E28) -> 10981827 | F29: =SUM(F24:F28) -> 13667620 | G29: =SUM(G24:G28) -> 16024341
A30: Mid point | C30: =B4 -> 0.56986301 | D30: =1+C30 -> 1.569863 | E30: =1+D30 -> 2.569863 | F30: =1+E30 -> 3.569863 | G30: =1+F30 -> 4.569863
A31: Discount Factor | C31: =1/((1+$B$5)^C30) -> 0.952889 | D31: =1/((1+$B$5)^D30) -> 0.87551906 | E31: =1/((1+$B$5)^E30) -> 0.80443119 | F31: =1/((1+$B$5)^F30) -> 0.7391153 | G31: =1/((1+$B$5)^G30) -> 0.67910274
A32: PV of FCFF | C32: =C31*C29 -> 6035970.4 | D32: =D31*D29 -> 9502820.8 | E32: =E31*E29 -> 8834124.1 | F32: =F31*F29 -> 10101947 | G32: =G31*G29 -> 10882174
A33: Accumalated PV of FCFF | B33: =SUM(C32:G32) -> 45357036
A34: Terminal Value | B34: =G32*(1-B6)/(B5-B6) -> 1.5598178e+08
A35: PV of Terminal Value | B35: =B34*G31 -> 1.0592765e+08
A36: Corporate value | B36: =B33+B35 -> 1.5128469e+08
A37: Cash | B37: =BS!G3 -> 4142015.8
A38: Debt | B38: =BS!G75 -> 24647474
A39: Owners' equity value | B39: =B36+B37-B38 -> 1.3077923e+08
A40: Number of shares | B40: 731854815
A41: Price | B41: =(B39*10^6)/B40 -> 178695.59

Sheet Financial Ratios
B1: 2017A | C1: 2018A | D1: 2019A | E1: 2020A | F1: 2021A | G1: 2022F | H1: 2023F | I1: 2024F | J1: 2025F | K1: 2026F
A2: LIQUIDITY RATIO
A3: Current ratio | B3: =BS!C2/BS!C65 -> 1.2003999 | C3: =BS!D2/BS!D65 -> 1.3035546 | D3: =BS!E2/BS!E65 -> 1.2309769 | E3: =BS!F2/BS!F65 -> 1.2683224 | F3: =BS!G2/BS!G65 -> 1.2198029 | G3: =BS!H2/BS!H65 -> 1.4021085 | H3: =BS!I2/BS!I65 -> 1.4037031 | I3: =BS!J2/BS!J65 -> 1.4561796 | ... K3: =BS!L2/BS!L65 -> 1.5874353
A4: Quick ratio | B4: =(BS!C2-BS!C17)/BS!C65 -> 0.43354835 | C4: =(BS!D2-BS!D17)/BS!D65 -> 0.3305174 | D4: =(BS!E2-BS!E17)/BS!E65 -> 0.32579808 | E4: =(BS!F2-BS!F17)/BS!F65 -> 0.60820965 | F4: =(BS!G2-BS!G17)/BS!G65 -> 0.5350161 | G4: =(BS!H2-BS!H17)/BS!H65 -> 0.71443956 | H4: =(BS!I2-BS!I17)/BS!I65 -> 0.65622797 | I4: =(BS!J2-BS!J17)/BS!J65 -> 0.71745601 | ... K4: =(BS!L2-BS!L17)/BS!L65 -> 0.84783809
A5: Cash Ratio | B5: =BS!C3/BS!C65 -> 0.21706908 | C5: =BS!D3/BS!D65 -> 0.20912821 | D5: =BS!E3/BS!E65 -> 0.10952804 | E5: =BS!F3/BS!F65 -> 0.24973588 | F5: =BS!G3/BS!G65 -> 0.097246035 | G5: =BS!H3/BS!H65 -> 0.31200993 | H5: =BS!I3/BS!I65 -> 0.27722135 | I5: =BS!J3/BS!J65 -> 0.35609338 | ... K5: =BS!L3/BS!L65 -> 0.53435515
A7: SOLVENCY RATIO
A8: (D+E)/E | B8: =BS!C114/BS!C92 -> 3.8624111 | C8: =BS!D114/BS!D92 -> 3.1306268 | D8: =BS!E114/BS!E92 -> 3.4345764 | E8: =BS!F114/BS!F92 -> 2.9732465 | F8: =BS!G114/BS!G92 -> 3.0901288 | G8: =BS!H114/BS!H92 -> 2.4398461 | H8: =BS!I114/BS!I92 -> 2.3647526 | I8: =BS!J114/BS!J92 -> 2.2093072 | ... K8: =BS!L114/BS!L92 -> 2.0123962
A9: Interest Coverage Ratio | B9: =(IS!B15+IS!B7)/IS!B7 -> 13.046674 | C9: =(IS!C15+IS!C7)/IS!C7 -> 9.6759271 | D9: =(IS!D15+IS!D7)/IS!D7 -> 9.8947734 | E9: =(IS!E15+IS!E7)/IS!E7 -> 10.10724 | F9: =(IS!F15+IS!F7)/IS!F7 -> 10.595667 | G9: =(IS!G15+IS!G7)/IS!G7 -> 10.612011 | H9: =(IS!H15+IS!H7)/IS!H7 -> 12.326784 | I9: =(IS!I15+IS!I7)/IS!I7 -> 13.357442 | ... K9: =(IS!K15+IS!K7)/IS!K7 -> 15.878481
A10: Cash Coverage Ratio | B10: =(IS!B15+IS!B7+CF!B5)/IS!B7 -> 16.00425 | C10: =(IS!C15+IS!C7+CF!C5)/IS!C7 -> 12.477994 | D10: =(IS!D15+IS!D7+CF!D5)/IS!D7 -> 12.43435 | E10: =(IS!E15+IS!E7+CF!E5)/IS!E7 -> 13.803485 | F10: =(IS!F15+IS!F7+CF!F5)/IS!F7 -> 14.926322 | G10: =(IS!G15+IS!G7+CF!G5)/IS!G7 -> 14.330286 | H10: =(IS!H15+IS!H7+CF!H5)/IS!H7 -> 16.584265 | I10: =(IS!I15+IS!I7+CF!I5)/IS!I7 -> 17.928363 | ... K10: =(IS!K15+IS!K7+CF!K5)/IS!K7 -> 22.031424
A12: ASSET MANAGEMENT RATIO
A13: Inventory Turnover | C13: =IS!C3/AVERAGE(BS!C17:D17) -> 4.8293839 | D13: =IS!D3/AVERAGE(BS!D17:E17) -> 3.8288354 | E13: =IS!E3/AVERAGE(BS!E17:F17) -> 3.7456722 | F13: =IS!F3/AVERAGE(BS!F17:G17) -> 3.9237346 | G13: =IS!G3/AVERAGE(BS!G17:H17) -> 3.7755055 | H13: =IS!H3/AVERAGE(BS!H17:I17) -> 3.8955772 | I13: =IS!I3/AVERAGE(BS!I17:J17) -> 3.8554166 | J13: =IS!J3/AVERAGE(BS!J17:K17) -> 3.8356452 | K13: =IS!K3/AVERAGE(BS!K17:L17) -> 3.8160756
A14: Days of inventory on hand (DOH) | C14: =365/C13 -> 75.578999 | D14: =365/D13 -> 95.329249 | E14: =365/E13 -> 97.445794 | F14: =365/F13 -> 93.023621 | G14: =365/G13 -> 96.675795 | H14: =365/H13 -> 93.696 | I14: =365/I13 -> 94.672 | J14: =365/J13 -> 95.16 | K14: =365/K13 -> 95.648
A15: Receivables Turnover | C15: =IS!C2/AVERAGE(BS!C8:D8) -> 40.161888 | D15: =IS!D2/AVERAGE(BS!D8:E8) -> 60.861198 | E15: =IS!E2/AVERAGE(BS!E8:F8) -> 63.657071 | F15: =IS!F2/AVERAGE(BS!F8:G8) -> 51.691598 | G15: =IS!G2/AVERAGE(BS!G8:H8) -> 43.87851 | H15: =IS!H2/AVERAGE(BS!H8:I8) -> 43.403416 | I15: =IS!I2/AVERAGE(BS!I8:J8) -> 41.782853 | J15: =IS!J2/AVERAGE(BS!J8:K8) -> 41.198987 | K15: =IS!K2/AVERAGE(BS!K8:L8) -> 41.205447
A16: Average Collection Period | C16: =365/C15 -> 9.0882182 | D16: =365/D15 -> 5.997253 | E16: =365/E15 -> 5.7338485 | F16: =365/F15 -> 7.0611089 | G16: =365/G15 -> 8.3184229 | H16: =365/H15 -> 8.4094763 | I16: =365/I15 -> 8.7356409 | J16: =365/J15 -> 8.8594412 | K16: =365/K15 -> 8.8580523
A17: Payable Turnover | C17: =(IS!C3+BS!D17-BS!C17)/AVERAGE(BS!C66:D66) -> 9.811854 | D17: =(IS!D3+BS!E17-BS!D17)/AVERAGE(BS!D66:E66) -> 8.964125 | E17: =(IS!E3+BS!F17-BS!E17)/AVERAGE(BS!E66:F66) -> 7.5317503 | F17: =(IS!F3+BS!G17-BS!F17)/AVERAGE(BS!F66:G66) -> 10.050824 | G17: =(IS!G3+BS!H17-BS!G17)/AVERAGE(BS!G66:H66) -> 8.9752952 | H17: =(IS!H3+BS!I17-BS!H17)/AVERAGE(BS!H66:I66) -> 9.0976918 | I17: =(IS!I3+BS!J17-BS!I17)/AVERAGE(BS!I66:J66) -> 8.9442071 | J17: =(IS!J3+BS!K17-BS!J17)/AVERAGE(BS!J66:K66) -> 8.9943267 | K17: =(IS!K3+BS!L17-BS!K17)/AVERAGE(BS!K66:L66) -> 8.8012227
A18: Average Collection Period | C18: =365/C17 -> 37.199901 | D18: =365/D17 -> 40.717861 | E18: =365/E17 -> 48.461511 | F18: =365/F17 -> 36.315431 | G18: =365/G17 -> 40.667186 | H18: =365/H17 -> 40.120067 | I18: =365/I17 -> 40.808536 | J18: =365/J17 -> 40.581137 | K18: =365/K17 -> 41.471511
A19: Assets Turnover | C19: =IS!C2/AVERAGE(BS!C63:D63) -> 3.3964454 | D19: =IS!D2/AVERAGE(BS!D63:E63) -> 2.9263447 | E19: =IS!E2/AVERAGE(BS!E63:F63) -> 2.4742942 | F19: =IS!F2/AVERAGE(BS!F63:G63) -> 2.2560647 | G19: =IS!G2/AVERAGE(BS!G63:H63) -> 2.1029668 | H19: =IS!H2/AVERAGE(BS!H63:I63) -> 2.109867 | I19: =IS!I2/AVERAGE(BS!I63:J63) -> 2.0814815 | J19: =IS!J2/AVERAGE(BS!J63:K63) -> 2.0652429 | K19: =IS!K2/AVERAGE(BS!K63:L63) -> 1.9620484
A21: PROFITABILITY RATIO
A22: Gross Profit Margin | B22: =IS!B4/IS!B2 -> 0.16795014 | C22: =IS!C4/IS!C2 -> 0.17675432 | D22: =IS!D4/IS!D2 -> 0.19073103 | E22: =IS!E4/IS!E2 -> 0.22068517 | F22: =IS!F4/IS!F2 -> 0.22472802 | G22: =IS!G4/IS!G2 -> 0.22684463 | H22: =IS!H4/IS!H2 -> 0.22531397 | I22: =IS!I4/IS!I2 -> 0.22772596 | ... K22: =IS!K4/IS!K2 -> 0.23125549
A23: Operating Profit Margin | B23: =IS!B11/IS!B2 -> 0.042138258 | C23: =IS!C11/IS!C2 -> 0.043623953 | D23: =IS!D11/IS!D2 -> 0.049275465 | E23: =IS!E11/IS!E2 -> 0.049863919 | F23: =IS!F11/IS!F2 -> 0.05258382 | G23: =IS!G11/IS!G2 -> 0.056146611 | H23: =IS!H11/IS!H2 -> 0.057101041 | I23: =IS!I11/IS!I2 -> 0.062859005 | ... K23: =IS!K11/IS!K2 -> 0.067234365
A24: Net Profit Margin | B24: =IS!B18/IS!B2 -> 0.03326656 | C24: =IS!C18/IS!C2 -> 0.033292103 | D24: =IS!D18/IS!D2 -> 0.037546058 | E24: =IS!E18/IS!E2 -> 0.036112542 | F24: =IS!F18/IS!F2 -> 0.039862575 | G24: =IS!G18/IS!G2 -> 0.043505409 | H24: =IS!H18/IS!H2 -> 0.043959399 | I24: =IS!I18/IS!I2 -> 0.050076158 | ... K24: =IS!K18/IS!K2 -> 0.054312114
A25: EBIT Margin | B25: =(IS!B15+IS!B7)/IS!B2 -> 0.045862576 | C25: =(IS!C15+IS!C7)/IS!C2 -> 0.048808558 | D25: =(IS!D15+IS!D7)/IS!D2 -> 0.055019579 | E25: =(IS!E15+IS!E7)/IS!E2 -> 0.055310542 | F25: =(IS!F15+IS!F7)/IS!F2 -> 0.058117449 | G25: =(IS!G15+IS!G7)/IS!G2 -> 0.062000528 | H25: =(IS!H15+IS!H7)/IS!H2 -> 0.062174951 | I25: =(IS!I15+IS!I7)/IS!I2 -> 0.06796814 | ... K25: =(IS!K15+IS!K7)/IS!K2 -> 0.071777864
A26: EBITDA Margin | B26: =(IS!B15+IS!B7+CF!B5)/IS!B2 -> 0.056259256 | C26: =(IS!C15+IS!C7+CF!C5)/IS!C2 -> 0.062943107 | D26: =(IS!D15+IS!D7+CF!D5)/IS!D2 -> 0.069140818 | E26: =(IS!E15+IS!E7+CF!E5)/IS!E2 -> 0.075537752 | F26: =(IS!F15+IS!F7+CF!F5)/IS!F2 -> 0.081871179 | G26: =(IS!G15+IS!G7+CF!G5)/IS!G2 -> 0.083724495 | H26: =(IS!H15+IS!H7+CF!H5)/IS!H2 -> 0.083649224 | I26: =(IS!I15+IS!I7+CF!I5)/IS!I2 -> 0.091226855 | ... K26: =(IS!K15+IS!K7+CF!K5)/IS!K2 -> 0.099591931
A27: ROA | B27: =IS!B18/BS!C63 -> 0.096697611 | C27: =IS!C18/BS!D63 -> 0.10241998 | D27: =IS!D18/BS!E63 -> 0.091978309 | E27: =IS!E18/BS!F63 -> 0.085157457 | F27: =IS!F18/BS!G63 -> 0.077835753 | G27: =IS!G18/BS!H63 -> 0.080659617 | H27: =IS!H18/BS!I63 -> 0.086193264 | I27: =IS!I18/BS!J63 -> 0.097517613 | ... K27: =IS!K18/BS!L63 -> 0.096963742
A28: ROE | B28: =IS!B18/BS!C92 -> 0.37348593 | C28: =IS!C18/BS!D92 -> 0.32063874 | D28: =IS!D18/BS!E92 -> 0.31590653 | E28: =IS!E18/BS!F92 -> 0.25319411 | F28: =IS!F18/BS!G92 -> 0.2405225 | G28: =IS!G18/BS!H92 -> 0.19679705 | H28: =IS!H18/BS!I92 -> 0.20382575 | I28: =IS!I18/BS!J92 -> 0.21544637 | ... K28: =IS!K18/BS!L92 -> 0.19512947
A29: ROAA | C29: =IS!C18/AVERAGE(BS!C63:D63) -> 0.11307481 | D29: =IS!D18/AVERAGE(BS!D63:E63) -> 0.10987271 | E29: =IS!E18/AVERAGE(BS!E63:F63) -> 0.089353054 | F29: =IS!F18/AVERAGE(BS!F63:G63) -> 0.08993255 | G29: =IS!G18/AVERAGE(BS!G63:H63) -> 0.091490429 | H29: =IS!H18/AVERAGE(BS!H63:I63) -> 0.092748487 | I29: =IS!I18/AVERAGE(BS!I63:J63) -> 0.1042326 | J29: =IS!J18/AVERAGE(BS!J63:K63) -> 0.11106801 | K29: =IS!K18/AVERAGE(BS!K63:L63) -> 0.106563
A30: ROEA | C30: =IS!C18/AVERAGE(BS!C92:D92) -> 0.38682762 | D30: =IS!D18/AVERAGE(BS!D92:E92) -> 0.36316635 | E30: =IS!E18/AVERAGE(BS!E92:F92) -> 0.28378879 | F30: =IS!F18/AVERAGE(BS!F92:G92) -> 0.27336506 | G30: =IS!G18/AVERAGE(BS!G92:H92) -> 0.24559389 | H30: =IS!H18/AVERAGE(BS!H92:I92) -> 0.22249074 | I30: =IS!I18/AVERAGE(BS!I92:J92) -> 0.23755186 | J30: =IS!J18/AVERAGE(BS!J92:K92) -> 0.23261791 | K30: =IS!K18/AVERAGE(BS!K92:L92) -> 0.213895
A31: ROIC (CFA) | B31: =((IS!B15+IS!B7)*(1-(1-IS!B18/IS!B15)))/(BS!C92+BS!C75+BS!C86-BS!C3) -> 0.2569613 | C31: =((IS!C15+IS!C7)*(1-(1-IS!C18/IS!C15)))/(BS!D92+BS!D75+BS!D86-BS!D3) -> 0.2616281 | D31: =((IS!D15+IS!D7)*(1-(1-IS!D18/IS!D15)))/(BS!E92+BS!E75+BS!E86-BS!E3) -> 0.18409206 | E31: =((IS!E15+IS!E7)*(1-(1-IS!E18/IS!E15)))/(BS!F92+BS!F75+BS!F86-BS!F3) -> 0.17481073 | F31: =((IS!F15+IS!F7)*(1-(1-IS!F18/IS!F15)))/(BS!G92+BS!G75+BS!G86-BS!G3) -> 0.13238092 | G31: =((IS!G15+IS!G7)*(1-(1-IS!G18/IS!G15)))/(BS!H92+BS!H75+BS!H86-BS!H3) -> 0.16310607 | H31: =((IS!H15+IS!H7)*(1-(1-IS!H18/IS!H15)))/(BS!I92+BS!I75+BS!I86-BS!I3) -> 0.16961123 | I31: =((IS!I15+IS!I7)*(1-(1-IS!I18/IS!I15)))/(BS!J92+BS!J75+BS!J86-BS!J3) -> 0.19499658 | ... K31: =((IS!K15+IS!K7)*(1-(1-IS!K18/IS!K15)))/(BS!L92+BS!L75+BS!L86-BS!L3) -> 0.21186162
A33: MARKET VALUE RATIO
A34: EPS | E34: =IS!E23 -> 5675.7904 | F34: =IS!F23 -> 6896.7094 | G34: =IS!G23 -> 4544.4885 | H34: =IS!H23 -> 5655.7088 | I34: =IS!I23 -> 7345.6147 | J34: =IS!J23 -> 8843.5324 | K34: =IS!K23 -> 9925.0923
A36: GROWTH RATIO
A37: Operationg Profit Growth Rate | C37: =SALE!C53 -> 0.30413841 | D37: =SALE!D53 -> 0.18098277 | E37: =SALE!E53 -> 0.062361858 | F37: =SALE!F53 -> 0.13277397 | G37: =SALE!G53 -> 0.24405669 | H37: =SALE!H53 -> 0.23167163 | I37: =SALE!I53 -> 0.14008082 | J37: =SALE!J53 -> 0.12098384 | K37: =SALE!K53 -> 0.11129149
A38: Gross Profit Margin Growth Rate | C38: =IS!C4/IS!B4-1 -> 0.37250321 | D38: =IS!D4/IS!C4-1 -> 0.27436806 | E38: =IS!E4/IS!D4-1 -> 0.22920484 | F38: =IS!F4/IS!E4-1 -> 0.15352586 | G38: =IS!G4/IS!F4-1 -> 0.25577385 | H38: =IS!H4/IS!G4-1 -> 0.22336081 | I38: =IS!I4/IS!H4-1 -> 0.1522854 | J38: =IS!J4/IS!I4-1 -> 0.13345114 | K38: =IS!K4/IS!J4-1 -> 0.11610242
A39: EBIT Growth Rate | C39: =IS!C15/IS!B15-1 -> 0.34777433 | D39: =IS!D15/IS!C15-1 -> 0.33465979 | E39: =IS!E15/IS!D15-1 -> 0.070503992 | F39: =IS!F15/IS!E15-1 -> 0.19628472 | G39: =IS!G15/IS!F15-1 -> 0.32739053 | H39: =IS!H15/IS!G15-1 -> 0.2530121 | I39: =IS!I15/IS!H15-1 -> 0.2547986 | J39: =IS!J15/IS!I15-1 -> 0.18884279 | K39: =IS!K15/IS!J15-1 -> 0.12081107
A40: EAT Growth Rate | C40: =IS!C18/IS!B18-1 -> 0.30513974 | D40: =IS!D18/IS!C18-1 -> 0.33188487 | E40: =IS!E18/IS!D18-1 -> 0.021800669 | F40: =IS!F18/IS!E18-1 -> 0.25040456 | G40: =IS!G18/IS!F18-1 -> 0.35774459 | H40: =IS!H18/IS!G18-1 -> 0.24452445 | I40: =IS!I18/IS!H18-1 -> 0.2987181 | J40: =IS!J18/IS!I18-1 -> 0.20388838 | K40: =IS!K18/IS!J18-1 -> 0.12229446
A41: Total Assets Growth Rate | C41: =BS!D63/BS!C63-1 -> 0.23221948 | D41: =BS!E63/BS!D63-1 -> 0.48308468 | E41: =BS!F63/BS!E63-1 -> 0.10364378 | F41: =BS!G63/BS!F63-1 -> 0.36802522 | G41: =BS!H63/BS!G63-1 -> 0.31021043 | H41: =BS!I63/BS!H63-1 -> 0.16462541 | I41: =BS!J63/BS!I63-1 -> 0.14790292 | J41: =BS!K63/BS!J63-1 -> 0.11402576 | K41: =BS!L63/BS!K63-1 -> 0.21975191
A42: Short-term Debt Growth Rate | C42: =BS!D65/BS!C65-1 -> 0.1409981 | D42: =BS!E65/BS!D65-1 -> 0.58635059 | E42: =BS!F65/BS!E65-1 -> 0.0344608 | F42: =BS!G65/BS!F65-1 -> 0.44763835 | G42: =BS!H65/BS!G65-1 -> 0.14313686 | H42: =BS!I65/BS!H65-1 -> 0.13893998 | I42: =BS!J65/BS!I65-1 -> 0.088723188 | J42: =BS!K65/BS!J65-1 -> 0.018093034 | K42: =BS!L65/BS!K65-1 -> 0.22669264
A43: Debt Growth Rate | C43: =BS!D64/BS!C64-1 -> 0.13159403 | D43: =BS!E64/BS!D64-1 -> 0.54468556 | E43: =BS!F64/BS!E64-1 -> 0.033306384 | F43: =BS!G64/BS!F64-1 -> 0.39424838 | G43: =BS!H64/BS!G64-1 -> 0.14313686 | H43: =BS!I64/BS!H64-1 -> 0.13893998 | I43: =BS!J64/BS!I64-1 -> 0.088723188 | J43: =BS!K64/BS!J64-1 -> 0.018093034 | K43: =BS!L64/BS!K64-1 -> 0.22669264
A44: Equity Growth Rate | C44: =BS!D92/BS!C92-1 -> 0.5202509 | D44: =BS!E92/BS!D92-1 -> 0.35183619 | E44: =BS!F92/BS!E92-1 -> 0.27488552 | F44: =BS!G92/BS!F92-1 -> 0.31628047 | G44: =BS!H92/BS!G92-1 -> 0.65941572 | H44: =BS!I92/BS!H92-1 -> 0.20160847 | I44: =BS!J92/BS!I92-1 -> 0.2286686 | J44: =BS!K92/BS!J92-1 -> 0.2300379 | K44: =BS!L92/BS!K92-1 -> 0.21280468
A46: FINANCIAL LEVERAGE GROWTH RATIO
A47: Short-term Debt/Total Debt | B47: =BS!C65/BS!C64 -> 0.92905576 | C47: =BS!D65/BS!D64 -> 0.93677664 | D47: =BS!E65/BS!E64 -> 0.96204446 | E47: =BS!F65/BS!F64 -> 0.96311926 | F47: =BS!G65/BS!G64 -> 1 | G47: =BS!H65/BS!H64 -> 1 | H47: =BS!I65/BS!I64 -> 1 | I47: =BS!J65/BS!J64 -> 1 | ... K47: =BS!L65/BS!L64 -> 1
A48: Borrowings/Total Assets | B48: =(BS!C86+BS!C75)/BS!C64 -> 0.40224314 | C48: =(BS!D86+BS!D75)/BS!D64 -> 0.36806725 | D48: =(BS!E86+BS!E75)/BS!E64 -> 0.47872112 | E48: =(BS!F86+BS!F75)/BS!F64 -> 0.54835683 | F48: =(BS!G86+BS!G75)/BS!G64 -> 0.57867214 | G48: =(BS!H86+BS!H75)/BS!H64 -> 0.5426491 | H48: =(BS!I86+BS!I75)/BS!I64 -> 0.50277059 | I48: =(BS!J86+BS!J75)/BS!J64 -> 0.51674903 | ... K48: =(BS!L86+BS!L75)/BS!L64 -> 0.51749044
A49: D/A | B49: =BS!C64/BS!C63 -> 0.74109437 | C49: =BS!D64/BS!D63 -> 0.68057515 | D49: =BS!E64/BS!E63 -> 0.70884328 | E49: =BS!F64/BS!F63 -> 0.66366731 | F49: =BS!G64/BS!G63 -> 0.67638889 | G49: =BS!H64/BS!H63 -> 0.59013809 | H49: =BS!I64/BS!I63 -> 0.57712279 | I49: =BS!J64/BS!J63 -> 0.54736943 | ... K49: =BS!L64/BS!L63 -> 0.50307997
A50: E/A | B50: =BS!C92/BS!C63 -> 0.25890563 | C50: =BS!D92/BS!D63 -> 0.31942485 | D50: =BS!E92/BS!E63 -> 0.29115672 | E50: =BS!F92/BS!F63 -> 0.33633269 | F50: =BS!G92/BS!G63 -> 0.32361111 | G50: =BS!H92/BS!H63 -> 0.40986191 | H50: =BS!I92/BS!I63 -> 0.42287721 | I50: =BS!J92/BS!J63 -> 0.45263057 | ... K50: =BS!L92/BS!L63 -> 0.49692003
A51: Short-term Debt/Equity | B51: =BS!C65/BS!C92 -> 2.6593396 | C51: =BS!D65/BS!D92 -> 1.9959215 | D51: =BS!E65/BS!E92 -> 2.3421708 | E51: =BS!F65/BS!F92 -> 1.9004717 | F51: =BS!G65/BS!G92 -> 2.0901288 | G51: =BS!H65/BS!H92 -> 1.4398461 | H51: =BS!I65/BS!I92 -> 1.3647526 | I51: =BS!J65/BS!J92 -> 1.2093072 | ... K51: =BS!L65/BS!L92 -> 1.0123962
A52: Borrowings/Equity | B52: =(BS!C86+BS!C75)/BS!C92 -> 1.1513852 | C52: =(BS!D86+BS!D75)/BS!D92 -> 0.78421396 | D52: =(BS!E86+BS!E75)/BS!E92 -> 1.1654832 | E52: =(BS!F86+BS!F75)/BS!F92 -> 1.0820432 | F52: =(BS!G86+BS!G75)/BS!G92 -> 1.2094993 | G52: =(BS!H86+BS!H75)/BS!H92 -> 0.7813312 | H52: =(BS!I86+BS!I75)/BS!I92 -> 0.68615748 | I52: =(BS!J86+BS!J75)/BS!J92 -> 0.62490834 | ... K52: =(BS!L86+BS!L75)/BS!L92 -> 0.52390536
A53: Short-term Debt/Equity | B53: =BS!C64/BS!C92 -> 2.8624111 | C53: =BS!D64/BS!D92 -> 2.1306268 | D53: =BS!E64/BS!E92 -> 2.4345764 | E53: =BS!F64/BS!F92 -> 1.9732465 | F53: =BS!G64/BS!G92 -> 2.0901288 | G53: =BS!H64/BS!H92 -> 1.4398461 | H53: =BS!I64/BS!I92 -> 1.3647526 | I53: =BS!J64/BS!J92 -> 1.2093072 | ... K53: =BS!L64/BS!L92 -> 1.0123962
A55: CASHFLOW RATIO
A56: Cashflow from Operating/Net Revenue | B56: =CF!B10/IS!B2 -> 0.040151822 | C56: =CF!C10/IS!C2 -> 0.026135362 | D56: =CF!D10/IS!D2 -> -0.012587133 | E56: =CF!E10/IS!E2 -> 0.099427222 | F56: =CF!F10/IS!F2 -> 0.0013938926 | G56: =CF!G10/IS!G2 -> 0.058379311 | H56: =CF!H10/IS!H2 -> 0.043071872 | I56: =CF!I10/IS!I2 -> 0.061973212 | ... K56: =CF!K10/IS!K2 -> 0.070018753
A57: Cashflow from Operating/Short-term Debt | B57: =CF!B10/BS!C65 -> 0.16951097 | C57: =CF!C10/BS!D65 -> 0.126113 | D57: =CF!D10/BS!E65 -> -0.045217081 | E57: =CF!E10/BS!F65 -> 0.36680854 | F57: =CF!F10/BS!G65 -> 0.004023895 | G57: =CF!G10/BS!H65 -> 0.18340798 | H57: =CF!H10/BS!I65 -> 0.14633463 | I57: =CF!I10/BS!J65 -> 0.22048321 | ... K57: =CF!K10/BS!L65 -> 0.24847918
A58: Net Cashflow/Short-term Debt | B58: =CF!B29/BS!C65 -> 0.15362186 | C58: =CF!C29/BS!D65 -> 0.018877329 | D58: =CF!D29/BS!E65 -> -0.022302666 | E58: =CF!E29/BS!F65 -> 0.14385527 | F58: =CF!F29/BS!G65 -> -0.075270029 | G58: =CF!G29/BS!H65 -> 0.22694047 | H58: =CF!H29/BS!I65 -> 0.003273697 | I58: =CF!I29/BS!J65 -> 0.1014636 | ... K58: =CF!K29/BS!L65 -> 0.24900774
A59: Cashflow from Operating/Equity | B59: =CF!B10/BS!C114 -> 0.11671135 | C59: =CF!C10/BS!D114 -> 0.08040295 | D59: =CF!D10/BS!E114 -> -0.03083528 | E59: =CF!E10/BS!F114 -> 0.23446063 | F59: =CF!F10/BS!G114 -> 0.0027217179 | G59: =CF!G10/BS!H114 -> 0.10823603 | H59: =CF!H10/BS!I114 -> 0.084453048 | I59: =CF!I10/BS!J114 -> 0.12068577 | ... K59: =CF!K10/BS!L114 -> 0.1250049
A60: Cashflow from Operating/Operating Profit | B60: =CF!B10/IS!B11 -> 0.95285908 | C60: =CF!C10/IS!C11 -> 0.59910578 | D60: =CF!D10/IS!D11 -> -0.25544423 | E60: =CF!E10/IS!E11 -> 1.9939713 | F60: =CF!F10/IS!F11 -> 0.026508014 | G60: =CF!G10/IS!G11 -> 1.0397655 | H60: =CF!H10/IS!H11 -> 0.75430977 | I60: =CF!I10/IS!I11 -> 0.98590826 | ... K60: =CF!K10/IS!K11 -> 1.0414132
A61: Cashflow from Operating/Debt | B61: =CF!B10/BS!C64 -> 0.15748514 | C61: =CF!C10/BS!D64 -> 0.11813971 | D61: =CF!D10/BS!E64 -> -0.043500842 | E61: =CF!E10/BS!F64 -> 0.35328037 | F61: =CF!F10/BS!G64 -> 0.004023895 | G61: =CF!G10/BS!H64 -> 0.18340798 | H61: =CF!H10/BS!I64 -> 0.14633463 | I61: =CF!I10/BS!J64 -> 0.22048321 | ... K61: =CF!K10/BS!L64 -> 0.24847918

Sheet M- Scores
A1: MOBILE WORLD, JSC (HOSE: MWG) Analysis of financial reporting fraud assessment index
B4: We use Beneish's M-Score to reassess the likelihood of financial statement fraud by the company.
B5: Beneish M-Score:
B6: M-Score (8 variables) = -4.48 + 0.0290xDSRI + 0.528xGMI + 0.404xAQI + 0.892xSGI + 0.115xDEPI - 0.172xSGAI + 4.679xTATA - 0.327xLVGI
B8: Financial Ratio Indexes | C8: 2017 | D8: 2018 | E8: 2019 | F8: 2020 | G8: 2021
B9: Days Sales Receivable Index (DSRI) | D9: =(D28/D26)/(C28/C26) -> 0.4276432 | E9: =(E28/E26)/(D28/D26) -> 0.99636856 | F9: =(F28/F26)/(E28/E26) -> 0.82729318 | G9: =(G28/G26)/(F28/F26) -> 1.7498722
B10: Gross Margin Index (GMI) | D10: =((C26-C27)/C26)/((D26-D27)/D26) -> 0.9501897 | E10: =((D26-D27)/D26)/((E26-E27)/E26) -> 0.92672031 | F10: =((E26-E27)/E26)/((F26-F27)/F26) -> 0.86426755 | G10: =((F26-F27)/F26)/((G26-G27)/G26) -> 0.98201004
B11: Asset Quality Index (AQI) | D11: =(1-((D29+D30)/D32))/(1-((C29+C30)/C32)) -> 2.2390839 | E11: =(1-((E29+E30)/E32))/(1-((D29+D30)/D32)) -> 0.61611001 | F11: =(1-((F29+F30)/F32))/(1-((E29+E30)/E32)) -> 0.99211306 | G11: =(1-((G29+G30)/G32))/(1-((F29+F30)/F32)) -> 0.73242886
B12: Sales Growth Index (SGI) | D12: =D26/C26 -> 1.3041384 | E12: =E26/D26 -> 1.1809828 | F12: =F26/E26 -> 1.0623619 | G12: =G26/F26 -> 1.132774
B13: Depreciation Index (DEPI) | D13: =(C31/(C30+C31))/(D31/(D30+D31)) -> 0.6408315 | E13: =(D31/(D30+D31))/(E31/(E30+E31)) -> 1.2719345 | F13: =(E31/(E30+E31))/(F31/(F30+F31)) -> 0.90086498 | G13: =(F31/(F30+F31))/(G31/(G30+G31)) -> 0.98639765
B14: Sales, General and Administration Expense Index (SGAI) | D14: =(D33/D26)/(C33/C26) -> 1.0039317 | E14: =(E33/E26)/(D33/D26) -> 0.99680223 | F14: =(F33/F26)/(E33/E26) -> 1.545286 | G14: =(G33/G26)/(F33/F26) -> 0.99142693
B15: Leverage Index (LVGI) | D15: =((D36+D37)/D32)/((C36+C37)/C32) -> 0.91833805 | E15: =((E36+E37)/E32)/((D36+D37)/D32) -> 1.0415356 | F15: =((F36+F37)/F32)/((E36+E37)/E32) -> 0.93626803 | G15: =((G36+G37)/G32)/((F36+F37)/F32) -> 1.0191686
B16: Total Accrual on Total Assets (TATA) | D16: =(D34-D35)/D32 -> 0.022017029 | E16: =(E34-E35)/E32 -> 0.12281359 | F16: =(F34-F35)/F32 -> -0.14930317 | G16: =(G34-G35)/G32 -> 0.075114035
B17: Beneish M-Score (8 biến) | E17: =-4.48 + 0.029*E9/D9 + 0.528*D10/E10 + 0.404*E11/D11 + 0.892*E12/D12 + 0.115*D13/E13 - 0.172*E14/D14 + 4.679*E16 - 0.327*E15/D15 -> -2.8611932 | F17: =-4.48 + 0.029*F9/E9 + 0.528*E10/F10 + 0.404*F11/E11 + 0.892*F12/E12 + 0.115*E13/F13 - 0.172*F14/E14 + 4.679*F16 - 0.327*F15/E15 -> -3.5336194 | G17: =-4.48 + 0.029*G9/F9 + 0.528*F10/G10 + 0.404*G11/F11 + 0.892*G12/F12 + 0.115*F13/G13 - 0.172*G14/F14 + 4.679*G16 - 0.327*G15/F15 -> -2.7144116
B19: KẾT LUẬN:
B20: MWG did not manipulate its financial statements during the 2019-2021 period.
B21: Beneish M-Score (8 variables) < -2,22: Company is not likely to have manipulated their earnings
B22: Beneish M-Score (8 variables) > -2,22: Company is likely to have manipulated their earnings
G24: Unit: Million VND
C25: 2017 | D25: 2018 | E25: 2019 | F25: 2020 | G25: 2021
B26: Net Revenue | C26: =DATA!C152 -> 66339804 | D26: =DATA!D152 -> 86516287 | E26: =DATA!E152 -> 102174244 | F26: =DATA!F152 -> 1.0854602e+08 | G26: =DATA!G152 -> 1.2295811e+08
B27: COGS | C27: =DATA!C154 -> 55198025 | D27: =DATA!D154 -> 71224159 | E27: =DATA!E154 -> 82686445 | F27: =DATA!F154 -> 84591522 | G27: =DATA!G154 -> 95325974
B28: Payables | C28: =DATA!C17 -> 2765847.8 | D28: =DATA!D17 -> 1542529.7 | E28: =DATA!E17 -> 1815085.6 | F28: =DATA!F17 -> 1595251 | G28: =DATA!G17 -> 3162122
B29: Current Assets | C29: =DATA!C6 -> 18862861 | D29: =DATA!D6 -> 23371995 | E29: =DATA!E6 -> 35011897 | F29: =DATA!F6 -> 37317234 | G29: =DATA!G6 -> 51955258
B30: PP&E | C30: =DATA!C50 -> 3435848.3 | D30: =DATA!D50 -> 3304923.5 | E30: =DATA!E50 -> 5375279.2 | F30: =DATA!F50 -> 7267319.3 | G30: =DATA!G50 -> 9566954.9
B31: Depreciation | C31: =-CAPEX!B16 -> 686732.39 | D31: =-CAPEX!C16 -> 1160832.3 | E31: =-CAPEX!D16 -> 1380695 | F31: =-CAPEX!E16 -> 2132376.3 | G31: =-CAPEX!F16 -> 2857407.2
B32: Total Assets | C32: =DATA!C81 -> 22822664 | D32: =DATA!D81 -> 28122532 | E32: =DATA!E81 -> 41708096 | F32: =DATA!F81 -> 46030880 | G32: =DATA!G81 -> 62971405
B33: SGA Expense | C33: =DATA!C167 -> 1345497.4 | D33: =DATA!D167 -> 1761613.9 | E33: =DATA!E167 -> 2073782.9 | F33: =DATA!F167 -> 3404431.8 | G33: =DATA!G167 -> 3823390.1
B34: Earnings after Tax (EAT) | C34: =DATA!C183 -> 2206897.1 | D34: =DATA!D183 -> 2880309.1 | E34: =DATA!E183 -> 3836240.1 | F34: =DATA!F183 -> 3919872.7 | G34: =DATA!G183 -> 4901426.7
B35: Cashflow from Operating Activities | C35: =DATA!C194 -> 2663664 | D35: =DATA!D194 -> 2261134.5 | E35: =DATA!E194 -> -1286080.8 | F35: =DATA!F194 -> 10792429 | G35: =DATA!G194 -> 171390.4
B36: Short-term Debt | C36: =DATA!C85 -> 15713815 | D36: =DATA!D85 -> 17929433 | E36: =DATA!E85 -> 28442367 | F36: =DATA!F85 -> 29422513 | G36: =DATA!G85 -> 42593159
B37: Long-term Debt | C37: =DATA!C101 -> 1199933 | D37: =DATA!D101 -> 1210063.2 | E37: =DATA!E101 -> 1122136.7 | F37: =DATA!F101 -> 1126676.7 | G37: =DATA!G101 -> 0

Sheet SALE
B1: 2017A | C1: 2018A | D1: 2019A | E1: 2020A | F1: 2021A | G1: 2022F | H1: 2023F | I1: 2024F | J1: 2025F | K1: 2026F
A2: ICT &CE( ĐMX, TGDĐ, Topzone, Bluetronics )
A3: Thegioididong | B3: 34708000 | C3: =0.4*C52 -> 34606515 | D3: =0.57*D52 -> 58239319 | E3: =0.272*E52 -> 29524517 | F3: =0.25662*F52 -> 31553509 | G3: =G8*G7*12 -> 34806448 | H3: =H7*H8*12 -> 37277706 | I3: =I7*I8*12 -> 38019606 | J3: =J7*J8*12 -> 37825743 | K3: =K7*K8*12 -> 37423606
A4: Growth | C4: =(C3-B3)/B3 -> -0.0029239714 | D4: =(D3-C3)/C3 -> 0.68290044 | E4: =(E3-D3)/D3 -> -0.49304838 | F4: =(F3-E3)/E3 -> 0.068722269 | G4: =(G3-F3)/F3 -> 0.10309278 | H4: =(H3-G3)/G3 -> 0.071 | I4: =(I3-H3)/H3 -> 0.019901961 | J4: =(J3-I3)/I3 -> -0.0050990099 | K4: =(K3-J3)/J3 -> -0.010631313
A5: The number of old stores | B5: 951 | C5: =B7 -> 1072 | D5: =C7 -> 1032 | E5: =D7 -> 996 | F5: =E7 -> 913 | G5: =F7 -> 970 | H5: =G7 -> 1000 | I5: =H7 -> 1020 | J5: =I7 -> 1010 | K5: =J7 -> 990
A6: The number of new stores | B6: =1072-B5 -> 121 | C6: =C7-C5 -> -40 | D6: =D7-D5 -> -36 | E6: =E7-E5 -> -83 | F6: =F7-F5 -> 57 | G6: 30 | H6: 20 | I6: -10 | J6: -20 | K6: -25
A7: Total stores | B7: =SUM(B5:B6) -> 1072 | C7: 1032 | D7: 996 | E7: 913 | F7: 970 | G7: =SUM(G5:G6) -> 1000 | H7: =SUM(H5:H6) -> 1020 | I7: =SUM(I5:I6) -> 1010 | J7: =SUM(J5:J6) -> 990 | K7: =SUM(K5:K6) -> 965
A8: Average revenue per store per month | B8: =(B3/B7)/12 -> 2698.0721 | C8: =(C3/C7)/12 -> 2794.4537 | D8: =(D3/D7)/12 -> 4872.7677 | E8: =(E3/E7)/12 -> 2694.8263 | F8: =(F3/F7)/12 -> 2710.7826 | G8: =F8*(1+G9) -> 2900.5374 | H8: =G8*(1+H9) -> 3045.5642 | I8: =H8*(1+I9) -> 3136.9312 | J8: =I8*(1+J9) -> 3183.9851 | K8: =J8*(1+K9) -> 3231.7449
A9: Same-store sales growth (SSSG) | G9: 0.07 | H9: 0.05 | I9: 0.03 | J9: 0.015 | K9: 0.015
A11: Đienmayxanh | B11: 30245000 | C11: =0.55*C52 -> 47583958 | D11: =0.325*D52 -> 33206629 | E11: =0.532*E52 -> 57746482 | F11: =0.51*F52 -> 62708634 | G11: =G16*G15*12 -> 71697816 | H11: =H16*H15*12 -> 76136175 | I11: =I16*I15*12 -> 79628120 | J11: =J16*J15*12 -> 82526222 | K11: =K16*K15*12 -> 85493349
A12: Growth | C12: =(C11-B11)/B11 -> 0.57328345 | D12: =(D11-C11)/C11 -> -0.30214655 | E12: =(E11-D11)/D11 -> 0.73900464 | F12: =(F11-E11)/E11 -> 0.085929938 | G12: =(G11-F11)/F11 -> 0.14334839 | H12: =(H11-G11)/G11 -> 0.06190369 | I12: =(I11-H11)/H11 -> 0.045864466 | J12: =(J11-I11)/I11 -> 0.036395447 | K12: =(K11-J11)/J11 -> 0.035953757
A13: The number of old stores | B13: =B15-B14 -> 256 | C13: =B15 -> 642 | D13: =C15 -> 750 | E13: =D15 -> 1018 | F13: =E15 -> 1427 | G13: =F15 -> 1992 | H13: =G15 -> 2222 | I13: =H15 -> 2302 | J13: =I15 -> 2372 | K13: =J15 -> 2422
A14: The number of new stores | B14: 386 | C14: =C15-C13 -> 108 | D14: =D15-D13 -> 268 | E14: =E15-E13 -> 409 | F14: =F15-F13 -> 565 | G14: 230 | H14: 80 | I14: 70 | J14: 50 | K14: 50
A15: Total stores | B15: 642 | C15: 750 | D15: 1018 | E15: 1427 | F15: 1992 | G15: =SUM(G13:G14) -> 2222 | H15: =SUM(H13:H14) -> 2302 | I15: =SUM(I13:I14) -> 2372 | J15: =SUM(J13:J14) -> 2422 | K15: =SUM(K13:K14) -> 2472
A16: Average revenue per store per month | B16: =(B11/B15)/12 -> 3925.8827 | C16: =(C11/C15)/12 -> 5287.1064 | D16: =(D11/D15)/12 -> 2718.2899 | E16: =(E11/E15)/12 -> 3372.2543 | F16: =(F11/F15)/12 -> 2623.3532 | G16: =F16*(1+G17) -> 2688.937 | H16: =G16*(1+H17) -> 2756.1604 | I16: =H16*(1+I17) -> 2797.5028 | J16: =I16*(1+J17) -> 2839.4654 | K16: =J16*(1+K17) -> 2882.0574
A17: Same-store sales growth (SSSG) | G17: 0.025 | H17: =G17 -> 0.025 | I17: 0.015 | J17: 0.015 | K17: 0.015
A19: Bluetronics | D19: n/a | E19: n/a | F19: =0.39%*F52 -> 479536.61 | G19: =G23*G24*12 -> 813294.1 | H19: =H23*H24*12 -> 862091.74 | I19: =I23*I24*12 -> 905196.33 | J19: =J23*J24*12 -> 950456.15 | K19: =K23*K24*12 -> 997978.95
A20: Growth | G20: =(G19/F19)-1 -> 0.696 | H20: =(H19/G19)-1 -> 0.06 | I20: =(I19/H19)-1 -> 0.05 | J20: =(J19/I19)-1 -> 0.05 | K20: =(K19/J19)-1 -> 0.05
A21: The number of old stores | B21: 0 | C21: 0 | D21: =C23 -> 10 | E21: =D23 -> 19 | F21: =E23 -> 38 | G21: =F23 -> 50 | H21: =G23 -> 80 | I21: =H23 -> 80 | J21: =I23 -> 80 | K21: =J23 -> 80
A22: The number of new stores | B22: 0 | C22: =C23-C21 -> 10 | D22: =D23-D21 -> 9 | E22: =E23-E21 -> 19 | F22: =F23-F21 -> 12 | G22: 30 | H22: 0 | I22: 0 | J22: 0 | K22: 0
A23: Total stores | B23: 0 | C23: 10 | D23: 19 | E23: 38 | F23: 50 | G23: =SUM(G21:G22) -> 80 | H23: =SUM(H21:H22) -> 80 | I23: =SUM(I21:I22) -> 80 | J23: =SUM(J21:J22) -> 80 | K23: =SUM(K21:K22) -> 80
A24: Average revenue per store per month | F24: =F19/F23/12 -> 799.22769 | G24: =F24*(1+G25) -> 847.18135 | H24: =G24*(1+H25) -> 898.01223 | I24: =H24*(1+I25) -> 942.91284 | J24: =I24*(1+J25) -> 990.05849 | K24: =J24*(1+K25) -> 1039.5614
A25: Same-store sales growth (SSSG) | G25: 0.06 | H25: 0.06 | I25: 0.05 | J25: 0.05 | K25: 0.05
A27: Topzone | F27: n/a | G27: =G32*G31*12 -> 9900000 | H27: =H32*H31*12 -> 22140000 | I27: =I32*I31*12 -> 26058780 | J27: =J32*J31*12 -> 29784001 | K27: =K32*K31*12 -> 33903065
A28: Growth | H28: =(H27/G27)-1 -> 1.2363636 | I28: =(I27/H27)-1 -> 0.177 | J28: =(J27/I27)-1 -> 0.14295455 | K28: =(K27/J27)-1 -> 0.13829787
A29: The number of old stores | B29: 0 | C29: 0 | D29: 0 | E29: 0 | F29: 0 | G29: =F31 -> 10 | H29: =G31 -> 110 | I29: =H31 -> 200 | J29: =I31 -> 220 | K29: =J31 -> 235
A30: The number of new stores | B30: 0 | C30: 0 | D30: 0 | E30: 0 | F30: 10 | G30: 100 | H30: 90 | I30: 20 | J30: 15 | K30: 15
A31: Total stores | B31: 0 | C31: 0 | D31: 0 | E31: 0 | F31: 10 | G31: =SUM(G29:G30) -> 110 | H31: =SUM(H29:H30) -> 200 | I31: =SUM(I29:I30) -> 220 | J31: =SUM(J29:J30) -> 235 | K31: =SUM(K29:K30) -> 250
A32: Average revenue per store per month | G32: =7500 -> 7500 | H32: =G32*1.23 -> 9225 | I32: =H32*1.07 -> 9870.75 | J32: =I32*1.07 -> 10561.703 | K32: =J32*1.07 -> 11301.022
A33: Same-store sales growth (SSSG) | H33: 0.23 | I33: 0.07 | J33: 0.07 | K33: 0.07
A35: FMCG
A36: Bachhoaxanh | B36: =B52-B3-B11 -> 1386804.2 | C36: =C52-C3-C11 -> 4325814.3 | D36: =D52-D3-D11 -> 10728296 | E36: =E52-E3-E11 -> 21275020 | F36: =F52-F3-F11-F19 -> 28216426 | G36: =G41*G40*12 -> 31981296 | H36: =H41*H40*12 -> 45204162 | I36: =I41*I40*12 -> 59998975 | J36: =J41*J40*12 -> 75809289 | K36: =K41*K40*12 -> 92129345
A37: Growth | C37: =(C36-B36)/B36 -> 2.1192683 | D37: =(D36-C36)/C36 -> 1.4800638 | E37: =(E36-D36)/D36 -> 0.98307547 | F37: =(F36-E36)/E36 -> 0.32627026 | G37: =(G36-F36)/F36 -> 0.1334283 | H37: =(H36-G36)/G36 -> 0.41345622 | I37: =(I36-H36)/H36 -> 0.32728873 | J37: =(J36-I36)/I36 -> 0.26350975 | K37: =(K36-J36)/J36 -> 0.21527778
A38: The number of old stores | B38: =B40-B39 -> 48 | C38: =B40 -> 283 | D38: =C40 -> 405 | E38: =D40 -> 1008 | F38: =E40 -> 1719 | G38: =F40 -> 2106 | H38: =G40 -> 2170 | I38: =H40 -> 2840 | J38: =I40 -> 3590 | K38: =J40 -> 4320
A39: The number of new stores | B39: 235 | C39: =C40-C38 -> 122 | D39: =D40-D38 -> 603 | E39: =E40-E38 -> 711 | F39: =F40-F38 -> 387 | G39: 64 | H39: 670 | I39: 750 | J39: 730 | K39: 680
A40: Total stores | B40: 283 | C40: 405 | D40: 1008 | E40: 1719 | F40: 2106 | G40: =SUM(G38:G39) -> 2170 | H40: =SUM(H38:H39) -> 2840 | I40: =SUM(I38:I39) -> 3590 | J40: =SUM(J38:J39) -> 4320 | K40: =SUM(K38:K39) -> 5000
A41: Average revenue per store per month | B41: =B36/B40/12 -> 408.36402 | C41: =C36/C40/12 -> 890.08526 | D41: =D36/D40/12 -> 886.9292 | E41: =E36/E40/12 -> 1031.3661 | F41: =F36/F40/12 -> 1116.5094 | G41: =F41*(1+G42) -> 1228.1604 | H41: =G41*(1+H42) -> 1326.4132 | I41: =H41*(1+I42) -> 1392.7339 | J41: =I41*(1+J42) -> 1462.3705 | K41: =J41*(1+K42) -> 1535.4891
A42: Same-store sales growth (SSSG) | G42: 0.1 | H42: 0.08 | I42: 0.05 | J42: 0.05 | K42: 0.05
A44: Pharmaceutical
A45: An Khang | E45: n/a | F45: n/a | G45: =G49*G50*12 -> 3768000 | H45: =H49*H50*12 -> 6784800 | I45: =I49*I50*12 -> 10186176 | J45: =J49*J50*12 -> 13888090 | K45: =K49*K50*12 -> 17633646
A46: Growth | H46: =(H45/G45)-1 -> 0.80063694 | I46: =(I45/H45)-1 -> 0.50132296 | J46: =(J45/I45)-1 -> 0.36342525 | K46: =(K45/J45)-1 -> 0.26969555
A47: The number of old stores | B47: 0 | C47: 0 | D47: =C49 -> 7 | E47: =D49 -> 17 | F47: =E49 -> 68 | G47: =F49 -> 178 | H47: =G49 -> 628 | I47: =H49 -> 1028 | J47: =I49 -> 1378 | K47: =J49 -> 1708
A48: The number of new stores | B48: 0 | C48: =C49-C47 -> 7 | D48: =D49-D47 -> 10 | E48: =E49-E47 -> 51 | F48: =F49-F47 -> 110 | G48: 450 | H48: 400 | I48: 350 | J48: 330 | K48: 300
A49: Total stores | B49: 0 | C49: 7 | D49: 17 | E49: 68 | F49: 178 | G49: =SUM(G47:G48) -> 628 | H49: =SUM(H47:H48) -> 1028 | I49: =SUM(I47:I48) -> 1378 | J49: =SUM(J47:J48) -> 1708 | K49: =SUM(K47:K48) -> 2008
A50: Average revenue per store per month | G50: 500 | H50: =G50*(1+H51) -> 550 | I50: =H50*(1+I51) -> 616 | J50: =I50*(1+J51) -> 677.6 | K50: =J50*(1+K51) -> 731.808
A51: Same-store sales growth (SSSG) | H51: 0.1 | I51: 0.12 | J51: 0.1 | K51: 0.08
A52: Total revenue | B52: =IS!B2 -> 66339804 | C52: =IS!C2 -> 86516287 | D52: =IS!D2 -> 102174244 | E52: =IS!E2 -> 1.0854602e+08 | F52: =IS!F2 -> 1.2295811e+08 | G52: =G45+G36+G27+G19+G11+G3 -> 1.5296685e+08 | H52: =H45+H36+H27+H19+H11+H3 -> 1.8840494e+08 | I52: =I45+I36+I27+I19+I11+I3 -> 2.1479685e+08 | J52: =J45+J36+J27+J19+J11+J3 -> 2.407838e+08 | K52: =K45+K36+K27+K19+K11+K3 -> 2.6758099e+08
A53: Growth | C53: =(C52/B52)-1 -> 0.30413841 | D53: =(D52/C52)-1 -> 0.18098277 | E53: =(E52/D52)-1 -> 0.062361858 | F53: =(F52/E52)-1 -> 0.13277397 | G53: =(G52/F52)-1 -> 0.24405669 | H53: =(H52/G52)-1 -> 0.23167163 | I53: =(I52/H52)-1 -> 0.14008082 | J53: =(J52/I52)-1 -> 0.12098384 | K53: =(K52/J52)-1 -> 0.11129149

Sheet IS
A1: MWG (Unit: Million VND) | B1: 2017 | C1: 2018 | D1: 2019 | E1: 2020 | F1: 2021 | G1: 2022F | H1: 2023F | I1: 2024F | J1: 2025F | K1: 2026F
A2: 1. Net revenue from sale of goods and services | B2: 66339804 | C2: 86516287 | D2: 102174244 | E2: 1.0854602e+08 | F2: 1.2295811e+08 | G2: =SALE!G52 -> 1.5296685e+08 | H2: =SALE!H52 -> 1.8840494e+08 | I2: =SALE!I52 -> 2.1479685e+08 | J2: =SALE!J52 -> 2.407838e+08 | K2: =SALE!K52 -> 2.6758099e+08
A3: 2. Costs of goods sold | B3: 55198025 | C3: 71224159 | D3: 82686445 | E3: 84591522 | F3: 95325974 | G3: =G59 -> 1.1826715e+08 | H3: =H59 -> 1.4595467e+08 | I3: =I59 -> 1.6588203e+08 | J3: =J59 -> 1.8534124e+08 | K3: =K59 -> 2.0570142e+08
A4: 3. Gross profit | B4: 11141779 | C4: 15292128 | D4: 19487799 | E4: 23954497 | F4: 27632132 | G4: =G2-G3 -> 34699709 | H4: =H2-H3 -> 42450264 | I4: =I2-I3 -> 48914819 | J4: =J2-J3 -> 55442558 | K4: =K2-K3 -> 61879573 | M4: 1. Revenue from sale of goods and services
A5: 4. Income from financial activities | B5: 250509.8 | C5: 342083.9 | D5: 631177.9 | E5: 794121.8 | F5: 1287956 | G5: =F5*1.05 -> 1352353.8 | H5: =G5*1.05 -> 1419971.5 | I5: =H5*1.05 -> 1490970.1 | J5: =I5*1.06 -> 1580428.3 | K5: =J5*1.06 -> 1675254 | M5: 2. Costs of goods sold
A6: 5. Expenses from financial activities | B6: 234286.6 | C6: 436573.2 | D6: 569754.8 | E6: 594151.5 | F6: 714707.2 | G6: =G2*G31+G7 -> 904810.26 | H6: =H2*H31+H7 -> 966089.13 | I6: =I2*I31+I7 -> 1114506 | J6: =J2*J31+J7 -> 1093101.7 | K6: =K2*K31+K7 -> 1247121.2 | M6: 3. Gross profit
A7: - In which: Interest expenses | B7: 233202.3 | C7: 436416.6 | D7: 568136.7 | E7: 594003.8 | F7: 674427.7 | G7: ='FI&FE'!G2 -> 893706.73 | H7: ='FI&FE'!H2 -> 950293.92 | I7: ='FI&FE'!I2 -> 1092974.4 | J7: ='FI&FE'!J2 -> 1064900.5 | K7: ='FI&FE'!K2 -> 1209586.2 | M7: 4. Income from financial activities
A8: 6. Gain (loss) in profits of associates | B8: 0 | C8: -2101 | D8: -3473.3 | E8: -3706.9 | F8: -2210.5 | G8: =G2*G33 -> -4391.273 | H8: =H2*H33 -> -5076.603 | I8: =I2*I33 -> -5271.8442 | J8: =J2*J33 -> -6436.6258 | K8: =K2*K33 -> -6976.7763 | M8: 5. Expenses from financial activities
A9: 7. Selling expenses | B9: 7017061.3 | C9: 9659741.2 | D9: 12437283 | E9: 15333799 | F9: 17914173 | G9: =G2*G34 -> 21415360 | H9: =H2*H34 -> 25811476 | I9: =I2*I34 -> 28997575 | J9: =J2*J34 -> 32505813 | K9: =K2*K34 -> 36123434 | M9: - In which: Interest expenses
A10: 8. General and administrative expenses | B10: 1345497.4 | C10: 1761613.9 | D10: 2073782.9 | E10: 3404431.8 | F10: 3823390.1 | G10: =G2*G35 -> 5138931.2 | H10: =H2*H35 -> 6329475.7 | I10: =I2*I35 -> 6786520.2 | J10: =J2*J35 -> 7366795.6 | K10: =K2*K35 -> 8186657.3 | M10: 6. Share in profits of associates
A11: 9. Operating profit | B11: 2795443.8 | C11: 3774182.4 | D11: 5034683.4 | E11: 5412529.9 | F11: 6465606.9 | G11: =G4+G5-G6+G8-G9-G10 -> 8588570.4 | H11: =H4+H5-H6+H8-H9-H10 -> 10758118 | I11: =I4+I5-I6+I8-I9-I10 -> 13501916 | J11: =J4+J5-J6+J8-J9-J10 -> 16050839 | K11: =K4+K5-K6+K8-K9-K10 -> 17990638 | M11: 7. Selling expenses
A12: 10. Other income | B12: 17684.6 | C12: 33233.3 | D12: 41557 | E12: 43512.7 | F12: 54872.8 | G12: =G$2*G37 -> 64792.248 | H12: =H$2*H37 -> 81941.341 | I12: =I$2*I37 -> 92200.681 | J12: =J$2*J37 -> 104038.75 | K12: =K$2*K37 -> 115237.72 | M12: 8. General and administrative expenses
A13: 11. Other expenses | B13: 3816.4 | C13: 21097.2 | D13: 22793.3 | E13: 46307.2 | F13: 48896 | G13: =G$2*G38 -> 63043.562 | H13: =H$2*H38 -> 76285.404 | I13: =I$2*I38 -> 87748.812 | J13: =J$2*J38 -> 97929.338 | K13: =K$2*K38 -> 109070.11 | M13: 9. Operating profit
A14: 12. Other profit | B14: 13868.3 | C14: 12136.2 | D14: 18763.8 | E14: -2794.5 | F14: 5976.8 | G14: =G12-G13 -> 1748.6854 | H14: =H12-H13 -> 5655.9367 | I14: =I12-I13 -> 4451.869 | J14: =J12-J13 -> 6109.4146 | K14: =K12-K13 -> 6167.6055 | M14: 10. Other income
A15: 13. Earning Before Interest and Tax | B15: 2809312 | C15: 3786318.6 | D15: 5053447.2 | E15: 5409735.4 | F15: 6471583.8 | G15: =G11+G14 -> 8590319.1 | H15: =H11+H14 -> 10763774 | I15: =I11+I14 -> 13506368 | J15: =J11+J14 -> 16056948 | K15: =K11+K14 -> 17996806 | M15: 11. Other expenses
A16: 14. Current corporate income tax expense | B16: 639743.6 | C16: 933836.7 | D16: 1248353.1 | E16: 1598413.8 | F16: 1632975.7 | G16: =G$2*G41 -> 2050995.5 | H16: =H$2*H41 -> 2600900.7 | I16: =I$2*I41 -> 2899306.2 | J16: =J$2*J41 -> 3267504.1 | K16: =K$2*K41 -> 3645614.8 | M16: 12. Other profit
A17: 15. Deferred corporate income tax expense | B17: -37328.7 | C17: -27827.2 | D17: -31146 | E17: -108551.1 | F17: -62818.6 | G17: =G$2*G42 -> -115561.96 | H17: =H$2*H42 -> -119294.7 | I17: =I$2*I42 -> -149139.15 | J17: =J$2*J42 -> -159821.33 | K17: =K$2*K42 -> -181698.33 | M17: 13. Earning Before Interest and Tax
A18: 16. Net profit after tax | B18: 2206897.1 | C18: 2880309.1 | D18: 3836240.1 | E18: 3919872.7 | F18: 4901426.7 | G18: =G15-G16-G17 -> 6654885.6 | H18: =H15-H16-H17 -> 8282167.8 | I18: =I15-I16-I17 -> 10756201 | J18: =J15-J16-J17 -> 12949266 | K18: =K15-K16-K17 -> 14532889 | M18: 14. Current corporate income tax expense
A19: 17. Equity holders of non-controlling interest | B19: 1217.5 | C19: 1584.9 | D19: 1970.5 | E19: 2104.9 | F19: 2557.4 | G19: =G2*G44 -> 3073.9247 | H19: =H2*H44 -> 3852.3457 | I19: =I2*I44 -> 4354.2033 | J19: =J2*J44 -> 4902.1681 | K19: =K2*K44 -> 5435.971 | M19: 15. Deferred corporate income tax expense
A20: 18. Net profit after tax of parent company | B20: 2205679.6 | C20: 2878724.1 | D20: 3834269.5 | E20: 3917767.8 | F20: 4898869.3 | G20: =G18-G19 -> 6651811.6 | H20: =H18-H19 -> 8278315.4 | I20: =I18-I19 -> 10751847 | J20: =J18-J19 -> 12944364 | K20: =K18-K19 -> 14527453 | M20: 16. Net profit after tax
M21: 17. Equity holders of non-controlling interest
A22: Share outstanding | E22: =690259427 -> 690259427 | F22: =710319805 -> 710319805 | G22: =DCF!B40*2 -> 1463709630 | H22: =G22 -> 1463709630 | I22: =H22 -> 1463709630 | J22: =I22 -> 1463709630 | K22: =J22 -> 1463709630 | M22: 18. Net profit after tax of parent company
A23: EPS | E23: =E20*10^6/E22 -> 5675.7904 | F23: =F20*10^6/F22 -> 6896.7094 | G23: =(G20*10^6)/G22 -> 4544.4885 | H23: =(H20*10^6)/H22 -> 5655.7088 | I23: =(I20*10^6)/I22 -> 7345.6147 | J23: =(J20*10^6)/J22 -> 8843.5324 | K23: =(K20*10^6)/K22 -> 9925.0923
A25: MWG Common-size Income Statement
A26: 1. Net revenue from sale of goods and services | B26: =B2/B$2 -> 1 | C26: =C2/C$2 -> 1 | D26: =D2/D$2 -> 1 | E26: =E2/E$2 -> 1 | F26: =F2/F$2 -> 1 | G26: =G2/G$2 -> 1 | H26: =H2/H$2 -> 1 | I26: =I2/I$2 -> 1 | ... K26: =K2/K$2 -> 1
A27: 2. Costs of goods sold | B27: =B3/B$2 -> 0.83204986 | C27: =C3/C$2 -> 0.82324568 | D27: =D3/D$2 -> 0.80926897 | E27: =E3/E$2 -> 0.77931483 | F27: =F3/F$2 -> 0.77527198 | G27: =G3/G$2 -> 0.77315537 | H27: =H3/H$2 -> 0.77468603 | I27: =I3/I$2 -> 0.77227404 | ... K27: =K3/K$2 -> 0.76874451
A28: 3. Gross profit | B28: =B4/B$2 -> 0.16795014 | C28: =C4/C$2 -> 0.17675432 | D28: =D4/D$2 -> 0.19073103 | E28: =E4/E$2 -> 0.22068517 | F28: =F4/F$2 -> 0.22472802 | G28: =G4/G$2 -> 0.22684463 | H28: =H4/H$2 -> 0.22531397 | I28: =I4/I$2 -> 0.22772596 | ... K28: =K4/K$2 -> 0.23125549
A29: 4. Income from financial activities | B29: =B5/B$2 -> 0.0037761613 | C29: =C5/C$2 -> 0.0039539827 | D29: =D5/D$2 -> 0.0061774658 | E29: =E5/E$2 -> 0.0073159919 | F29: =F5/F$2 -> 0.010474755 | G29: =G5/G$2 -> 0.008840829 | H29: =H5/H$2 -> 0.0075368062 | I29: =I5/I$2 -> 0.0069413031 | ... K29: =K5/K$2 -> 0.0062607361
A30: 5. Expenses from financial activities | B30: =B6/B$2 -> 0.0035316143 | C30: =C6/C$2 -> 0.0050461389 | D30: =D6/D$2 -> 0.0055763055 | E30: =E6/E$2 -> 0.005473729 | F30: =F6/F$2 -> 0.0058126074 | G30: =G6/G$2 -> 0.005915074 | H30: =H6/H$2 -> 0.0051277273 | I30: =I6/I$2 -> 0.0051886515 | ... K30: =K6/K$2 -> 0.0046607243
A31: Financial expenses (excluding interest expenses) | B31: =(B6-B7)/B2 -> 1.6344637e-05 | C31: =(C6-C7)/C2 -> 1.8100638e-06 | D31: =(D6-D7)/D2 -> 1.5836672e-05 | E31: =(E6-E7)/E2 -> 1.3607132e-06 | F31: =(F6-F7)/F2 -> 0.00032758719 | G31: =AVERAGE(B31:F31) -> 7.2587854e-05 | H31: =AVERAGE(C31:G31) -> 8.3836498e-05 | I31: =AVERAGE(D31:H31) -> 0.00010024178 | J31: =AVERAGE(E31:I31) -> 0.00011712281 | K31: =AVERAGE(F31:J31) -> 0.00014027523
A32: - In which: Interest expenses | B32: =B7/B$2 -> 0.0035152696 | C32: =C7/C$2 -> 0.0050443288 | D32: =D7/D$2 -> 0.0055604688 | E32: =E7/E$2 -> 0.0054723683 | F32: =F7/F$2 -> 0.0054850202 | G32: =G7/G2 -> 0.0058424861 | H32: =H7/H2 -> 0.0050438908 | I32: =I7/I2 -> 0.0050884097 | J32: =J7/J2 -> 0.0044226416 | K32: =K7/K2 -> 0.0045204491
A33: 6. Share in profits of associates | B33: =B8/B$2 -> 0 | C33: =C8/C$2 -> -2.4284445e-05 | D33: =D8/D$2 -> -3.399389e-05 | E33: =E8/E$2 -> -3.4150492e-05 | F33: =F8/F$2 -> -1.7977668e-05 | G33: =AVERAGE(D33:F33) -> -2.870735e-05 | H33: =AVERAGE(E33:G33) -> -2.694517e-05 | I33: =AVERAGE(F33:H33) -> -2.4543396e-05 | J33: =AVERAGE(G33:I33) -> -2.6731972e-05 | K33: =AVERAGE(H33:J33) -> -2.6073513e-05
A34: 7. Selling expenses | B34: =B9/B$2 -> 0.10577453 | C34: =C9/C$2 -> 0.11165229 | D34: =D9/D$2 -> 0.1217262 | E34: =E9/E$2 -> 0.14126542 | F34: =F9/F$2 -> 0.14569331 | G34: 0.14 | H34: =G34-0.3% -> 0.137 | I34: =H34-0.2% -> 0.135 | J34: =I34 -> 0.135 | K34: =J34 -> 0.135
A35: 8. General and administrative expenses | B35: =B10/B$2 -> 0.020281902 | C35: =C10/C$2 -> 0.020361645 | D35: =D10/D$2 -> 0.020296533 | E35: =E10/E$2 -> 0.031363949 | F35: =F10/F$2 -> 0.031095063 | G35: =F35+0.25% -> 0.033595063 | H35: =G35 -> 0.033595063 | I35: =H35-0.2% -> 0.031595063 | J35: =I35-0.1% -> 0.030595063 | K35: =J35 -> 0.030595063
A36: 9. Operating profit | B36: =B11/B$2 -> 0.042138258 | C36: =C11/C$2 -> 0.043623953 | D36: =D11/D$2 -> 0.049275465 | E36: =E11/E$2 -> 0.049863919 | F36: =F11/F$2 -> 0.05258382 | G36: =G11/G2 -> 0.056146611 | H36: =H11/H2 -> 0.057101041 | I36: =I11/I2 -> 0.062859005 | J36: =J11/J2 -> 0.066660793 | K36: =K11/K2 -> 0.067234365
A37: 10. Other income | B37: =B12/B$2 -> 0.00026657601 | C37: =C12/C$2 -> 0.00038412767 | D37: =D12/D$2 -> 0.00040672677 | E37: =E12/E$2 -> 0.00040086868 | F37: =F12/F$2 -> 0.00044627233 | G37: =AVERAGE(E37:F37) -> 0.0004235705 | H37: =AVERAGE(F37:G37) -> 0.00043492142 | I37: =AVERAGE(G37:H37) -> 0.00042924596 | J37: =AVERAGE(H37:I37) -> 0.00043208369 | K37: =AVERAGE(I37:J37) -> 0.00043066482
A38: 11. Other expenses | B38: =B13/B$2 -> 5.7528056e-05 | C38: =C13/C$2 -> 0.00024385235 | D38: =D13/D$2 -> 0.00022308264 | E38: =E13/E$2 -> 0.00042661352 | F38: =F13/F$2 -> 0.0003976639 | G38: =AVERAGE(E38:F38) -> 0.00041213871 | H38: =AVERAGE(F38:G38) -> 0.00040490131 | I38: =AVERAGE(G38:H38) -> 0.00040852001 | J38: =AVERAGE(H38:I38) -> 0.00040671066 | K38: =AVERAGE(I38:J38) -> 0.00040761533
A39: 12. Other profit | B39: =B14/B$2 -> 0.00020904946 | C39: =C14/C$2 -> 0.00014027648 | D39: =D14/D$2 -> 0.00018364511 | E39: =E14/E$2 -> -2.5744841e-05 | F39: =F14/F$2 -> 4.8608426e-05 | G39: =G14/G$2 -> 1.1431793e-05 | H39: =H14/H$2 -> 3.0020109e-05 | I39: =I14/I$2 -> 2.0725951e-05 | ... K39: =K14/K$2 -> 2.3049491e-05
A40: 13. Earning Before Interest and Tax | B40: =B15/B$2 -> 0.042347306 | C40: =C15/C$2 -> 0.043764229 | D40: =D15/D$2 -> 0.04945911 | E40: =E15/E$2 -> 0.049838174 | F40: =F15/F$2 -> 0.052632429 | G40: =G15/G$2 -> 0.056158042 | H40: =H15/H$2 -> 0.057131061 | I40: =I15/I$2 -> 0.062879731 | ... K40: =K15/K$2 -> 0.067257415
A41: 14. Current corporate income tax expense | B41: =B16/B$2 -> 0.0096434352 | C41: =C16/C$2 -> 0.010793768 | D41: =D16/D$2 -> 0.012217884 | E41: =E16/E$2 -> 0.014725679 | F41: =F16/F$2 -> 0.013280749 | G41: =AVERAGE(D41:F41) -> 0.013408104 | H41: =AVERAGE(E41:G41) -> 0.013804844 | I41: =AVERAGE(F41:H41) -> 0.013497899 | J41: =AVERAGE(G41:I41) -> 0.013570282 | K41: =AVERAGE(H41:J41) -> 0.013624342
A42: 15. Deferred corporate income tax expense | B42: =B17/B$2 -> -0.00056268933 | C42: =C17/C$2 -> -0.00032164117 | D42: =D17/D$2 -> -0.0003048322 | E42: =E17/E$2 -> -0.0010000468 | F42: =F17/F$2 -> -0.00051089434 | G42: =AVERAGE(E42:F42) -> -0.00075547057 | H42: =AVERAGE(F42:G42) -> -0.00063318245 | I42: =AVERAGE(G42:H42) -> -0.00069432651 | J42: =AVERAGE(H42:I42) -> -0.00066375448 | K42: =AVERAGE(I42:J42) -> -0.0006790405
A43: 16. Net profit after tax | B43: =B18/B$2 -> 0.03326656 | C43: =C18/C$2 -> 0.033292103 | D43: =D18/D$2 -> 0.037546058 | E43: =E18/E$2 -> 0.036112542 | F43: =F18/F$2 -> 0.039862575 | G43: =G18/G2 -> 0.043505409 | H43: =H18/H2 -> 0.043959399 | I43: =I18/I2 -> 0.050076158 | J43: =J18/J2 -> 0.053779638 | K43: =K18/K2 -> 0.054312114
A44: 17. Equity holders of non-controlling interest | B44: =B19/B$2 -> 1.8352481e-05 | C44: =C19/C$2 -> 1.8319094e-05 | D44: =D19/D$2 -> 1.9285682e-05 | E44: =E19/E$2 -> 1.9391775e-05 | F44: =F19/F$2 -> 2.0798954e-05 | G44: =AVERAGE(E44:F44) -> 2.0095365e-05 | H44: =AVERAGE(F44:G44) -> 2.0447159e-05 | I44: =AVERAGE(G44:H44) -> 2.0271262e-05 | J44: =AVERAGE(H44:I44) -> 2.0359211e-05 | K44: =AVERAGE(I44:J44) -> 2.0315236e-05
A45: 18. Net profit after tax of parent company | B45: =B20/B$2 -> 0.033248208 | C45: =C20/C$2 -> 0.033273782 | D45: =D20/D$2 -> 0.037526771 | E45: =E20/E$2 -> 0.03609315 | F45: =F20/F$2 -> 0.039841776 | G45: =G20/G$2 -> 0.043485314 | H45: =H20/H$2 -> 0.043938952 | I45: =I20/I$2 -> 0.050055887 | ... K45: =K20/K$2 -> 0.054291799
A48: COGS
A49: Thegioididong.com | G49: =SALE!G3*(1-IS!G50) -> 26800965 | H49: =SALE!H3*(1-IS!H50) -> 28703834 | I49: =SALE!I3*(1-IS!I50) -> 29275096 | J49: =SALE!J3*(1-IS!J50) -> 29125822 | K49: =SALE!K3*(1-IS!K50) -> 28816177
A50: Gross margin | F50: 0.23 | G50: 0.23 | H50: 0.23 | I50: 0.23 | J50: 0.23 | K50: 0.23
A51: Dienmayxanh.com & Bluetronics | G51: =(SALE!G11+SALE!G19)*(1-IS!G52) -> 55833555 | H51: =(SALE!H11+SALE!H19)*(1-IS!H52) -> 59288666 | I51: =(SALE!I11+SALE!I19)*(1-IS!I52) -> 62010654 | J51: =(SALE!J11+SALE!J19)*(1-IS!J52) -> 64277042 | K51: =(SALE!K11+SALE!K19)*(1-IS!K52) -> 66598323
A52: Gross margin | F52: 0.23 | G52: 0.23 | H52: 0.23 | I52: 0.23 | J52: 0.23 | K52: 0.23
A53: Topzone | G53: =SALE!G27*(1-IS!G54) -> 8811000 | H53: =SALE!H27*(1-IS!H54) -> 19151100 | I53: =SALE!I27*(1-IS!I54) -> 22149963 | J53: =SALE!J27*(1-IS!J54) -> 25316401 | K53: =SALE!K27*(1-IS!K54) -> 28817605
A54: Gross margin | G54: 0.11 | H54: 0.135 | I54: 0.15 | J54: 0.15 | K54: 0.15
A55: Bachhoaxanh.com | G55: =(1-G56)*SALE!G36 -> 23826065 | H55: =(1-H56)*SALE!H36 -> 33451080 | I55: =(1-I56)*SALE!I36 -> 44399241 | J55: =(1-J56)*SALE!J36 -> 55719828 | K55: =(1-K56)*SALE!K36 -> 67715068
A56: Gross margin | F56: 0.27 | G56: 0.255 | H56: 0.26 | I56: 0.26 | J56: 0.265 | K56: 0.265
A57: An Khang | G57: =(1-G58)*SALE!G45 -> 2995560 | H57: =(1-H58)*SALE!H45 -> 5359992 | I57: =(1-I58)*SALE!I45 -> 8047079 | J57: =(1-J58)*SALE!J45 -> 10902150 | K57: =(1-K58)*SALE!K45 -> 13754244
A58: Gross margin | G58: 0.205 | H58: 0.21 | I58: 0.21 | J58: 0.215 | K58: 0.22
A59: Total cost of sales | B59: =B3 -> 55198025 | C59: =C3 -> 71224159 | D59: =D3 -> 82686445 | E59: =E3 -> 84591522 | F59: =F3 -> 95325974 | G59: =G49+G51+G53+G55+G57 -> 1.1826715e+08 | H59: =H49+H51+H53+H55+H57 -> 1.4595467e+08 | I59: =I49+I51+I53+I55+I57 -> 1.6588203e+08 | J59: =J49+J51+J53+J55+J57 -> 1.8534124e+08 | K59: =K49+K51+K53+K55+K57 -> 2.0570142e+08
A60: Gross margin | B60: =1-B59/B2 -> 0.16795014 | C60: =1-C59/C2 -> 0.17675432 | D60: =1-D59/D2 -> 0.19073103 | E60: =1-E59/E2 -> 0.22068517 | F60: =1-F59/F2 -> 0.22472802 | G60: =1-G59/G2 -> 0.22684463 | H60: =1-H59/H2 -> 0.22531397 | I60: =1-I59/I2 -> 0.22772596 | ... K60: =1-K59/K2 -> 0.23125549

Sheet BS
B1: MWG (Unit: Million VND) | C1: 2017 | D1: 2018 | E1: 2019 | F1: 2020 | G1: 2021 | H1: 2022F | I1: 2023F | J1: 2024F | K1: 2025F | L1: 2026F
B2: A. CURRENT ASSETS | C2: 18862861 | D2: 23371995 | E2: 35011897 | F2: 37317234 | G2: 51955258 | H2: =H3+H4+H8+H17+H20 -> 68268395 | I2: =I3+I4+I8+I17+I20 -> 77842032 | J2: =J3+J4+J8+J17+J20 -> 87916690 | K2: =K3+K4+K8+K17+K20 -> 96497049 | L2: =L3+L4+L8+L17+L20 -> 1.196949e+08
B3: I. Cash and Cash Equivalents | C3: 3410983.4 | D3: 3749550.3 | E3: 3115236.8 | F3: 7347857.4 | G3: 4142015.8 | H3: =CF!G31 -> 15191704 | I3: =CF!H31 -> 15373246 | J3: =CF!I31 -> 21499101 | K3: =CF!J31 -> 21515604 | L3: =CF!K31 -> 40291145
B4: II. Short-term Financial Investment | C4: 0 | D4: 50922.5 | E4: 3137000 | F4: 8057318.8 | G4: 14236626 | H4: =G4 -> 14236626 | I4: =H4 -> 14236626 | J4: =I4 -> 14236626 | K4: =J4 -> 14236626 | L4: =K4 -> 14236626
B5: 1. Securities available for sale | C5: 0 | D5: 0 | E5: 0 | F5: 0 | G5: 0 | H5: 0 | I5: 0 | J5: 0 | K5: 0 | L5: 0
B6: 2. Provision for decline in value of investments in securities | C6: 0 | D6: 0 | E6: 0 | F6: 0 | G6: 0 | H6: 0 | I6: 0 | J6: 0 | K6: 0 | L6: 0
B7: 3. Securities hold to maturity | C7: 0 | D7: 50922.5 | E7: 3137000 | F7: 8057318.8 | G7: 14236626 | H7: =G7 -> 14236626 | I7: =H7 -> 14236626 | J7: =I7 -> 14236626 | K7: =J7 -> 14236626 | L7: =K7 -> 14236626
B8: III. Short-term Receivables | C8: 2765847.8 | D8: 1542529.7 | E8: 1815085.6 | F8: 1595251 | G8: 3162122 | H8: =SUM(H9:H16) -> 3810168.4 | I8: =SUM(I9:I16) -> 4871403.4 | J8: =SUM(J9:J16) -> 5410175.6 | K8: =SUM(K9:K16) -> 6278645.9 | L8: =SUM(L9:L16) -> 6709005.6
B9: 1. Short-term receivables from customers | C9: 1431776.8 | D9: 369573.7 | E9: 262268.4 | F9: 196394.5 | G9: 384236.6 | H9: =NWC!G4 -> 298005.72 | I9: =NWC!H4 -> 566280.27 | J9: =NWC!I4 -> 405209.36 | K9: =NWC!J4 -> 691531.67 | L9: =NWC!K4 -> 522964.33
B10: 2. Prepaid for suppliers | C10: 117942 | D10: 21007.3 | E10: 195016.8 | F10: 287913.3 | G10: 390738.8 | H10: =NWC!G11 -> 486101.22 | I10: =NWC!H11 -> 598717.08 | J10: =NWC!I11 -> 682585.86 | K10: =NWC!J11 -> 765167.72 | L10: =NWC!K11 -> 850324.37
B11: 3. Internal short-term receivables | C11: 0 | D11: 0 | E11: 0 | F11: 0 | G11: 0 | H11: 0 | I11: 0 | J11: 0 | K11: 0 | L11: 0
B12: 4. Receivables according to construction contract progress | C12: 0 | D12: 0 | E12: 0 | F12: 0 | G12: 0 | H12: 0 | I12: 0 | J12: 0 | K12: 0 | L12: 0
B13: 5. Short-term loan receivable | C13: 84700 | D13: 0 | E13: 0 | F13: 80000 | G13: 961917.7 | H13: =NWC!G15 -> 1273163.6 | I13: =NWC!H15 -> 1662321.9 | J13: =NWC!I15 -> 1895181.3 | K13: =NWC!J15 -> 2124467.7 | L13: =NWC!K15 -> 2360902.8
B14: 6. Other short-term receivables | C14: 1131428.9 | D14: 1151948.8 | E14: 1357800.4 | F14: 1030943.1 | G14: 1425228.9 | H14: =NWC!G13 -> 1752897.8 | I14: =NWC!H13 -> 2044084.1 | J14: =NWC!I13 -> 2427199.1 | K14: =NWC!J13 -> 2697478.9 | L14: =NWC!K13 -> 2974814
B15: 7. Provision for short-term doubtful receivables | C15: 0 | D15: 0 | E15: 0 | F15: 0 | G15: 0 | H15: 0 | I15: 0 | J15: 0 | K15: 0 | L15: 0
B16: 8. Assets missing pending for resolution | C16: 0 | D16: 0 | E16: 0 | F16: 0 | G16: 0 | H16: 0 | I16: 0 | J16: 0 | K16: 0 | L16: 0
B17: IV. Inventory | C17: 12050163 | D17: 17446005 | E17: 25745428 | F17: 19422178 | G17: 29167232 | H17: =H18+H19 -> 33482468 | I17: =I18+I19 -> 41451060 | J17: =J18+J19 -> 44600358 | K17: =K18+K19 -> 52041136 | L17: =L18+L19 -> 55766695
B18: 1. Inventory | C18: 12309956 | D18: 17821138 | E18: 26195935 | F18: 19926364 | G18: 29850069 | H18: =NWC!G6 -> 34305807 | I18: =NWC!H6 -> 42470348 | J18: =NWC!I6 -> 45697089 | K18: =NWC!J6 -> 53320836 | L18: =NWC!K6 -> 57138007
B19: 2. Provision for devaluation of inventory | C19: -259792.8 | D19: -375132.3 | E19: -450506.2 | F19: -504186 | G19: -682836.5 | H19: =NWC!G9 -> -823339.38 | I19: =NWC!H9 -> -1019288.4 | J19: =NWC!I9 -> -1096730.1 | K19: =NWC!J9 -> -1279700.1 | L19: =NWC!K9 -> -1371312.2
B20: V. Other Current Asset | C20: 635867.5 | D20: 582987 | E20: 1199146.1 | F20: 894629.3 | G20: 1247261.4 | H20: =NWC!G37 -> 1547427.6 | I20: =NWC!H37 -> 1909696 | J20: =NWC!I37 -> 2170429 | K20: =NWC!J37 -> 2425036.6 | L20: =NWC!K37 -> 2691432.6
B21: 1. Short-term prepaid expense | C21: 338169.6 | D21: 283034.7 | E21: 487030.6 | F21: 563786.3 | G21: 569195.6 | H21: =(G21/G$20)*H$20 -> 706178.35 | I21: =(H21/H20)*I20 -> 871501.79 | J21: =(I21/I20)*J20 -> 990488.95 | K21: =(J21/J20)*K20 -> 1106680.7 | L21: =(K21/K20)*L20 -> 1228252.2
B22: 2. Deductible input VAT | C22: 297598.2 | D22: 298109.3 | E22: 709225.1 | F22: 326091.3 | G22: 636081.4 | H22: =(G22/G$20)*H$20 -> 789160.9 | I22: =(H22/H$20)*I$20 -> 973911.39 | J22: =(I22/I$20)*J$20 -> 1106880.6 | K22: =(J22/J$20)*K$20 -> 1236726.1 | L22: =(K22/K$20)*L$20 -> 1372583.4
B23: 3. Taxes and other receivables from the State budget | C23: 99.7 | D23: 1842.9 | E23: 2890.4 | F23: 4751.7 | G23: 41984.4 | H23: =(G23/G$20)*H$20 -> 52088.376 | I23: =(H23/H$20)*I$20 -> 64282.787 | J23: =(I23/I$20)*J$20 -> 73059.391 | K23: =(J23/J$20)*K$20 -> 81629.807 | L23: =(K23/K$20)*L$20 -> 90597.034
B24: 4. Government bond repurchase transaction | C24: 0 | D24: 0 | E24: 0 | F24: 0 | G24: 0 | H24: 0 | I24: 0 | J24: 0 | K24: 0 | L24: 0
B25: 5. Other current asset | C25: 0 | D25: 0 | E25: 0 | F25: 0 | G25: 0 | H25: 0 | I25: 0 | J25: 0 | K25: 0 | L25: 0
B26: B. NON-CURRENT ASSETS | C26: 3959802.9 | D26: 4750536.7 | E26: 6696198.6 | F26: 8713646 | G26: 11016147 | H26: =H27+H35+H48+H51+H57 -> 14237397 | I26: =I27+I35+I48+I51+I57 -> 18246309 | J26: =J27+J35+J48+J51+J57 -> 22383397 | K26: =K27+K35+K48+K51+K57 -> 26380090 | L26: =L27+L35+L48+L51+L57 -> 30184719
B27: I. Long-term receivables | C27: 242116 | D27: 313775.6 | E27: 374563.6 | F27: 439493.3 | G27: 482389.2 | H27: =H33 -> 482389.2 | I27: =I33 -> 482389.2 | J27: =J33 -> 482389.2 | K27: =K33 -> 482389.2 | L27: =L33 -> 482389.2
B28: 1. Long term trade receivables | C28: 0 | D28: 0 | E28: 0 | F28: 0 | G28: 0 | H28: 0 | I28: 0 | J28: 0 | K28: 0 | L28: 0
B29: 2. Long term advance to suppliers | C29: 0 | D29: 0 | E29: 0 | F29: 0 | G29: 0 | H29: 0 | I29: 0 | J29: 0 | K29: 0 | L29: 0
B30: 3. Working capital from sub-units | C30: 0 | D30: 0 | E30: 0 | F30: 0 | G30: 0 | H30: 0 | I30: 0 | J30: 0 | K30: 0 | L30: 0
B31: 4. Internal receivables | C31: 0 | D31: 0 | E31: 0 | F31: 0 | G31: 0 | H31: 0 | I31: 0 | J31: 0 | K31: 0 | L31: 0
B32: 5. Long term loan receivables | C32: 0 | D32: 0 | E32: 0 | F32: 0 | G32: 0 | H32: 0 | I32: 0 | J32: 0 | K32: 0 | L32: 0
B33: 6. Long term other receivables | C33: 242116 | D33: 313775.6 | E33: 374563.6 | F33: 439493.3 | G33: 482389.2 | H33: =G33 -> 482389.2 | I33: =H33 -> 482389.2 | J33: =I33 -> 482389.2 | K33: =J33 -> 482389.2 | L33: =K33 -> 482389.2
B34: 7. Provision for long-term bad debts | C34: 0 | D34: 0 | E34: 0 | F34: 0 | G34: 0 | H34: 0 | I34: 0 | J34: 0 | K34: 0 | L34: 0
B35: II. Fixed assets | C35: 3463658 | D35: 3333147.7 | E35: 5403777 | F35: 7294961.7 | G35: 9647168.9 | H35: =H36+H42 -> 12654930 | I35: =I36+I42 -> 16541491 | J35: =J36+J42 -> 20603131 | K35: =K36+K42 -> 24623892 | L35: =L36+L42 -> 28361814
B36: 1. Tangible fixed assets | C36: 3435848.3 | D36: 3304923.5 | E36: 5375279.2 | F36: 7267319.3 | G36: 9566954.9 | H36: =H37+H38 -> 12579624 | I36: =I37+I38 -> 16471265 | J36: =J37+J38 -> 20538155 | K36: =K37+K38 -> 24564338 | L36: =L37+L38 -> 28307613
B37: - Cost | C37: 4832699.9 | D37: 5788326.3 | E37: 9148456 | F37: 12963311 | G37: 17987088 | H37: =CAPEX!G3 -> 24255544 | I37: =CAPEX!H3 -> 32125613 | J37: =CAPEX!I3 -> 41120801 | K37: =CAPEX!J3 -> 51210083 | L37: =CAPEX!K3 -> 62328170
B38: - Accumulated depreciation | C38: -1396851.6 | D38: -2483402.8 | E38: -3773176.8 | F38: -5695992.1 | G38: -8420132.9 | H38: =CAPEX!G4 -> -11675920 | I38: =CAPEX!H4 -> -15654348 | J38: =CAPEX!I4 -> -20582645 | K38: =CAPEX!J4 -> -26645745 | L38: =CAPEX!K4 -> -34020557
B39: 2. Fixed assets of finance leasing | C39: 0 | D39: 0 | E39: 0 | F39: 0 | G39: 0
B40: - Cost | C40: 0 | D40: 0 | E40: 0 | F40: 0 | G40: 0
B41: - Accumulated depreciation | C41: 0 | D41: 0 | E41: 0 | F41: 0 | G41: 0
B42: 3. Intangible fixed assets | C42: 27809.7 | D42: 28224.1 | E42: 28497.8 | F42: 27642.4 | G42: 80213.9 | H42: =H43+H44 -> 75305.496 | I42: =I43+I44 -> 70226.019 | J42: =J43+J44 -> 64975.527 | K42: =K43+K44 -> 59554.022 | L42: =L43+L44 -> 54201.352
B43: - Cost | C43: 32779.5 | D43: 33838.4 | E43: 34852.2 | F43: 35811.6 | G43: 90297.8 | H43: =CAPEX!G37 -> 91257.2 | I43: =CAPEX!H37 -> 92216.6 | J43: =CAPEX!I37 -> 93176 | K43: =CAPEX!J37 -> 94135.4 | L43: =CAPEX!K37 -> 95094.8
B44: - Accumulated depreciation | C44: -4969.8 | D44: -5614.3 | E44: -6354.4 | F44: -8169.3 | G44: -10083.8 | H44: =CAPEX!G38 -> -15951.704 | I44: =CAPEX!H38 -> -21990.581 | J44: =CAPEX!I38 -> -28200.473 | K44: =CAPEX!J38 -> -34581.378 | L44: =CAPEX!K38 -> -40893.448
B45: III. Investment properties | C45: 0 | D45: 0 | E45: 0 | F45: 0 | G45: 0
B46: 1. Cost | C46: 0 | D46: 0 | E46: 0 | F46: 0 | G46: 0
B47: 2. Accumulated depreciation | C47: 0 | D47: 0 | E47: 0 | F47: 0 | G47: 0
B48: IV. Long term assets in progress | C48: 35457.4 | D48: 256832 | E48: 87430.4 | F48: 132620.4 | G48: 79697.9 | H48: =H50 -> 247550.34 | I48: =I50 -> 304900.73 | J48: =J50 -> 347611.48 | K48: =K50 -> 292250.14 | L48: =L50 -> 324775.09
B49: 1. Long term work in progress | C49: 0 | D49: 0 | E49: 0 | F49: 0 | G49: 0
B50: 2. Long term construction in progress | C50: 35457.4 | D50: 256832 | E50: 87430.4 | F50: 132620.4 | G50: 79697.9 | H50: =CAPEX!G92 -> 247550.34 | I50: =CAPEX!H92 -> 304900.73 | J50: =CAPEX!I92 -> 347611.48 | K50: =CAPEX!J92 -> 292250.14 | L50: =CAPEX!K92 -> 324775.09
B51: V. Long-term investments | C51: 0 | D51: 59937.8 | E51: 56464.5 | F51: 52757.5 | G51: 0 | H51: 0 | I51: 0 | J51: 0 | K51: 0 | L51: 0
B52: 1. Investments in subsidiary | C52: 0 | D52: 0 | E52: 0 | F52: 0 | G52: 0 | H52: 0 | I52: 0 | J52: 0 | K52: 0 | L52: 0
B53: 2. Investments in joint-venture, associates | C53: 0 | D53: 59937.8 | E53: 56464.5 | F53: 52757.5 | G53: 0 | H53: 0 | I53: 0 | J53: 0 | K53: 0 | L53: 0
B54: 3. Other long-term investments | C54: 0 | D54: 0 | E54: 0 | F54: 0 | G54: 0 | H54: 0 | I54: 0 | J54: 0 | K54: 0 | L54: 0
B55: 4. Provision for long-term investments | C55: 0 | D55: 0 | E55: 0 | F55: 0 | G55: 0 | H55: 0 | I55: 0 | J55: 0 | K55: 0 | L55: 0
B56: 5. Held-to-maturity investments | C56: 0 | D56: 0 | E56: 0 | F56: 0 | G56: 0 | H56: 0 | I56: 0 | J56: 0 | K56: 0 | L56: 0
B57: VI. Other long-term assets | C57: 218571.5 | D57: 786843.7 | E57: 773963.1 | F57: 793813.2 | G57: 806891.1 | H57: =SUM(H58:H62) -> 852527.73 | I57: =SUM(I58:I62) -> 917528.58 | J57: =SUM(J58:J62) -> 950265.56 | K57: =SUM(K58:K62) -> 981558.19 | L57: =SUM(L58:L62) -> 1015740.6
B58: 1. Long-term prepaid expenses | C58: 97701.1 | D58: 84768.1 | E58: 104029.5 | F58: 76720.2 | G58: 88371.4 | H58: =H122 -> 109939.03 | I58: =I122 -> 135408.79 | J58: =J122 -> 154376.96 | K58: =K122 -> 173054.08 | L58: =L122 -> 192313.52
B59: 2. Deferred tax assets | C59: 120870.5 | D59: 149548.7 | E59: 178798.7 | F59: 287349.8 | G59: 350168.4 | H59: =H127 -> 435629.34 | I59: =I127 -> 536552.3 | J59: =J127 -> 611712.99 | K59: =K127 -> 685720.37 | L59: =L127 -> 762035.22
B60: 3. Long-term equipment, materials and spare parts | C60: 0 | D60: 0 | E60: 0 | F60: 0 | G60: 0 | H60: 0 | I60: 0 | J60: 0 | K60: 0 | L60: 0
B61: 4. Other long-term assets | C61: 0 | D61: 0 | E61: 0 | F61: 0 | G61: 0 | H61: 0 | I61: 0 | J61: 0 | K61: 0 | L61: 0
B62: 5. Goodwill | C62: 0 | D62: 552526.8 | E62: 491135 | F62: 429743.1 | G62: 368351.2 | H62: =H140 -> 306959.36 | I62: =I140 -> 245567.49 | J62: =J140 -> 184175.62 | K62: =K140 -> 122783.75 | L62: =L140 -> 61391.873
B63: TOTAL ASSETS | C63: 22822664 | D63: 28122532 | E63: 41708096 | F63: 46030880 | G63: 62971405 | H63: =H26+H2 -> 82505792 | I63: =I26+I2 -> 96088341 | J63: =J26+J2 -> 1.1030009e+08 | K63: =K26+K2 -> 1.2287714e+08 | L63: =L26+L2 -> 1.4987962e+08
B64: C. LIABILITIES | C64: 16913748 | D64: 19139496 | E64: 29564503 | F64: 30549190 | G64: 42593159 | H64: =H65+H78 -> 48689810 | I64: =I65+I78 -> 55454771 | J64: =J65+J78 -> 60374896 | K64: =K65+K78 -> 61467261 | L64: =L65+L78 -> 75401436
B65: I. Current liabilities | C65: 15713815 | D65: 17929433 | E65: 28442367 | F65: 29422513 | G65: 42593159 | H65: =SUM(H66:H77) -> 48689810 | I65: =SUM(I66:I77) -> 55454771 | J65: =SUM(J66:J77) -> 60374896 | K65: =SUM(K66:K77) -> 61467261 | L65: =SUM(L66:L77) -> 75401436
B66: 1. Trade payables | C66: 7373229.7 | D66: 8244614.2 | E66: 12055386 | F66: 8728168.9 | G66: 12179775 | H66: =NWC!G19 -> 15135735 | I66: =NWC!H19 -> 18702137 | J66: =NWC!I19 -> 19094692 | K66: =NWC!J19 -> 23772779 | L66: =NWC!K19 -> 23817648
B67: 2. Advances from customers | C67: 22475.5 | D67: 38061.6 | E67: 81194.1 | F67: 86907.4 | G67: 98379.3 | H67: =NWC!G21 -> 122389.43 | I67: =NWC!H21 -> 150743.58 | J67: =NWC!I21 -> 171859.87 | K67: =NWC!J21 -> 192652.14 | L67: =NWC!K21 -> 214092.68
B68: 3. Statutory obligations | C68: 137421.6 | D68: 217699.6 | E68: 374623.3 | F68: 634917.9 | G68: 696559 | H68: =NWC!G23 -> 887207.76 | I68: =NWC!H23 -> 1092748.6 | J68: =NWC!I23 -> 1267301.4 | K68: =NWC!J23 -> 1420624.4 | L68: =NWC!K23 -> 1578727.8
B69: 4. Payables to employees | C69: 133725.1 | D69: 149775 | E69: 258242.3 | F69: 533572.3 | G69: 531987.4 | H69: =NWC!G25 -> 697776.16 | I69: =NWC!H25 -> 875728.03 | J69: =NWC!I25 -> 1011880.4 | K69: =NWC!J25 -> 1149115.7 | L69: =NWC!K25 -> 1295918.9
B70: 5. Accrued expenses | C70: 1585372.4 | D70: 2173064.9 | E70: 1851967 | F70: 3191005.4 | G70: 3885356.4 | H70: =NWC!G27 -> 4640871 | I70: =NWC!H27 -> 5838129.2 | J70: =NWC!I27 -> 6572261.2 | K70: =NWC!J27 -> 7378406.7 | L70: =NWC!K27 -> 8169425.4
B71: 6. Payables to related parties | C71: 0 | D71: 0 | E71: 0 | F71: 0 | G71: 0 | H71: 0 | I71: 0 | J71: 0 | K71: 0 | L71: 0
B72: 7. Payables from construction contract | C72: 0 | D72: 0 | E72: 0 | F72: 0 | G72: 0 | H72: 0 | I72: 0 | J72: 0 | K72: 0 | L72: 0
B73: 8. Short-term deferred revenue | C73: 0 | D73: 0 | E73: 333.6 | F73: 308.4 | G73: 0 | H73: 0 | I73: 0 | J73: 0 | K73: 0 | L73: 0
B74: 9. Other short-term payables | C74: 807310.1 | D74: 1208214.3 | E74: 717884.7 | F74: 546045.4 | G74: 476319.9 | H74: =NWC!G31 -> 681037.63 | I74: =NWC!H31 -> 784332.55 | J74: =NWC!I31 -> 925259.55 | K74: =NWC!J31 -> 1019793.8 | L74: =NWC!K31 -> 1142960.4
B75: 10. Short-term loan and payable for finance leasing | C75: 5603506 | D75: 5836454.6 | E75: 13031016 | F75: 15625180 | G75: 24647474 | H75: ='FI&FE'!G10 -> 26421481 | I75: ='FI&FE'!H10 -> 27881028 | J75: ='FI&FE'!I10 -> 31198669 | K75: ='FI&FE'!J10 -> 26363518 | L75: ='FI&FE'!K10 -> 39019522
B76: 11. Provision for short-term payable | C76: 45824.5 | D76: 56568.6 | E76: 71690.5 | F76: 76377.4 | G76: 77277.6 | H76: =NWC!G29 -> 103281.56 | I76: =NWC!H29 -> 129894.41 | J76: =NWC!I29 -> 132942.24 | K76: =NWC!J29 -> 170340.57 | L76: =NWC!K29 -> 163110.37
B77: 12. Reward and welfare funds | C77: 4950 | D77: 4980.1 | E77: 30.1 | F77: 30.1 | G77: 30.1 | H77: =G77 -> 30.1 | I77: =H77 -> 30.1 | J77: =I77 -> 30.1 | K77: =J77 -> 30.1 | L77: =K77 -> 30.1
B78: II. Non-current liabilities | C78: 1199933 | D78: 1210063.2 | E78: 1122136.7 | F78: 1126676.7 | G78: 0 | H78: 0 | I78: 0 | J78: 0 | K78: 0 | L78: 0
B79: 1. Long term trade payables | C79: 0 | D79: 0 | E79: 0 | F79: 0 | G79: 0 | H79: 0 | I79: 0 | J79: 0 | K79: 0 | L79: 0
B80: 2. Long term advance to customers | C80: 0 | D80: 0 | E80: 0 | F80: 0 | G80: 0 | H80: 0 | I80: 0 | J80: 0 | K80: 0 | L80: 0
B81: 3. Long term accruals | C81: 0 | D81: 0 | E81: 0 | F81: 0 | G81: 0 | H81: 0 | I81: 0 | J81: 0 | K81: 0 | L81: 0
B82: 4. Working capital from subunits | C82: 0 | D82: 0 | E82: 0 | F82: 0 | G82: 0 | H82: 0 | I82: 0 | J82: 0 | K82: 0 | L82: 0
B83: 5. Long term payables to related parties | C83: 0 | D83: 0 | E83: 0 | F83: 0 | G83: 0 | H83: 0 | I83: 0 | J83: 0 | K83: 0 | L83: 0
B84: 6. Long term deferred revenue | C84: 0 | D84: 0 | E84: 0 | F84: 0 | G84: 0 | H84: 0 | I84: 0 | J84: 0 | K84: 0 | L84: 0
B85: 7. Other long term liabilities | C85: 0 | D85: 0 | E85: 0 | F85: 0 | G85: 0 | H85: 0 | I85: 0 | J85: 0 | K85: 0 | L85: 0
B86: 8. Long term loans and debts | C86: 1199933 | D86: 1208167.1 | E86: 1122136.7 | F86: 1126676.7 | G86: 0 | H86: 0 | I86: 0 | J86: 0 | K86: 0 | L86: 0
B87: 9. Convertible bond | C87: 0 | D87: 0 | E87: 0 | F87: 0 | G87: 0 | H87: 0 | I87: 0 | J87: 0 | K87: 0 | L87: 0
B88: 10. Preference shares | C88: 0 | D88: 0 | E88: 0 | F88: 0 | G88: 0 | H88: 0 | I88: 0 | J88: 0 | K88: 0 | L88: 0
B89: 11. Deferred tax liabilities | C89: 0 | D89: 1896 | E89: 0 | F89: 0 | G89: 0 | H89: 0 | I89: 0 | J89: 0 | K89: 0 | L89: 0
... B91: 13. The development of science and technology fund | C91: 0 | D91: 0 | E91: 0 | F91: 0 | G91: 0 | H91: 0 | I91: 0 | J91: 0 | K91: 0 | L91: 0
B92: D. OWNER’S EQUITY | C92: 5908916.3 | D92: 8983035.3 | E92: 12143592 | F92: 15481690 | G92: 20378246 | H92: =H93 -> 33815982 | I92: =I93 -> 40633570 | J92: =J93 -> 49925192 | K92: =K93 -> 61409878 | L92: =L93 -> 74478188
B93: I. Capital | C93: 5908916.3 | D93: 8983035.3 | E93: 12143592 | F93: 15481690 | G93: 20378246 | H93: =H94+H97+H100+H102+H106+H110 -> 33815982 | I93: =I94+I97+I100+I102+I106+I110 -> 40633570 | J93: =J94+J97+J100+J102+J106+J110 -> 49925192 | K93: =K94+K97+K100+K102+K106+K110 -> 61409878 | L93: =L94+L97+L100+L102+L106+L110 -> 74478188
B94: 1. Contributed chartered capital | C94: 3169884.4 | D94: 4434961.8 | E94: 4435461.8 | F94: 4532099.9 | G94: 7130655 | H94: =EQUITY!G3 -> 14645795 | I94: =EQUITY!H3 -> 14645795 | J94: =EQUITY!I3 -> 14645795 | K94: =EQUITY!J3 -> 14645795 | L94: =EQUITY!K3 -> 14645795
B95: - Ordinary shares | C95: 3169884.4 | D95: 4434961.8 | E95: 4435461.8 | F95: 4532099.9 | G95: 7130655 | H95: =H94 -> 14645795 | I95: =I94 -> 14645795 | J95: =J94 -> 14645795 | K95: =K94 -> 14645795 | L95: =L94 -> 14645795
B96: - Preference shares | C96: 0 | D96: 0 | E96: 0 | F96: 0 | G96: 0 | H96: 0 | I96: 0 | J96: 0 | K96: 0 | L96: 0
B97: 2. Share premium | C97: 36717.7 | D97: 551452 | E97: 555207 | F97: 558110.4 | G97: 558110.4 | H97: =EQUITY!G4 -> 558110.41 | I97: =EQUITY!H4 -> 558110.41 | J97: =EQUITY!I4 -> 558110.41 | K97: =EQUITY!J4 -> 558110.41 | L97: =EQUITY!K4 -> 558110.41
B98: 3. Bond option | C98: 0 | D98: 0 | E98: 0 | F98: 0 | G98: 0 | H98: 0 | I98: 0 | J98: 0 | K98: 0 | L98: 0
B99: 4. Other equity | C99: 1130.5 | D99: 1130.5 | E99: 1130.5 | F99: 0 | G99: 0 | H99: 0 | I99: 0 | J99: 0 | K99: 0 | L99: 0
B100: 5. Treasury shares | C100: -79.2 | D100: -808.9 | E100: -5658.9 | F100: -6040.9 | G100: -2320 | H100: =EQUITY!G6 -> -2320 | I100: =EQUITY!H6 -> -2320 | J100: =EQUITY!I6 -> -2320 | K100: =EQUITY!J6 -> -2320 | L100: =EQUITY!K6 -> -2320
B101: 6. Asset revaluation difference | C101: 0 | D101: 0 | E101: 0 | F101: 0 | G101: 0
...

Sheet CF
A1: CASH FLOW STATEMENT (Unit: Million VND) | B1: 2017 | C1: 2018 | D1: 2019 | E1: 2020 | F1: 2021 | G1: 2022F | H1: 2023F | I1: 2024F | J1: 2025F | K1: 2026F
A2: I. CASH FLOWS FROM OPERATING ACTIVITIES
A3: 1. Net profit before tax | B3: =IS!B18 -> 2206897.1 | C3: =IS!C18 -> 2880309.1 | D3: =IS!D18 -> 3836240.1 | E3: =IS!E18 -> 3919872.7 | F3: =IS!F18 -> 4901426.7 | G3: =IS!G18 -> 6654885.6 | H3: =IS!H18 -> 8282167.8 | I3: =IS!I18 -> 10756201 | ... K3: =IS!K18 -> 14532889 | L3: CF1
A4: Adjustments for:
A5: Depreciation and amortisation | B5: =DATA!C197 -> 689713.7 | C5: =DATA!D197 -> 1222868.7 | D5: =DATA!E197 -> 1442826.9 | E5: =DATA!F197 -> 2195583.1 | F5: =DATA!G197 -> 2920713.6 | G5: =SUMIF(BS!$A$274:$A$384,$L5,BS!H$274:H$384) -> 3323046.8 | H5: =SUMIF(BS!$A$274:$A$384,$L5,BS!I$274:I$384) -> 4045858.9 | I5: =SUMIF(BS!$A$274:$A$384,$L5,BS!J$274:J$384) -> 4995898.7 | J5: =SUMIF(BS!$A$274:$A$384,$L5,BS!K$274:K$384) -> 6130873 | K5: =SUMIF(BS!$A$274:$A$384,$L5,BS!L$274:L$384) -> 7442515.6 | L5: CF2
A6: Provision for decline in value of investments | B6: =DATA!C198 -> 125969 | C6: =DATA!D198 -> 126083.6 | D6: =DATA!E198 -> 90495.8 | E6: =DATA!F198 -> 58366.7 | F6: =DATA!G198 -> 179550.7 | G6: =SUMIF(BS!$A$274:$A$384,$L6,BS!H$274:H$384) -> 166506.84 | H6: =SUMIF(BS!$A$274:$A$384,$L6,BS!I$274:I$384) -> 222561.83 | I6: =SUMIF(BS!$A$274:$A$384,$L6,BS!J$274:J$384) -> 80489.6 | J6: =SUMIF(BS!$A$274:$A$384,$L6,BS!K$274:K$384) -> 220368.26 | K6: =SUMIF(BS!$A$274:$A$384,$L6,BS!L$274:L$384) -> 84381.911 | L6: CF3
A7: NWC | B7: =SUM(DATA!C208:C212) -> -245716 | C7: =SUM(DATA!D208:D212) -> -1968501.2 | D7: =SUM(DATA!E208:E212) -> -6454639.6 | E7: =SUM(DATA!F208:F212) -> 5150738.3 | F7: =SUM(DATA!G208:G212) -> -6997177 | G7: =SUMIF(BS!$A$274:$A$384,$L7,BS!H$274:H$384) -> -807144.87 | H7: =SUMIF(BS!$A$274:$A$384,$L7,BS!I$274:I$384) -> -3946974.2 | I7: =SUMIF(BS!$A$274:$A$384,$L7,BS!J$274:J$384) -> -2166076.8 | J7: =SUMIF(BS!$A$274:$A$384,$L7,BS!K$274:K$384) -> -2602099.8 | K7: =SUMIF(BS!$A$274:$A$384,$L7,BS!L$274:L$384) -> -2962129.3 | L7: CF5
A8: Other adjustment | B8: =B10-SUM(B3:B7) -> -113199.8 | C8: =C10-SUM(C3:C7) -> 374.3 | D8: =D10-SUM(D3:D7) -> -201004 | E8: =E10-SUM(E3:E7) -> -532131.6 | F8: =F10-SUM(F3:F7) -> -833123.6 | G8: =SUMIF(BS!$A$274:$A$384,$L8,BS!H$274:H$384) -> -407194.79 | H8: =SUMIF(BS!$A$274:$A$384,$L8,BS!I$274:I$384) -> -488661.05 | I8: =SUMIF(BS!$A$274:$A$384,$L8,BS!J$274:J$384) -> -354861.89 | J8: =SUMIF(BS!$A$274:$A$384,$L8,BS!K$274:K$384) -> -347292.14 | K8: =SUMIF(BS!$A$274:$A$384,$L8,BS!L$274:L$384) -> -361970.29 | L8: CF4
A10: Net cashflow from operating activities | B10: =DATA!C194 -> 2663664 | C10: =DATA!D194 -> 2261134.5 | D10: =DATA!E194 -> -1286080.8 | E10: =DATA!F194 -> 10792429 | F10: =DATA!G194 -> 171390.4 | G10: =SUM(G3:G8) -> 8930099.5 | H10: =SUM(H3:H8) -> 8114953.3 | I10: =SUM(I3:I8) -> 13311651 | J10: =SUM(J3:J8) -> 16351115 | K10: =SUM(K3:K8) -> 18735687
A11: II.CASH FLOWS FROM INVESTING ACTIVITIES
A12: Purchase and construction of fixed assets and other long-term assets | B12: =DATA!C219 -> -2065069.6 | C12: =DATA!D219 -> -1495931.9 | D12: =DATA!E219 -> -3066921.2 | E12: =DATA!F219 -> -3911358.2 | F12: =DATA!G219 -> -4976876.6 | G12: =SUMIF(BS!$A$274:$A$384,$L12,BS!H$274:H$384) -> -6437268.3 | H12: =SUMIF(BS!$A$274:$A$384,$L12,BS!I$274:I$384) -> -7928378.5 | I12: =SUMIF(BS!$A$274:$A$384,$L12,BS!J$274:J$384) -> -9038857.8 | J12: =SUMIF(BS!$A$274:$A$384,$L12,BS!K$274:K$384) -> -10034881 | K12: =SUMIF(BS!$A$274:$A$384,$L12,BS!L$274:L$384) -> -11151571 | L12: CF6
A13: Proceeds from disposals of assets | B13: =DATA!C220 -> 180 | C13: =DATA!D220 -> 1340 | D13: =DATA!E220 -> 1290.8 | E13: =DATA!F220 -> 2018.1 | F13: =DATA!G220 -> 1107
A14: Loans provided to related parties and other | B14: =DATA!C221 -> -210280 | C14: =DATA!D221 -> -85922.5 | D14: =DATA!E221 -> -8997469.9 | E14: =DATA!F221 -> -11512469 | F14: =DATA!G221 -> -19225219
A15: Collection of loans provided to related parties and other | B15: =DATA!C222 -> 125580 | C15: =DATA!D222 -> 0 | D15: =DATA!E222 -> 5911392.3 | E15: =DATA!F222 -> 6512150.1 | F15: =DATA!G222 -> 12163994
A16: Payments for equity investments in other entities | B16: =DATA!C223 -> 0 | C16: =DATA!D223 -> -828166.5 | D16: =DATA!E223 -> 0 | E16: =DATA!F223 -> 0 | F16: =DATA!G223 -> -16385
A17: Proceed from collection investment in other entity | B17: =DATA!C224 -> 0 | C17: =DATA!D224 -> 0 | D17: =DATA!E224 -> 0 | E17: =DATA!F224 -> 0 | F17: =DATA!G224 -> 0
A18: Interest and dividend received | B18: =DATA!C225 -> 29374.6 | C18: =DATA!D225 -> 64286.8 | D18: =DATA!E225 -> 278946.3 | E18: =DATA!F225 -> 335398 | F18: =DATA!G225 -> 798510.2 | L18: CF7
A19: Proceed from other investment acitivities | B19: =DATA!C226 -> 0 | C19: =DATA!D226 -> 0 | D19: =DATA!E226 -> 0 | E19: =DATA!F226 -> 0 | F19: =DATA!G226 -> 0
A20: Net cashflow from investing | B20: =SUM(B12:B19) -> -2120215 | C20: =SUM(C12:C19) -> -2344394.1 | D20: =SUM(D12:D19) -> -5872761.7 | E20: =SUM(E12:E19) -> -8574261 | F20: =SUM(F12:F19) -> -11254870 | G20: =SUM(G12:G19) -> -6437268.3 | H20: =SUM(H12:H19) -> -7928378.5 | I20: =SUM(I12:I19) -> -9038857.8 | ... K20: =SUM(K12:K19) -> -11151571
A22: III. CASH FLOWS FROM FINANCING ACTIVITIES
A23: Proceeds from issuance of ordinary shares | B23: =DATA!C229 -> 92466.5 | C23: =DATA!D229 -> 703840.2 | D23: =DATA!E229 -> 90454.8 | E23: =DATA!F229 -> 105200.4 | F23: =DATA!G229 -> 228253 | G23: =SUMIF(BS!$A$274:$A$384,$L23,BS!H$274:H$384) -> 7515139.8 | H23: =SUMIF(BS!$A$274:$A$384,$L23,BS!I$274:I$384) -> 0 | I23: =SUMIF(BS!$A$274:$A$384,$L23,BS!J$274:J$384) -> 0 | J23: =SUMIF(BS!$A$274:$A$384,$L23,BS!K$274:K$384) -> 0 | K23: =SUMIF(BS!$A$274:$A$384,$L23,BS!L$274:L$384) -> 0 | L23: CF9
A24: Money to return contributed capital to owners, buy back shares of the issued enterprise | B24: =DATA!C230 -> 0 | C24: =DATA!D230 -> -729.7 | D24: =DATA!E230 -> -4850.1 | E24: =DATA!F230 -> -6040.9 | F24: =DATA!G230 -> -2320 | K24: =SUMIF(BS!$A$274:$A$384,$L24,BS!L$274:L$384) -> 0
A25: Payments of loan | B25: =DATA!C231 -> 29465789 | C25: =DATA!D231 -> 31893805 | D25: =DATA!E231 -> 45905952 | E25: =DATA!F231 -> 51168161 | F25: =DATA!G231 -> 63936208 | G25: ='FI&FE'!G7 -> 72142959 | H25: ='FI&FE'!H7 -> 87572803 | I25: ='FI&FE'!I7 -> 1.0118804e+08 | J25: ='FI&FE'!J7 -> 1.0266277e+08 | K25: ='FI&FE'!K7 -> 1.3196283e+08
A26: Payments for principal of finance leaser | B26: =DATA!C232 -> -27456000 | C26: =DATA!D232 -> -31690849 | D26: =DATA!E232 -> -38801962 | E26: =DATA!F232 -> -48573997 | F26: =DATA!G232 -> -56045131 | G26: ='FI&FE'!G8 -> -70368952 | H26: ='FI&FE'!H8 -> -86113256 | I26: ='FI&FE'!I8 -> -97870400 | J26: ='FI&FE'!J8 -> -1.0749792e+08 | K26: ='FI&FE'!K8 -> -1.1930682e+08
A27: Dividend paid to owner | B27: =DATA!C234 -> -231718.9 | C27: =DATA!D234 -> -485862.4 | D27: =DATA!E234 -> -665093.5 | E27: =DATA!F234 -> -678908.8 | F27: =DATA!G234 -> -239519.4 | G27: =EQUITY!G49 -> -732289.74 | H27: =EQUITY!H49 -> -1464579.5 | I27: =EQUITY!I49 -> -1464579.5 | J27: =EQUITY!J49 -> -1464579.5 | K27: =EQUITY!K49 -> -1464579.5 | L27: CF8
A28: Net cashflow from financing activities | B28: =SUM(B23:B27) -> 1870536.6 | C28: =SUM(C23:C27) -> 420204.6 | D28: =SUM(D23:D27) -> 6524501.7 | E28: =SUM(E23:E27) -> 2014415.4 | F28: =SUM(F23:F27) -> 7877490.8 | G28: =SUM(G23:G27) -> 8556857.3 | H28: =SUM(H23:H27) -> -5032.7699 | I28: =SUM(I23:I27) -> 1853061.2 | ... K28: =SUM(K23:K27) -> 11191425
A29: Net cash flow during the period | B29: =DATA!C237 -> 2413985.5 | C29: =DATA!D237 -> 338459.8 | D29: =DATA!E237 -> -634340.6 | E29: =DATA!F237 -> 4232583.7 | F29: =DATA!G237 -> -3205988.3 | G29: =G28+G20+G10 -> 11049689 | H29: =H28+H20+H10 -> 181542.12 | I29: =I28+I20+I10 -> 6125854.2 | J29: =J28+J20+J10 -> 16503.776 | K29: =K28+K20+K10 -> 18775541
A30: Cash and cash equivalents at the beginning of the period | B30: =DATA!C239 -> 996983.5 | C30: =DATA!D239 -> 3410983.4 | D30: =DATA!E239 -> 3749550.3 | E30: =DATA!F239 -> 3115236.8 | F30: =DATA!G239 -> 7347857.4 | G30: =F31 -> 4142015.8 | H30: =G31 -> 15191704 | I30: =H31 -> 15373246 | J30: =I31 -> 21499101 | K30: =J31 -> 21515604
A31: Cash and cash equivalents at the end of the period | B31: =DATA!C241 -> 3410983.4 | C31: =DATA!D241 -> 3749550.3 | D31: =DATA!E241 -> 3115236.8 | E31: =DATA!F241 -> 7347857.4 | F31: =DATA!G241 -> 4142015.8 | G31: =G29+G30 -> 15191704 | H31: =H29+H30 -> 15373246 | I31: =I29+I30 -> 21499101 | J31: =J29+J30 -> 21515604 | K31: =K29+K30 -> 40291145

Sheet FI&FE
B1: 2017A | C1: 2018A | D1: 2019A | E1: 2020A | F1: 2021A | G1: 2022F | H1: 2023F | I1: 2024F | J1: 2025F | K1: 2026F
A2: Interest expense | B2: =IS!B7 -> 233202.3 | C2: =IS!C7 -> 436416.6 | D2: =IS!D7 -> 568136.7 | E2: =IS!E7 -> 594003.8 | F2: =IS!F7 -> 674427.7 | G2: =G11*AVERAGE(F10:G10) -> 893706.73 | H2: =H11*AVERAGE(G10:H10) -> 950293.92 | I2: =I11*AVERAGE(H10:I10) -> 1092974.4 | J2: =J11*AVERAGE(I10:J10) -> 1064900.5 | K2: =K11*AVERAGE(J10:K10) -> 1209586.2
A4: Short-term debt
A6: Outstanding debt | B6: 4788991.7 | C6: =B10 -> 5603506 | D6: =C10 -> 5836454.6 | E6: =D10 -> 13031016 | F6: =E10 -> 15625180 | G6: =F10 -> 24647474 | H6: =G10 -> 26421481 | I6: =H10 -> 27881028 | J6: =I10 -> 31198669 | K6: =J10 -> 26363518
A7: New debt during the period | B7: 28195514 | C7: 31656568 | D7: 45690847 | E7: 51168161 | F7: 65067425 | G7: =G14*G13 -> 72142959 | H7: =H14*H13 -> 87572803 | I7: =I14*I13 -> 1.0118804e+08 | J7: =J14*J13 -> 1.0266277e+08 | K7: =K14*K13 -> 1.3196283e+08
A8: Principal payment | B8: -27456000 | C8: -31688849 | D8: -38632142 | E8: -48573997 | F8: -56045131 | G8: =G17*IS!G3 -> -70368952 | H8: =H17*IS!H3 -> -86113256 | I8: =I17*IS!I3 -> -97870400 | J8: =J17*IS!J3 -> -1.0749792e+08 | K8: =K17*IS!K3 -> -1.1930682e+08
A9: Reclassify | B9: 75000 | C9: 265228.8 | D9: 135855.7 | E9: 0 | F9: 0 | G9: 0 | H9: 0 | I9: 0 | J9: 0 | K9: 0
A10: Ending outstanding debt | B10: =SUM(B6:B9) -> 5603506 | C10: =SUM(C6:C9) -> 5836454.6 | D10: =SUM(D6:D9) -> 13031016 | E10: =SUM(E6:E9) -> 15625180 | F10: =SUM(F6:F9) -> 24647474 | G10: =SUM(G6:G9) -> 26421481 | H10: =SUM(H6:H9) -> 27881028 | I10: =SUM(I6:I9) -> 31198669 | ... K10: =SUM(K6:K9) -> 39019522
A11: Interest rate | F11: =F2/AVERAGE(E10:F10) -> 0.033493084 | G11: 0.035 | H11: 0.035 | I11: 0.037 | J11: 0.037 | K11: 0.037
A13: Purchasing during the period | C13: =IS!C3+BS!D4-BS!C4 -> 71275082 | D13: =IS!D3+BS!E4-BS!D4 -> 85772522 | E13: =IS!E3+BS!F4-BS!E4 -> 89511841 | F13: =IS!F3+BS!G4-BS!F4 -> 1.0150528e+08 | G13: =IS!G3+BS!H4-BS!G4 -> 1.1826715e+08 | H13: =IS!H3+BS!I4-BS!H4 -> 1.4595467e+08 | I13: =IS!I3+BS!J4-BS!I4 -> 1.6588203e+08 | J13: =IS!J3+NWC!A41-BS!J4 -> 1.7110462e+08 | K13: =IS!K3+BS!L4-NWC!A41 -> 2.1993804e+08
A14: New debt/Purchasing | C14: =C7/C13 -> 0.44414637 | D14: =D7/D13 -> 0.53269796 | E14: =E7/E13 -> 0.57163567 | F14: =F7/F13 -> 0.64102502 | G14: 0.61 | H14: 0.6 | I14: 0.61 | J14: 0.6 | K14: 0.6
A15: Debt payment/Purcharsing | C15: =C8/C13 -> -0.44459926 | D15: =D8/D13 -> -0.45040231 | E15: =E8/E13 -> -0.54265442 | F15: =F8/F13 -> -0.55214005 | G15: =G8/G13 -> -0.595 | H15: =H8/H13 -> -0.59 | I15: =I8/I13 -> -0.59 | J15: =J8/J13 -> -0.62825845 | K15: =K8/K13 -> -0.5424565
A16: Change | C16: =C14+C15 -> -0.00045289601 | D16: =D14+D15 -> 0.082295648 | E16: =E14+E15 -> 0.028981246 | F16: =F14+F15 -> 0.088884971 | G16: =G14+G15 -> 0.015 | H16: =H14+H15 -> 0.01 | I16: =I14+I15 -> 0.02 | J16: =J14+J15 -> -0.028258448 | K16: =K14+K15 -> 0.057543497
A17: % Debt payment / COGS | B17: =B8/IS!B3 -> -0.49740911 | C17: =C8/IS!C3 -> -0.44491713 | D17: =D8/IS!D3 -> -0.46721252 | E17: =E8/IS!E3 -> -0.57421826 | F17: =F8/IS!F3 -> -0.58793137 | G17: =-59.5% -> -0.595 | H17: =-59% -> -0.59 | I17: =-59% -> -0.59 | J17: =-58% -> -0.58 | K17: =-58% -> -0.58

Sheet CAPEX
B1: 2017A | C1: 2018A | D1: 2019A | E1: 2020A | F1: 2021A | G1: 2022F | H1: 2023F | I1: 2024F | J1: 2025F | K1: 2026F
A2: Tangible fixed assets
A3: Historical cost | B3: =DATA!C51 -> 4832699.9 | C3: =DATA!D51 -> 5788326.3 | D3: =DATA!E51 -> 9148456 | E3: =DATA!F51 -> 12963311 | F3: =DATA!G51 -> 17987088 | G3: =G13 -> 24255544 | H3: =H13 -> 32125613 | I3: =I13 -> 41120801 | J3: =J13 -> 51210083 | K3: =K13 -> 62328170
A4: Accumulated depreciation | B4: =DATA!C52 -> -1396851.6 | C4: =DATA!D52 -> -2483402.8 | D4: =DATA!E52 -> -3773176.8 | E4: =DATA!F52 -> -5695992.1 | F4: =DATA!G52 -> -8420132.9 | G4: =G20 -> -11675920 | H4: =H20 -> -15654348 | I4: =I20 -> -20582645 | J4: =J20 -> -26645745 | K4: =K20 -> -34020557
A5: Forecasted value in detail
A6: Historical cost
A7: Beginning of period | B7: 2784487.1 | C7: =B13 -> 4832699.9 | D7: =C13 -> 5788326.3 | E7: =D13 -> 9148456 | F7: =E13 -> 12963311 | G7: =F13 -> 17987088 | H7: =G13 -> 24255544 | I7: =H13 -> 32125613 | J7: =I13 -> 41120801 | K7: =J13 -> 51210083
A8: New purchase | B8: 1968890.7 | C8: 864817.4 | D8: 2954660.4 | E8: 4006670.4 | F8: 4974659.6 | G8: =F8*(1+G93) -> 6188758.5 | H8: =G8*(1+H93) -> 7622518.3 | I8: =H8*(1+I93) -> 8690286.9 | J8: =I8*(1+J93) -> 9741671.2 | K8: =J8*(1+K93) -> 10825836
A9: Transfer from Construction in progress | B9: 84124.077 | C9: 56017.785 | D9: 500065.44 | E9: 29559.191 | F9: 98332.124 | G9: =-G90 -> 79697.9 | H9: =-H90 -> 247550.34 | I9: =-I90 -> 304900.73 | J9: =-J90 -> 347611.48 | K9: =-K90 -> 292250.14
A10: Liquiditate | B10: -4669.417 | C10: -153744.65 | D10: -94596.179 | E10: -221374.21 | F10: -159449.22 | G10: 0 | H10: 0 | I10: 0 | J10: 0 | K10: 0
A11: Reclassifying | B11: -132.614 | C11: 0 | D11: 0 | E11: 0 | F11: 0 | G11: 0 | H11: 0 | I11: 0 | J11: 0 | K11: 0
A12: Increase due to M&A | B12: 0 | C12: 188535.89 | D12: 0 | E12: 0 | F12: 110233.93 | G12: 0 | H12: 0 | I12: 0 | J12: 0 | K12: 0
A13: Ending balance | B13: =SUM(B7:B12) -> 4832699.9 | C13: =SUM(C7:C12) -> 5788326.3 | D13: =SUM(D7:D12) -> 9148456 | E13: =SUM(E7:E12) -> 12963311 | F13: =SUM(F7:F12) -> 17987088 | G13: =SUM(G7:G9) -> 24255544 | H13: =SUM(H7:H9) -> 32125613 | I13: =SUM(I7:I9) -> 41120801 | J13: =SUM(J7:J9) -> 51210083 | K13: =SUM(K7:K9) -> 62328170
A14: Accumulated depreciation
A15: Beginning of period | B15: -714678.34 | C15: =B20 -> -1396851.6 | D15: =C20 -> -2483402.8 | E15: =D20 -> -3773176.8 | F15: =E20 -> -5695992.1 | G15: =F20 -> -8420132.9 | H15: =G20 -> -11675920 | I15: =H20 -> -15654348 | J15: =I20 -> -20582645 | K15: =J20 -> -26645745
A16: Depriciation during the period | B16: -686732.39 | C16: -1160832.3 | D16: -1380695 | E16: -2132376.3 | F16: -2857407.2 | G16: =-G30 -> -3255787.1 | H16: =-H30 -> -3978428.2 | I16: =-I30 -> -4928296.9 | J16: =-J30 -> -6063100.2 | K16: =-K30 -> -7374811.7
A17: Liquiditate | B17: 4541.91 | C17: 152404.57 | D17: 90920.961 | E17: 209561.01 | F17: 149436.69
A18: Reclassifying | B18: 17.25 | C18: 0 | D18: 0 | E18: 0 | F18: 0
A19: Increase due to M&A | B19: 0 | C19: -78123.586 | D19: 0 | E19: 0 | F19: -16170.316
A20: Ending balance | B20: =SUM(B15:B19) -> -1396851.6 | C20: =C4 -> -2483402.8 | D20: =SUM(D15:D19) -> -3773176.8 | E20: =SUM(E15:E19) -> -5695992.1 | F20: =SUM(F15:F19) -> -8420132.9 | G20: =SUM(G15:G16) -> -11675920 | H20: =SUM(H15:H16) -> -15654348 | I20: =SUM(I15:I16) -> -20582645 | J20: =SUM(J15:J16) -> -26645745 | K20: =SUM(K15:K16) -> -34020557
A21: Average depreciable life | F21: =F13/-F16 -> 6.2948984
A22: Average depreciable life (years)(round-up) | F22: 6
A23: Annual depreciation rate (%) | F23: =1/F22 -> 0.16666667
A24: Depreciation of buildings and current investment structures | F24: =-F16 -> 2857407.2 | G24: =SYD($F$34,0,$F$22,1) -> 2733415.7 | H24: =SYD($F$34,0,$F$22,2) -> 2277846.4 | I24: =SYD($F$34,0,$F$22,3) -> 1822277.1 | J24: =SYD($F$34,0,$F$22,4) -> 1366707.8 | K24: =SYD($F$34,0,$F$22,5) -> 911138.56
A25: Depreciation of buildings and additional investment structures from 2022 | E25: Mid. Year adj. | F25: 0.5 | G25: =(SUM(G8:G9)/F22)*F25 -> 522371.37 | H25: =(SUM($G$8:$G$9)*$F$23) -> 1044742.7 | I25: =(SUM($G$8:$G$9)*$F$23) -> 1044742.7 | J25: =(SUM($G$8:$G$9)*$F$23) -> 1044742.7 | K25: =(SUM($G$8:$G$9)*$F$23) -> 1044742.7
A26: Depreciation of buildings and additional investment structures from 2023 | H26: =F25*SUM($H$8:$H$9)*$F$23 -> 655839.05 | I26: =SUM($H$8:$H$9)*$F$23 -> 1311678.1 | J26: =SUM($H$8:$H$9)*$F$23 -> 1311678.1 | K26: =SUM($H$8:$H$9)*$F$23 -> 1311678.1
A27: Depreciation of buildings and additional investment structures from 2024 | I27: =J27*F25 -> 749598.97 | J27: =SUM($I$8:$I$9)*$F$23 -> 1499197.9 | K27: =SUM($I$8:$I$9)*$F$23 -> 1499197.9
A28: Depreciation of buildings and additional investment structures from 2025 | J28: =K28*F25 -> 840773.56 | K28: =SUM($J$8:$J$9)*$F$23 -> 1681547.1
A29: Depreciation of buildings and additional investment structures from 2026 | K29: =F25*SUM(K8:K9)*F23 -> 926507.21
A30: Depreciation of buildings and structures over the years | G30: =SUM(G24:G29) -> 3255787.1 | H30: =SUM(H24:H29) -> 3978428.2 | I30: =SUM(I24:I29) -> 4928296.9 | J30: =SUM(J24:J29) -> 6063100.2 | K30: =SUM(K24:K29) -> 7374811.7
A32: Salvage value
A33: Beginning balance | B33: 1780323.7 | C33: =B34 -> 3435848.3 | D33: =C34 -> 3304923.5 | E33: =D34 -> 5375279.2 | F33: =E34 -> 7267319.3 | G33: =F34 -> 9566954.9 | H33: =G34 -> 12579624 | I33: =H34 -> 16471265 | J33: =I34 -> 20538155 | K33: =J34 -> 24564338
A34: Ending balance | B34: =B13+B20 -> 3435848.3 | C34: =C13+C20 -> 3304923.5 | D34: =D13+D20 -> 5375279.2 | E34: =E13+E20 -> 7267319.3 | F34: =F13+F20 -> 9566954.9 | G34: =G13+G20 -> 12579624 | H34: =H13+H20 -> 16471265 | I34: =I13+I20 -> 20538155 | ... K34: =K13+K20 -> 28307613
A36: Intangible fixed assets
A37: Historical cost | B37: =DATA!C57 -> 32779.5 | C37: =DATA!D57 -> 33838.4 | D37: =DATA!E57 -> 34852.2 | E37: =DATA!F57 -> 35811.6 | F37: =DATA!G57 -> 90297.8 | G37: =F37+G42 -> 91257.2 | H37: =G37+H42 -> 92216.6 | I37: =H37+I42 -> 93176 | J37: =I37+J42 -> 94135.4 | K37: =J37+K42 -> 95094.8
A38: Accumulated depreciation | B38: =DATA!C58 -> -4969.8 | C38: =DATA!D58 -> -5614.3 | D38: =DATA!E58 -> -6354.4 | E38: =DATA!F58 -> -8169.3 | F38: =DATA!G58 -> -10083.8 | G38: =G48+G73 -> -15951.704 | H38: =H48+H73 -> -21990.581 | I38: =I48+I73 -> -28200.473 | J38: =J48+J73 -> -34581.378 | K38: =K48+K73 -> -40893.448
A39: Forecasted value in detail (Software)
A40: Historical cost
A41: Beginning of period | B41: 5109.2 | C41: =B43 -> 6780.5 | D41: =C43 -> 7839.45 | E41: =D43 -> 8853.22 | F41: =E43 -> 9812.65 | G41: =F43 -> 10772.05 | H41: =G43 -> 11731.45 | I41: =H43 -> 12690.85 | J41: =I43 -> 13650.25 | K41: =J43 -> 14609.65
A42: New purchase | B42: 1671.3 | C42: 1058.95 | D42: 1013.77 | E42: 959.43 | F42: 959.4 | G42: =F42 -> 959.4 | H42: =G42 -> 959.4 | I42: =H42 -> 959.4 | J42: =I42 -> 959.4 | K42: =J42 -> 959.4
A43: Ending balance | B43: =B41+B42 -> 6780.5 | C43: =C41+C42 -> 7839.45 | D43: =D41+D42 -> 8853.22 | E43: =E41+E42 -> 9812.65 | F43: =F41+F42 -> 10772.05 | G43: =G41+G42 -> 11731.45 | H43: =H41+H42 -> 12690.85 | I43: =I41+I42 -> 13650.25 | ... K43: =K41+K42 -> 15569.05
A45: Accumulated depreciation
A46: Beginning of period | B46: -4493.66 | C46: =B48 -> -4969.8 | D46: =C48 -> -5614.28 | E46: =D48 -> -6354.37 | F46: =E48 -> -8169.27 | G46: =F48 -> -10083.84 | H46: =G48 -> -10599.034 | I46: =H48 -> -11285.242 | J46: =I48 -> -12142.464 | K46: =J48 -> -13170.7
A47: New purchase | B47: -476.14 | C47: -644.48 | D47: -740.09 | E47: -1814.9 | F47: -1914.57 | G47: =-G58 -> -515.194 | H47: =-H58 -> -686.208 | I47: =-I58 -> -857.222 | J47: =-J58 -> -1028.236 | K47: =-K58 -> -959.4
A48: Ending balance | B48: =SUM(B46:B47) -> -4969.8 | C48: =SUM(C46:C47) -> -5614.28 | D48: =SUM(D46:D47) -> -6354.37 | E48: =SUM(E46:E47) -> -8169.27 | F48: =SUM(F46:F47) -> -10083.84 | G48: =SUM(G46:G47) -> -10599.034 | H48: =SUM(H46:H47) -> -11285.242 | I48: =SUM(I46:I47) -> -12142.464 | ... K48: =SUM(K46:K47) -> -14130.1
A50: Average depreciable life | F50: 4
A51: Annual depreciation rate (%) | F51: =1/F50 -> 0.25
A52: Depreciation of additional computer software investments currently | F52: =-F47 -> 1914.57 | G52: =SYD($F$62,0,$F$50,1) -> 275.344 | H52: =SYD($F$62,0,$F$50,2) -> 206.508 | I52: =SYD($F$62,0,$F$50,3) -> 137.672 | J52: =SYD($F$62,0,$F$50,4) -> 68.836 | K52: 0
A53: Depreciation of additional computer software investments from 2022 | G53: =SLN($G$42,0,$F$50) -> 239.85 | H53: =SLN($G$42,0,$F$50) -> 239.85 | I53: =SLN($G$42,0,$F$50) -> 239.85 | J53: =SLN($G$42,0,$F$50) -> 239.85 | K53: 0
A54: Depreciation of additional computer software investments from 2023 | H54: =$F$51*$H$42 -> 239.85 | I54: =$F$51*$H$42 -> 239.85 | J54: =$F$51*$H$42 -> 239.85 | K54: =$F$51*$H$42 -> 239.85
A55: Depreciation of additional computer software investments from 2024 | I55: =F51*I42 -> 239.85 | J55: =I55 -> 239.85 | K55: =J55 -> 239.85
A56: Depreciation of additional computer software investments from 2025 | J56: =F51*J42 -> 239.85 | K56: =J56 -> 239.85
A57: Depreciation of additional computer software investments from 2026 | K57: =F51*K42 -> 239.85
A58: Depreciation of additional computer software investments over the year | F58: =SUM(F52:F57) -> 1914.57 | G58: =SUM(G52:G57) -> 515.194 | H58: =SUM(H52:H57) -> 686.208 | I58: =SUM(I52:I57) -> 857.222 | J58: =SUM(J52:J57) -> 1028.236 | K58: =SUM(K52:K57) -> 959.4
A60: Salvage value
A61: Beginning balance | B61: 615.58 | C61: =B62 -> 1810.7 | D61: =C62 -> 2225.25 | E61: =D62 -> 2498.937 | F61: =E62 -> 1643.499 | G61: =F62 -> 688.36 | H61: =G62 -> 1132.416 | I61: =H62 -> 1405.608 | J61: =I62 -> 1507.786 | K61: =J62 -> 1438.95
A62: Ending balance | B62: =B43+B48 -> 1810.7 | C62: =2225.25 -> 2225.25 | D62: 2498.937 | E62: 1643.499 | F62: 688.36 | G62: =G43+G48 -> 1132.416 | H62: =H43+H48 -> 1405.608 | I62: =I43+I48 -> 1507.786 | J62: =J43+J48 -> 1438.95 | K62: =K43+K48 -> 1438.95
A64: Forecasted value in detail (Brand)
A65: Historical cost
A66: Beginning of period | B66: 0 | C66: 0 | D66: 0 | E66: 0 | F66: 0 | G66: =F68 -> 53526.696 | H66: =G68 -> 53526.696 | I66: =H68 -> 53526.696 | J66: =I68 -> 53526.696 | K66: =J68 -> 53526.696
A67: New purchase | B67: 0 | C67: 0 | D67: 0 | E67: 0 | F67: 53526.696 | G67: 0 | H67: 0 | I67: 0 | J67: 0 | K67: 0
A68: Ending balance | B68: 0 | C68: 0 | D68: 0 | E68: 0 | F68: =SUM(F66:F67) -> 53526.696 | G68: =SUM(G66:G67) -> 53526.696 | H68: =SUM(H66:H67) -> 53526.696 | I68: =SUM(I66:I67) -> 53526.696 | J68: =SUM(J66:J67) -> 53526.696 | K68: =SUM(K66:K67) -> 53526.696
A70: Accumulated depreciation
A71: Beginning of period | B71: 0 | C71: 0 | D71: 0 | E71: 0 | F71: 0 | G71: =F73 -> 0 | H71: =G73 -> -5352.6696 | I71: =H73 -> -10705.339 | J71: =I73 -> -16058.009 | K71: =J73 -> -21410.678
A72: New purchase | B72: 0 | C72: 0 | D72: 0 | E72: 0 | F72: 0 | G72: =-G82 -> -5352.6696 | H72: =-H82 -> -5352.6696 | I72: =-I82 -> -5352.6696 | J72: =-J82 -> -5352.6696 | K72: =-K82 -> -5352.6696
A73: Ending balance | B73: 0 | C73: 0 | D73: 0 | E73: 0 | F73: 0 | G73: =SUM(G71:G72) -> -5352.6696 | H73: =SUM(H71:H72) -> -10705.339 | I73: =SUM(I71:I72) -> -16058.009 | J73: =SUM(J71:J72) -> -21410.678 | K73: =SUM(K71:K72) -> -26763.348
A74: Average depreciable life | F74: 10
A75: Annual depreciation rate (%) | F75: =1/F74 -> 0.1
A76: Depreciation of current brand value | F76: =F71 -> 0 | G76: =G71 -> 0
A77: Depreciation of brand value in 2022 | G77: =$F$67*$F$75 -> 5352.6696
A78: Depreciation of brand value in 2023 | G78: 0 | H78: =$F$67*$F$75 -> 5352.6696 | I78: 0 | J78: 0 | K78: 0
A79: Depreciation of brand value in 2024 | G79: 0 | H79: 0 | I79: =$F$67*$F$75 -> 5352.6696 | J79: 0 | K79: 0
A80: Depreciation of brand value in 2025 | G80: 0 | H80: 0 | I80: 0 | J80: =$F$67*$F$75 -> 5352.6696 | K80: 0
A81: Depreciation of brand value in 2026 | G81: 0 | H81: 0 | I81: 0 | J81: 0 | K81: =$F$67*$F$75 -> 5352.6696
A82: Depreciation of brand value during the year | G82: =SUM(G77:G81) -> 5352.6696 | H82: =SUM(H77:H81) -> 5352.6696 | I82: =SUM(I77:I81) -> 5352.6696 | J82: =SUM(J77:J81) -> 5352.6696 | K82: =SUM(K77:K81) -> 5352.6696
A84: Salvage value
A85: Beginning balance | B85: 0 | C85: 0 | D85: 0 | E85: 0 | F85: 0 | G85: =F86 -> 53526.696 | H85: =G86 -> 48174.026 | I85: =H86 -> 42821.357 | J85: =I86 -> 37468.687 | K85: =J86 -> 32116.018
A86: Ending balance | B86: 0 | C86: 0 | D86: 0 | E86: 0 | F86: =F68 -> 53526.696 | G86: =G68+G73 -> 48174.026 | H86: =H68+H73 -> 42821.357 | I86: =I68+I73 -> 37468.687 | J86: =J68+J73 -> 32116.018 | K86: =K68+K73 -> 26763.348
A88: Long-term work in progress
A89: WIP costs | C89: =B92 -> 35457.4 | D89: =C92 -> 256832 | E89: =D92 -> 87430.4 | F89: =E92 -> 132620.4 | G89: =F92 -> 79697.9 | H89: =G92 -> 247550.34 | I89: =H92 -> 304900.73 | J89: =I92 -> 347611.48 | K89: =J92 -> 292250.14
A90: Transfer to tangible fixed assets | G90: =-G89 -> -79697.9 | H90: =-H89 -> -247550.34 | I90: =-I89 -> -304900.73 | J90: =-J89 -> -347611.48 | K90: =-K89 -> -292250.14
A91: Increase during the period | B91: =B9 -> 84124.077 | G91: =G8*4% -> 247550.34 | H91: =H8*4% -> 304900.73 | I91: =I8*4% -> 347611.48 | J91: =J8*3% -> 292250.14 | K91: =K8*3% -> 324775.09
A92: Ending balance | B92: =DATA!C65 -> 35457.4 | C92: =DATA!D65 -> 256832 | D92: =DATA!E65 -> 87430.4 | E92: =DATA!F65 -> 132620.4 | F92: =DATA!G65 -> 79697.9 | G92: =SUM(G89:G91) -> 247550.34 | H92: =SUM(H89:H91) -> 304900.73 | I92: =SUM(I89:I91) -> 347611.48 | J92: =SUM(J89:J91) -> 292250.14 | K92: =SUM(K89:K91) -> 324775.09
A93: Revenue growth rate | C93: =SALE!C53 -> 0.30413841 | D93: =SALE!D53 -> 0.18098277 | E93: =SALE!E53 -> 0.062361858 | F93: =SALE!F53 -> 0.13277397 | G93: =SALE!G53 -> 0.24405669 | H93: =SALE!H53 -> 0.23167163 | I93: =SALE!I53 -> 0.14008082 | J93: =SALE!J53 -> 0.12098384 | K93: =SALE!K53 -> 0.11129149

Sheet NWC
A1: WORKING CAPITAL | B1: 2017A | C1: 2018A | D1: 2019A | E1: 2020A | F1: 2021A | G1: 2022F | H1: 2023F | I1: 2024F | J1: 2025F | K1: 2026F
A3: A part of non-current assets
A4: Receivables | B4: =DATA!C18 -> 1431776.8 | C4: =DATA!D18 -> 369573.7 | D4: =DATA!E18 -> 262268.4 | E4: =DATA!F18 -> 196394.5 | F4: =DATA!G18 -> 384236.6 | G4: =(2*IS!G2/G5)-NWC!F4 -> 298005.72 | H4: =(2*IS!H2/H5)-NWC!G4 -> 566280.27 | I4: =(2*IS!I2/I5)-NWC!H4 -> 405209.36 | J4: =(2*IS!J2/J5)-NWC!I4 -> 691531.67 | K4: =(2*IS!K2/K5)-NWC!J4 -> 522964.33
A5: Receivables turnover | C5: =IS!C2/AVERAGE(NWC!B4:C4) -> 96.057138 | D5: =IS!D2/AVERAGE(NWC!C4:D4) -> 323.41702 | E5: =IS!E2/AVERAGE(NWC!D4:E4) -> 473.31502 | F5: =IS!F2/AVERAGE(NWC!E4:F4) -> 423.53262 | G5: =AVERAGE(E5:F5) -> 448.42382 | H5: =AVERAGE(F5:G5) -> 435.97822 | I5: =AVERAGE(G5:H5) -> 442.20102 | J5: =AVERAGE(H5:I5) -> 439.08962 | K5: =AVERAGE(I5:J5) -> 440.64532
A6: Inventory | B6: =DATA!C28 -> 12309956 | C6: =DATA!D28 -> 17821138 | D6: =DATA!E28 -> 26195935 | E6: =DATA!F28 -> 19926364 | F6: =DATA!G28 -> 29850069 | G6: =(2*G7*IS!G3)/365-NWC!F6 -> 34305807 | H6: =(2*H7*IS!H3)/365-NWC!G6 -> 42470348 | I6: =(2*I7*IS!I3)/365-NWC!H6 -> 45697089 | J6: =(2*J7*IS!J3)/365-NWC!I6 -> 53320836 | K6: =(2*K7*IS!K3)/365-NWC!J6 -> 57138007
A7: Inventory turnover | C7: =(IS!C3/(AVERAGE(NWC!B6:C6))) -> 4.7276187 | D7: =365/(IS!D3/(AVERAGE(NWC!C6:D6))) -> 97.151543 | E7: =365/(IS!E3/(AVERAGE(NWC!D6:E6))) -> 99.505473 | F7: =365/(IS!F3/(AVERAGE(NWC!E6:F6))) -> 95.296156 | G7: =99 -> 99 | H7: 96 | I7: 97 | J7: 97.5 | K7: 98
A8: Days of inventory on hand (DOH) | C8: =365/C7 -> 77.205888 | D8: =365/D7 -> 3.757017 | E8: =365/E7 -> 3.66814 | F8: =365/F7 -> 3.830165 | G8: =365/G7 -> 3.6868687 | H8: =365/H7 -> 3.8020833 | I8: =365/I7 -> 3.7628866 | J8: =365/J7 -> 3.7435897 | K8: =365/K7 -> 3.7244898
A9: Provision for inventory | B9: =BS!C19 -> -259792.8 | C9: =BS!D19 -> -375132.3 | D9: =BS!E19 -> -450506.2 | E9: =BS!F19 -> -504186 | F9: =BS!G19 -> -682836.5 | G9: =G6*G10 -> -823339.38 | H9: =H6*H10 -> -1019288.4 | I9: =I6*I10 -> -1096730.1 | J9: =J6*J10 -> -1279700.1 | K9: =K6*K10 -> -1371312.2
A10: Provision/Inventory | B10: =B9/B6 -> -0.021104284 | C10: =C9/C6 -> -0.021049851 | D10: =D9/D6 -> -0.017197562 | E10: =E9/E6 -> -0.025302459 | F10: =F9/F6 -> -0.022875542 | G10: =-2.4% -> -0.024 | H10: =-2.4% -> -0.024 | I10: =-2.4% -> -0.024 | J10: =-2.4% -> -0.024 | K10: =-2.4% -> -0.024
A11: Prepaid to suppliers | B11: =DATA!C19 -> 117942 | C11: =DATA!D19 -> 21007.3 | D11: =DATA!E19 -> 195016.8 | E11: =DATA!F19 -> 287913.3 | F11: =DATA!G19 -> 390738.8 | G11: =G12*IS!G2 -> 486101.22 | H11: =H12*IS!H2 -> 598717.08 | I11: =I12*IS!I2 -> 682585.86 | J11: =J12*IS!J2 -> 765167.72 | K11: =K12*IS!K2 -> 850324.37
A12: Prepaid to suppliers/Net revenue | B12: =B11/IS!B2 -> 0.0017778467 | C12: =C11/IS!C2 -> 0.00024281324 | D12: =D11/IS!D2 -> 0.0019086689 | E12: =E11/IS!E2 -> 0.0026524538 | F12: =F11/IS!F2 -> 0.0031778206 | G12: =F12 -> 0.0031778206 | H12: =G12 -> 0.0031778206 | I12: =H12 -> 0.0031778206 | J12: =I12 -> 0.0031778206 | K12: =J12 -> 0.0031778206
A13: Other receivables | B13: =DATA!C23 -> 1131428.9 | C13: =DATA!D23 -> 1151948.8 | D13: =DATA!E23 -> 1357800.4 | E13: =DATA!F23 -> 1030943.1 | F13: =DATA!G23 -> 1425228.9 | G13: =G14*IS!G2 -> 1752897.8 | H13: =H14*IS!H2 -> 2044084.1 | I13: =I14*IS!I2 -> 2427199.1 | J13: =J14*IS!J2 -> 2697478.9 | K13: =K14*IS!K2 -> 2974814
A14: Other receivables/Net revenue | B14: =B13/IS!B2 -> 0.017055053 | C14: =C13/IS!C2 -> 0.01331482 | D14: =D13/IS!D2 -> 0.013289067 | E14: =E13/IS!E2 -> 0.0094977513 | F14: =F13/IS!F2 -> 0.011591175 | G14: =AVERAGE(D14:F14) -> 0.011459331 | H14: =AVERAGE(E14:G14) -> 0.010849419 | I14: =AVERAGE(F14:H14) -> 0.011299975 | J14: =AVERAGE(G14:I14) -> 0.011202908 | K14: =AVERAGE(H14:J14) -> 0.011117434
A15: Short-term loan receivables | B15: =DATA!C22 -> 84700 | C15: =DATA!D22 -> 0 | D15: =DATA!E22 -> 0 | E15: =DATA!F22 -> 80000 | F15: =DATA!G22 -> 961917.7 | G15: =G16*IS!G2 -> 1273163.6 | H15: =H16*IS!H2 -> 1662321.9 | I15: =I16*IS!I2 -> 1895181.3 | J15: =J16*IS!J2 -> 2124467.7 | K15: =K16*IS!K2 -> 2360902.8
A16: Short-term loan receivables/Net revenue | B16: =B15/IS!B2 -> 0.0012767599 | C16: =C15/IS!C2 -> 0 | D16: =D15/IS!D2 -> 0 | E16: =E15/IS!E2 -> 0.00073701459 | F16: =F15/IS!F2 -> 0.0078231337 | G16: =F16+0.05% -> 0.0083231337 | H16: =G16+0.05% -> 0.0088231337 | I16: =H16 -> 0.0088231337 | J16: =I16 -> 0.0088231337 | K16: =J16 -> 0.0088231337
A18: A part of current liabilities
A19: Payables | B19: =DATA!C86 -> 7373229.7 | C19: =DATA!D86 -> 8244614.2 | D19: =DATA!E86 -> 12055386 | E19: =DATA!F86 -> 8728168.9 | F19: =DATA!G86 -> 12179775 | G19: =(2*IS!G2/G20)-F19 -> 15135735 | H19: =(2*IS!H2/H20)-G19 -> 18702137 | I19: =(2*IS!I2/I20)-H19 -> 19094692 | J19: =(2*IS!J2/J20)-I19 -> 23772779 | K19: =(2*IS!K2/K20)-J19 -> 23817648
A20: Payables turnover | C20: =IS!C2/AVERAGE(NWC!B19:C19) -> 11.079159 | D20: =IS!D2/AVERAGE(NWC!C19:D19) -> 10.066428 | E20: =IS!E2/AVERAGE(NWC!D19:E19) -> 10.445376 | F20: =IS!F2/AVERAGE(NWC!E19:F19) -> 11.761855 | G20: =11.2 -> 11.2 | H20: =AVERAGE(E20:G20) -> 11.135744 | I20: =AVERAGE(F20:H20) -> 11.365866 | J20: =AVERAGE(G20:I20) -> 11.23387 | K20: =AVERAGE(H20:J20) -> 11.24516
A21: Unearned revenue | B21: =DATA!C87 -> 22475.5 | C21: =DATA!D87 -> 38061.6 | D21: =DATA!E87 -> 81194.1 | E21: =DATA!F87 -> 86907.4 | F21: =DATA!G87 -> 98379.3 | G21: =G22*IS!G2 -> 122389.43 | H21: =H22*IS!H2 -> 150743.58 | I21: =I22*IS!I2 -> 171859.87 | J21: =J22*IS!J2 -> 192652.14 | K21: =K22*IS!K2 -> 214092.68
A22: Unearned revenue/COGS | B22: =B21/IS!B2 -> 0.00033879358 | C22: =C21/IS!C2 -> 0.00043993566 | D22: =D21/IS!D2 -> 0.00079466309 | E22: =E21/IS!E2 -> 0.00080065027 | F22: =F21/IS!F2 -> 0.00080010422 | G22: =F22 -> 0.00080010422 | H22: =G22 -> 0.00080010422 | I22: =H22 -> 0.00080010422 | J22: =I22 -> 0.00080010422 | K22: =J22 -> 0.00080010422
A23: Statutory obligations | B23: =DATA!C88 -> 137421.6 | C23: =DATA!D88 -> 217699.6 | D23: =DATA!E88 -> 374623.3 | E23: =DATA!F88 -> 634917.9 | F23: =DATA!G88 -> 696559 | G23: =G24*IS!G2 -> 887207.76 | H23: =H24*IS!H2 -> 1092748.6 | I23: =I24*IS!I2 -> 1267301.4 | J23: =J24*IS!J2 -> 1420624.4 | K23: =K24*IS!K2 -> 1578727.8
A24: Statutory obligations/COGS | B24: =B23/IS!B2 -> 0.0020714803 | C24: =C23/IS!C2 -> 0.0025162846 | D24: =D23/IS!D2 -> 0.003666514 | E24: =E23/IS!E2 -> 0.0058492969 | F24: =F23/IS!F2 -> 0.0056650108 | G24: =0.58% -> 0.0058 | H24: =0.58% -> 0.0058 | I24: =0.59% -> 0.0059 | J24: =0.59% -> 0.0059 | K24: =0.59% -> 0.0059
A25: Payables to employees | B25: =DATA!C89 -> 133725.1 | C25: =DATA!D89 -> 149775 | D25: =DATA!E89 -> 258242.3 | E25: =DATA!F89 -> 533572.3 | F25: =DATA!G89 -> 531987.4 | G25: =G26*IS!G3 -> 697776.16 | H25: =H26*IS!H3 -> 875728.03 | I25: =I26*IS!I3 -> 1011880.4 | J25: =J26*IS!J3 -> 1149115.7 | K25: =K26*IS!K3 -> 1295918.9
A26: Payables to employees/COGS | B26: =B25/IS!B3 -> 0.0024226428 | C26: =C25/IS!C3 -> 0.0021028679 | D26: =D25/IS!D3 -> 0.0031231516 | E26: =E25/IS!E3 -> 0.0063076333 | F26: =F25/IS!F3 -> 0.0055807182 | G26: =0.59% -> 0.0059 | H26: =G26+0.01% -> 0.006 | I26: =H26+0.01% -> 0.0061 | J26: =I26+0.01% -> 0.0062 | K26: =J26+0.01% -> 0.0063
A27: Short-term payables | B27: =BS!C70 -> 1585372.4 | C27: =BS!D70 -> 2173064.9 | D27: =BS!E70 -> 1851967 | E27: =BS!F70 -> 3191005.4 | F27: =BS!G70 -> 3885356.4 | G27: =G28*IS!G3 -> 4640871 | H27: =H28*IS!H3 -> 5838129.2 | I27: =I28*IS!I3 -> 6572261.2 | J27: =J28*IS!J3 -> 7378406.7 | K27: =K28*IS!K3 -> 8169425.4
A28: Short-term payables/COGS | B28: =B27/IS!B3 -> 0.028721542 | C28: =C27/IS!C3 -> 0.030510222 | D28: =D27/IS!D3 -> 0.022397468 | E28: =E27/IS!E3 -> 0.03772252 | F28: =F27/IS!F3 -> 0.040758633 | G28: =AVERAGE(E28:F28) -> 0.039240577 | H28: =AVERAGE(F28:G28) -> 0.039999605 | I28: =AVERAGE(G28:H28) -> 0.039620091 | J28: =AVERAGE(H28:I28) -> 0.039809848 | K28: =AVERAGE(I28:J28) -> 0.039714969
A29: Provision for short-term payables | B29: =BS!C76 -> 45824.5 | C29: =BS!D76 -> 56568.6 | D29: =BS!E76 -> 71690.5 | E29: =BS!F76 -> 76377.4 | F29: =BS!G76 -> 77277.6 | G29: =G30*G19 -> 103281.56 | H29: =H30*H19 -> 129894.41 | I29: =I30*I19 -> 132942.24 | J29: =J30*J19 -> 170340.57 | K29: =K30*K19 -> 163110.37
A30: Provision for short-term payables/Payables | B30: =B29/B19 -> 0.0062149834 | C30: =C29/C19 -> 0.0068612792 | D30: =D29/D19 -> 0.0059467613 | E30: =E29/E19 -> 0.0087506785 | F30: =F29/F19 -> 0.0063447479 | G30: =AVERAGE(B30:F30) -> 0.00682369 | H30: =AVERAGE(C30:G30) -> 0.0069454314 | I30: =AVERAGE(D30:H30) -> 0.0069622618 | J30: =AVERAGE(E30:I30) -> 0.0071653619 | K30: =AVERAGE(F30:J30) -> 0.0068482986
A31: Other short-term payables | B31: =BS!C74 -> 807310.1 | C31: =BS!D74 -> 1208214.3 | D31: =BS!E74 -> 717884.7 | E31: =BS!F74 -> 546045.4 | F31: =BS!G74 -> 476319.9 | G31: =G32*IS!G2 -> 681037.63 | H31: =H32*IS!H2 -> 784332.55 | I31: =I32*IS!I2 -> 925259.55 | J31: =J32*IS!J2 -> 1019793.8 | K31: =K32*IS!K2 -> 1142960.4
A32: Other short-term payables/Revenue | B32: =B31/IS!B2 -> 0.012169317 | C32: =C31/IS!C2 -> 0.013965166 | D32: =D31/IS!D2 -> 0.0070260828 | E32: =E31/IS!E2 -> 0.0050305428 | F32: =F31/IS!F2 -> 0.0038738389 | G32: =AVERAGE(E32:F32) -> 0.0044521909 | H32: =AVERAGE(F32:G32) -> 0.0041630149 | I32: =AVERAGE(G32:H32) -> 0.0043076029 | J32: =AVERAGE(H32:I32) -> 0.0042353089 | K32: =AVERAGE(I32:J32) -> 0.0042714559
A34: Other current assets
A35: Beginnig balance | C35: =B37 -> 635867.5 | D35: =C37 -> 582987 | E35: =D37 -> 1199146.1 | F35: =E37 -> 894629.3 | G35: =F37 -> 1247261.4 | H35: =G37 -> 1547427.6 | I35: =H37 -> 1909696 | J35: =I37 -> 2170429 | K35: =J37 -> 2425036.6
A36: Increase/Decrease | C36: =C37-C35 -> -52880.5 | D36: =D37-D35 -> 616159.1 | E36: =E37-E35 -> -304516.8 | F36: =F37-F35 -> 352632.1 | G36: =G37-G35 -> 300166.22 | H36: =H37-H35 -> 362268.34 | I36: =I37-I35 -> 260733.03 | J36: =J37-J35 -> 254607.64 | K36: =K37-K35 -> 266396
A37: Ending balance | B37: =BS!C20 -> 635867.5 | C37: =BS!D20 -> 582987 | D37: =BS!E20 -> 1199146.1 | E37: =BS!F20 -> 894629.3 | F37: =BS!G20 -> 1247261.4 | G37: =G35*(1+G38) -> 1547427.6 | H37: =H35*(1+H38) -> 1909696 | I37: =I35*(1+I38) -> 2170429 | J37: =J35*(1+J38) -> 2425036.6 | K37: =K35*(1+K38) -> 2691432.6
A38: Increase as % growth of COGS | C38: =IS!C3/IS!B3-1 -> 0.29033891 | D38: =IS!D3/IS!C3-1 -> 0.16093255 | E38: =IS!E3/IS!D3-1 -> 0.023039782 | F38: =IS!F3/IS!E3-1 -> 0.12689749 | G38: =IS!G3/IS!F3-1 -> 0.24066024 | H38: =IS!H3/IS!G3-1 -> 0.23411004 | I38: =IS!I3/IS!H3-1 -> 0.13653117 | J38: =IS!J3/IS!I3-1 -> 0.11730752 | K38: =IS!K3/IS!J3-1 -> 0.10985236

Sheet EQUITY
B1: 2017A | C1: 2018A | D1: 2019A | E1: 2020A | F1: 2021A | G1: 2022F | H1: 2023F | I1: 2024F | J1: 2025F | K1: 2026F
A2: Common stock
A3: Contributed chartered capital | B3: =DATA!C119 -> 3169884.4 | C3: =DATA!D119 -> 4434961.8 | D3: =DATA!E119 -> 4435461.8 | E3: =DATA!F119 -> 4532099.9 | F3: =DATA!G119 -> 7130655 | G3: =G22 -> 14645795 | H3: =H22 -> 14645795 | I3: =I22 -> 14645795 | J3: =J22 -> 14645795 | K3: =K22 -> 14645795
A4: Additional paid-in capital | B4: =DATA!C122 -> 36717.7 | C4: =DATA!D122 -> 551452 | D4: =DATA!E122 -> 555207 | E4: =DATA!F122 -> 558110.4 | F4: =DATA!G122 -> 558110.4 | G4: =G28 -> 558110.41 | H4: =H28 -> 558110.41 | I4: =I28 -> 558110.41 | J4: =J28 -> 558110.41 | K4: =K28 -> 558110.41
A5: Other equity of the shareholders | B5: =DATA!C124 -> 1130.5 | C5: =DATA!D124 -> 1130.5 | D5: =DATA!E124 -> 1130.5 | E5: =DATA!F124 -> 0 | F5: =DATA!G124 -> 0 | G5: =DATA!H124 -> 0 | H5: =DATA!I124 -> 0 | I5: =DATA!J124 -> 0 | ... K5: =DATA!L124 -> 0
A6: Treasury stock | B6: =DATA!C125 -> -79.2 | C6: =DATA!D125 -> -808.9 | D6: =DATA!E125 -> -5658.9 | E6: =DATA!F125 -> -6040.9 | F6: =DATA!G125 -> -2320 | G6: =G36 -> -2320 | H6: =H36 -> -2320 | I6: =I36 -> -2320 | J6: =J36 -> -2320 | K6: =K36 -> -2320
A7: Exchange rate difference | B7: =DATA!C127 -> -86.1 | C7: =DATA!D127 -> 446.6 | D7: =DATA!E127 -> -28.4 | E7: =DATA!F127 -> -1443.8 | F7: =DATA!G127 -> 5388.4 | G7: =G40 -> 5388.425 | H7: =H40 -> 5388.425 | I7: =I40 -> 5388.425 | J7: =J40 -> 5388.425 | K7: =K40 -> 5388.425
A8: Undistributed after-tax profit | B8: =DATA!C131 -> 2698572.7 | C8: =DATA!D131 -> 3989603.9 | D8: =DATA!E131 -> 7149694.2 | E8: =DATA!F131 -> 10389684 | F8: =DATA!G131 -> 12674574 | G8: =G53 -> 18594096 | H8: =H53 -> 25407832 | I8: =I53 -> 34695100 | J8: =J53 -> 46174884 | K8: =K53 -> 59237757
A9: Non-controlling interest | B9: =DATA!C135 -> 2776.3 | C9: =DATA!D135 -> 6249.4 | D9: =DATA!E135 -> 7786.1 | E9: =DATA!F135 -> 9280.6 | F9: =DATA!G135 -> 11838 | G9: =G62 -> 14911.925 | H9: =H62 -> 18764.27 | I9: =I62 -> 23118.474 | J9: =J62 -> 28020.642 | K9: =K62 -> 33456.613
A11: DETAIL CALCULATIONS
A13: Contributed capital of shareholders
A15: Beginning balance | B15: 1539509.3 | C15: =B22 -> 3169884.4 | D15: =C22 -> 4434961.8 | E15: =D22 -> 4435461.8 | F15: =E22 -> 4532099.9 | G15: =F22 -> 7130654.9 | H15: =G22 -> 14645795 | I15: =H22 -> 14645795 | J15: =I22 -> 14645795 | K15: =J22 -> 14645795
A16: Issuance of shares | B16: 0 | C16: 61810.84 | D16: 500 | E16: 96638.09 | F16: 0
A17: Bonus share issuance | B17: 1538148.6 | C17: 0 | D17: 0 | E17: 0 | F17: 0
A18: ESOP | B18: 92226.48 | C18: 127295.11 | D18: 0 | E18: 0 | F18: 222212.1 | G18: =G15*2.696% -> 192242.46
A19: Dividend distribution | B19: 0 | C19: =C20 -> 1075971.5 | D19: 0 | E19: 0 | F19: 2376343 | G19: =G21+G20 -> 7322897.4
A20: In shares | B20: 0 | C20: 1075971.5 | D20: 0 | E20: 0 | F20: 0 | G20: =G15+G18 -> 7322897.4
A21: In cash | B21: 0 | C21: 0 | D21: 0 | E21: 0 | F21: =F19 -> 2376343
A22: Ending balance | B22: =SUM(B15:B19) -> 3169884.4 | C22: =SUM(C15:C18,C20) -> 4434961.8 | D22: =SUM(D15:D18,D20) -> 4435461.8 | E22: =SUM(E15:E18,E20) -> 4532099.9 | F22: =SUM(F15:F19) -> 7130654.9 | G22: =G15+G19+G18 -> 14645795 | H22: =H15+H19+H18 -> 14645795 | I22: =I15+I19+I18 -> 14645795 | J22: =J15+J19+J18 -> 14645795 | K22: =K15+K19+K18 -> 14645795
A24: Additional paid-in capital
A26: Beginning balance | B26: =B4 -> 36717.7 | C26: =B28 -> 36717.7 | D26: =C28 -> 551451.98 | E26: =D28 -> 555206.98 | F26: =E28 -> 558110.41 | G26: =F28 -> 558110.41 | H26: =G28 -> 558110.41 | I26: =H28 -> 558110.41 | J26: =I28 -> 558110.41 | K26: =J28 -> 558110.41
A27: Share issuance | C27: 514734.28 | D27: 3755 | E27: 2903.435
A28: Ending balance | B28: =B26 -> 36717.7 | C28: =SUM(C26:C27) -> 551451.98 | D28: =SUM(D26:D27) -> 555206.98 | E28: =SUM(E26:E27) -> 558110.41 | F28: =F26 -> 558110.41 | G28: =G26 -> 558110.41 | H28: =H26 -> 558110.41 | I28: =I26 -> 558110.41 | J28: =J26 -> 558110.41 | K28: =K26 -> 558110.41
A30: Treasury shares
A32: Beginning balance | B32: -79.164 | C32: =B36 -> -79.164 | D32: =C36 -> -808.864 | E32: =D36 -> -5658.924 | F32: =E36 -> -6040.93 | G32: =F36 -> -2320 | H32: =G36 -> -2320 | I32: =H36 -> -2320 | J32: =I36 -> -2320 | K32: =J36 -> -2320
A33: Issuance | E33: 5658.924 | F33: 0
A34: ESOP | F34: 6040.93
A35: Stock buyback | C35: -729.7 | D35: -4850.06 | E35: -6040.93 | F35: -2320
A36: Ending balance | B36: =B32 -> -79.164 | C36: =SUM(C32:C35) -> -808.864 | D36: =SUM(D32:D35) -> -5658.924 | E36: =SUM(E32:E35) -> -6040.93 | F36: =SUM(F32:F35) -> -2320 | G36: =G32 -> -2320 | H36: =H32 -> -2320 | I36: =I32 -> -2320 | J36: =J32 -> -2320 | K36: =K32 -> -2320
A37: Exchange rate differences
A38: Beginning balance | B38: 0 | C38: =B40 -> -86.063 | D38: =C40 -> 446.573 | E38: =D40 -> -28.377 | F38: =E40 -> -1443.755 | G38: =F40 -> 5388.425 | H38: =G40 -> 5388.425 | I38: =H40 -> 5388.425 | J38: =I40 -> 5388.425 | K38: =J40 -> 5388.425
A39: Exchange rate differences | B39: -86.063 | C39: 532.636 | D39: -474.95 | E39: -1415.378 | F39: 6832.18
A40: Ending balance | B40: =B39 -> -86.063 | C40: =SUM(C38:C39) -> 446.573 | D40: =SUM(D38:D39) -> -28.377 | E40: =SUM(E38:E39) -> -1443.755 | F40: =SUM(F38:F39) -> 5388.425 | G40: =F40 -> 5388.425 | H40: =G40 -> 5388.425 | I40: =H40 -> 5388.425 | J40: =I40 -> 5388.425 | K40: =J40 -> 5388.425
A42: Undistributed after-tax profit
A44: Beginning balance | B44: 2261763.4 | C44: =B53 -> 2698572.7 | D44: =C53 -> 3989603.8 | E44: =D53 -> 7149694.2 | F44: =E53 -> 10389684 | G44: =F53 -> 12674574 | H44: =G53 -> 18594096 | I44: =H53 -> 25407832 | J44: =I53 -> 34695100 | K44: =J53 -> 46174884
A45: Net profit for the year | B45: =DATA!C186 -> 2205679.6 | C45: =DATA!D186 -> 2878724.1 | D45: =DATA!E186 -> 3834269.5 | E45: =DATA!F186 -> 3917767.8 | F45: =DATA!G186 -> 4898869.3 | G45: =IS!G20 -> 6651811.6 | H45: =IS!H20 -> 8278315.4 | I45: =IS!I20 -> 10751847 | J45: =IS!J20 -> 12944364 | K45: =IS!K20 -> 14527453
A46: Provision | B46: 0 | C46: 0 | D46: -10000 | E46: 0 | F46: 0
A47: Dividend | B47: -230721.66 | C47: -484310.57 | D47: -664179.3 | E47: -678908.84
A48: Devidend in the form of shares | B48: 0 | C48: =-C20 -> -1075971.5 | D48: 0 | E48: 0 | F48: =-237635.732 -> -237635.73
A49: Dividend in the form of cash | B49: 0 | C49: 0 | D49: 0 | E49: 0 | F49: =-F21 -> -2376343 | G49: =-0.1*G19 -> -732289.74 | H49: =-0.1*H22 -> -1464579.5 | I49: =-0.1*I22 -> -1464579.5 | J49: =-0.1*J22 -> -1464579.5 | K49: =-0.1*K22 -> -1464579.5
A50: Bonus share issuance | B50: -1538148.6 | C50: 0 | D50: 0 | E50: 0 | F50: 0
A51: Reclassifying | B51: 0 | C51: 0 | D51: 0 | E51: 1130.494 | F51: 0
A52: Other changes (Internal capital transactions) | B52: 0 | C52: -27410.937 | D52: 0 | E52: 0 | F52: 0
A53: Ending balance | B53: =SUM(B44:B47,B50) -> 2698572.7 | C53: =SUM(C44:C52) -> 3989603.8 | D53: =D8 -> 7149694.2 | E53: =SUM(E44:E52) -> 10389684 | F53: =SUM(F44:F51) -> 12674574 | G53: =SUM(G44:G49) -> 18594096 | H53: =SUM(H44:H49) -> 25407832 | I53: =SUM(I44:I49) -> 34695100 | J53: =SUM(J44:J49) -> 46174884 | K53: =SUM(K44:K49) -> 59237757
A55: Other capital
A56: Beginning balance | B56: =B5 -> 1130.5 | C56: =B58 -> 1130.5 | D56: =C58 -> 1130.5 | E56: =D58 -> 1130.5 | F56: =E58 -> 0 | G56: 0 | H56: 0 | I56: 0 | J56: 0 | K56: 0
A57: Reclassifying | B57: 0 | C57: 0 | D57: 0 | E57: =-E56 -> -1130.5 | F57: 0 | G57: 0 | H57: 0 | I57: 0 | J57: 0 | K57: 0
A58: Ending balance | B58: =B56 -> 1130.5 | C58: =C56 -> 1130.5 | D58: =D56 -> 1130.5 | E58: =SUM(E56:E57) -> 0 | F58: =F56 -> 0 | G58: 0 | H58: 0 | I58: 0 | J58: 0 | K58: 0
A59: Non-controlling interest
A60: Beginning balance | F60: =E62 -> 9280.6 | G60: =F62 -> 11838 | H60: =G62 -> 14911.925 | I60: =H62 -> 18764.27 | J60: =I62 -> 23118.474 | K60: =J62 -> 28020.642
A61: Profit during the period | F61: =DATA!G185 -> 2557.4 | G61: =IS!G19 -> 3073.9247 | H61: =IS!H19 -> 3852.3457 | I61: =IS!I19 -> 4354.2033 | J61: =IS!J19 -> 4902.1681 | K61: =IS!K19 -> 5435.971
A62: Ending balance | B62: =B9 -> 2776.3 | C62: =C9 -> 6249.4 | D62: =D9 -> 7786.1 | E62: =E9 -> 9280.6 | F62: =F9 -> 11838 | G62: =SUM(G60:G61) -> 14911.925 | H62: =SUM(H60:H61) -> 18764.27 | I62: =SUM(I60:I61) -> 23118.474 | J62: =SUM(J60:J61) -> 28020.642 | K62: =SUM(K60:K61) -> 33456.613

Sheet Multiple
E1: (CAGR 2019-2021) | F1: (Average 2019-2021) | K1: Historical | L1: 2017 | M1: 2018 | N1: 2019 | O1: 2020 | P1: 2021
A2: ICT&CE | B2: Ticker | C2: Name | D2: Countries | E2: Revenue growth | F2: GPM | G2: ROE | H2: Beta | I2: Market P/E | J2: P/E(LTM) | K2: Relative P/E (LTM) | L2: P/E 2017 | M2: P/E 2018 | N2: P/E 2019 | O2: P/E 2020 | P2: P/E 2021
A3: 1 | B3: DGW VN Equity | C3: Digiworld Corporation | D3: Vietnam | E3: 0.58 | F3: 0.0682 | G3: 0.2808 | H3: 1.08 | I3: 13.85 | J3: 15.58 | K3: =J3/I3 -> 1.1249097 | L3: 10.58 | M3: 8.39 | N3: 5.81 | O3: 13.79 | P3: 16.56 | Q3: Mean | R3: =MEDIAN(K13:P13) -> 14.468848
A4: 2 | B4: FRT VN Equity | C4: FPT DIGITAL RETAIL JSC | D4: Vietnam | E4: 0.0648 | F4: 0.128 | G4: 0.1818 | H4: 1.77 | I4: 13.85 | J4: 20.86 | K4: =J4/I4 -> 1.5061372 | L4: 0 | M4: 14.49 | N4: 8.06 | O4: 120.3 | P4: 17.84
A5: 3 | B5: COM7 TB Equity | C5: Com7 PCL | D5: Thailand | E5: 0.22 | F5: 0.131 | G5: 0.422 | H5: 1.32 | I5: 19.88 | J5: 36.2 | K5: =J5/I5 -> 1.8209256 | L5: 31.96 | M5: 20.95 | N5: 26.24 | O5: 31.45 | P5: 37.33 | Q5: MWG | R5: 2022F
A6: 4 | B6: ERAA IJ Equity | C6: Erajaya Swasembada Tbk (ERAA) | D6: Indonesia | E6: 0.142 | F6: 0.1 | G6: 0.114 | H6: 1.67 | I6: 13.92 | J6: 8.31 | K6: =J6/I6 -> 0.59698276 | L6: 6.28 | M6: 8.03 | N6: 19.51 | O6: 11.46 | P6: 9.38 | Q6: Earnings after tax | R6: 6740.9
A7: 5 | B7: 1373 HK Equity | C7: International Housewares Retail Co Ltd | D7: HongKong | E7: 0.4715 | F7: 0.459 | G7: 0.218 | H7: 0.7 | I7: 10.93 | J7: 10.52 | K7: =J7/I7 -> 0.96248856 | L7: 14.43 | M7: 10.89 | N7: 12.41 | O7: 9 | P7: 7.67 | Q7: BHX and An Khang's earnings after tax (estimated) | R7: -2300
C8: Industry average | E8: =AVERAGE(E3:E7) -> 0.29566 | F8: =AVERAGE(F3:F7) -> 0.17724 | G8: =AVERAGE(G3:G7) -> 0.24332 | H8: =AVERAGE(H3:H7) -> 1.308 | K8: =AVERAGE(K3:K7) -> 1.2022888 | L8: =AVERAGE(L3/I3,L5/I5,L6/I6,L7/I7,L4/I4) -> 0.82858276 | M8: =AVERAGE(M3/$I$3,M5/$I$5,M6/$I$6,M7/$I$7,M4/$I$4) -> 0.85580333 | N8: =AVERAGE(N3/$I$3,N5/$I$5,N6/$I$6,N7/$I$7,N4/$I$4) -> 0.97167023 | O8: =AVERAGE(O3/$I$3,O5/$I$5,O6/$I$6,O7/$I$7,O4/$I$4) -> 2.5820556 | P8: =AVERAGE(P3/$I$3,P5/$I$5,P6/$I$6,P7/$I$7,P4/$I$4) -> 1.147422 | Q8: ICT&CE's earnings after tax | R8: =R6-R7 -> 9040.9
C9: Comparison with industry peers | D9: =PRODUCT(E9:G9)^(1/3)/PRODUCT(H9) -> 0.98597142 | E9: =(1+E8)/(1+E10) -> 1.2729248 | F9: =(1+F8)/(1+F10) -> 0.97158735 | G9: =(1+G8)/(1+G10) -> 0.97908897 | H9: =(1+H8)/(1+AVERAGE(H10,J10)) -> 1.0810304 | I9: P/E VN | J9: 13.85 | Q9: Outstanding shares | R9: =DCF!B40 -> 731854815
C10: ICT&CE | E10: =((SALE!F3+SALE!F11+SALE!F19)/(SALE!D11+SALE!D3))^(1/2)-1 -> 0.017860606 | F10: =AVERAGE(19%,21.5%,23%) -> 0.21166667 | G10: =AVERAGE('Financial Ratios'!D28:F28) -> 0.26987438 | H10: 0.95 | I10: Industry Beta | J10: 1.32 | Q10: EPS Forward | R10: =R8*10^9/R9 -> 12353.406
C11: Market-adjusted target P/E ratio | E11: P/E VN | F11: 13.85 | K11: =K8*$J$9 -> 16.651699 | L11: =L8*$J$9 -> 11.475871 | M11: =M8*$J$9 -> 11.852876 | N11: =N8*$J$9 -> 13.457633 | O11: =O8*$J$9 -> 35.76147 | P11: =P8*$J$9 -> 15.891795 | Q11: Price | R11: =R10*R3 -> 178739.56
C12: Relative adjustment | J12: =D9 -> 0.98597142
C13: Target P/E adjusted from operational performance | K13: =K11*$J$12 -> 16.4181 | L13: =L11*$J$12 -> 11.314881 | M13: =M11*$J$12 -> 11.686597 | N13: =N11*$J$12 -> 13.268841 | O13: =O11*$J$12 -> 35.259787 | P13: =P11*$J$12 -> 15.668855
A16: FMCG | B16: Ticker | C16: Name | D16: Countries | E16: Revenue growth | F16: GPM | G16: Beta | H16: Market P/E | I16: P/S(LTM) | J16: Relative P/S (LTM) | K16: P/S 2017 | L16: P/S 2018 | M16: P/S 2019 | N16: P/S 2020 | O16: P/S 2021 | Q16: BETA (BHX)
A17: 1 | B17: MSN VN Equity | C17: Masan Group Corporation | D17: VietNam | E17: 0.5403 | F17: 0.2581 | G17: 0.8 | H17: 13.85 | I17: 1.97 | J17: =I17/H17 -> 0.14223827 | K17: 2.14 | L17: 2.19 | M17: 1.76 | N17: 1.35 | O17: 2.27 | Q17: Beta L | R17: =(1+(1-R19)*R18)*R20 -> 0.5475
A18: 2 | B18: VNM VN Equity | C18: Vietnam Dairy Products JSC | D18: VietNam | E18: 0.04 | F18: 0.4557 | G18: 0.7 | H18: 13.85 | I18: 2.38 | J18: =I18/H18 -> 0.17184116 | K18: 5.93 | L18: 3.98 | M18: 3.6 | N18: 3.81 | O18: 2.96 | Q18: D/E | R18: 0
A19: 3 | B19: AMRT IJ | C19: Sumber Alfaria Trijaya Tbk PT | D19: Indonesia | E19: 0.0787 | F19: 0.2036 | G19: 0.38 | H19: 13.92 | I19: 0.87 | J19: =I19/H19 -> 0.0625 | K19: 0.41 | L19: 0.58 | M19: 0.5 | N19: 0.44 | O19: 0.59 | Q19: tax rate | R19: 0
A20: 4 | B20: 5903 TT | C20: Taiwan FamilyMart Co Ltd | D20: Taiwan | E20: 0.0374 | F20: 0.3642 | G20: 0.31 | H20: 11.96 | I20: 0.51 | J20: =I20/H20 -> 0.04264214 | K20: 0.62 | L20: 0.66 | M20: 0.63 | N20: 0.69 | O20: 0.66 | Q20: Beta U | R20: =G21 -> 0.5475
C21: Industry average | E21: =AVERAGE(E17:E20) -> 0.1741 | F21: =AVERAGE(F17:F20) -> 0.3204 | G21: =AVERAGE(G17:G20) -> 0.5475 | H21: =AVERAGE(H17:H20) -> 13.395 | J21: =AVERAGE(J17:J20) -> 0.10480539 | K21: =AVERAGE(K17/$H$17,K18/$H$18,K19/$H$19,K20/$H$20) -> 0.16599124 | L21: =AVERAGE(L17/$H$17,L18/$H$18,L19/$H$19,L20/$H$20) -> 0.13558449 | M21: =AVERAGE(M17/$H$17,M18/$H$18,M19/$H$19,M20/$H$20) -> 0.11889968 | N21: =AVERAGE(N17/$H$17,N18/$H$18,N19/$H$19,N20/$H$20) -> 0.11546617 | O21: =AVERAGE(O17/$H$17,O18/$H$18,O19/$H$19,O20/$H$20) -> 0.11879658 | Q21: Adjusted Beta | R21: =R17*0.67+1*0.33 -> 0.696825
C22: Comparison with industry peers | D22: =(PRODUCT(E22:F22)^(1/2))/PRODUCT(G22) -> 0.96690555 | E22: =(1+E21)/(1+E23) -> 0.72396813 | F22: =(1+F21)/(1+F23) -> 1.0740781 | G22: =(1+G21)/(1+G23) -> 0.91199741 | I22: P/E VN | J22: 13.85
C23: Bach Hoa Xanh | E23: =(SALE!F36/SALE!D36)^(1/2)-1 -> 0.62175646 | F23: =AVERAGE(18.9%,24.9%,25%) -> 0.22933333 | G23: =R21 -> 0.696825 | Q23: Revenue in 12 months forward | R23: =SALE!G36 -> 31981296
C24: Market-adjusted target P/S ratio | K24: =$J$22*K21 -> 2.2989787 | L24: =$J$22*L21 -> 1.8778452 | M24: =$J$22*M21 -> 1.6467606 | N24: =$J$22*N21 -> 1.5992065 | O24: =$J$22*O21 -> 1.6453327 | Q24: Outstanding shares | R24: =R9 -> 731854815
C25: Relative adjustment | J25: =D22 -> 0.96690555 | Q25: Mean | R25: =MEDIAN(K26:O26) -> 1.592262
C26: Target P/S adjusted from operational performance | K26: =K24*$J$25 -> 2.2228953 | L26: =L24*$J$25 -> 1.815699 | M26: =M24*$J$25 -> 1.592262 | N26: =N24*$J$25 -> 1.5462816 | O26: =O24*$J$25 -> 1.5908813 | Q26: Revenue/COGS in 2022 | R26: =R24*10^3/R23 -> 22883.839
Q27: P/S FW | R27: =R25 -> 1.592262
Q28: Price | R28: =R25*R26 -> 36437.066
A31: Pharaceutical retail | B31: Ticker | C31: Name | D31: Countries | E31: Revenue growth | F31: GPM | G31: Beta | H31: Market P/E | I31: P/S(LTM) | J31: Relative P/S (LTM) | K31: P/S 2017 | L31: P/S 2018 | M31: P/S 2019 | N31: P/S 2020 | O31: P/S 2021 | Q31: Revenue in 12 months forward | R31: =SALE!G52 -> 1.5296685e+08
A32: 1 | B32: KAEF IJ Equity | C32: Kimia Farma Persero Tbk | D32: Indonesia | E32: 0.1627 | F32: 0.3673 | G32: -0.48 | H32: 13.92 | I32: 0.64 | J32: =I32/H32 -> 0.045977011 | K32: 2.45 | L32: 1.71 | M32: 0.74 | N32: 2.36 | O32: 1.05 | Q32: Outstanding shares | R32: =R9 -> 731854815
A33: 2 | B33: RRHI:PM | C33: Robinsons Retail Holdings Inc | D33: Philippines | E33: -0.0056 | F33: 0.2253 | G33: 0.5 | H33: 22.49 | I33: 0.53 | J33: =I33/H33 -> 0.023566029 | K33: 1.16 | L33: 0.84 | M33: 0.77 | N33: 0.68 | O33: 0.65 | Q33: Revenue/COGS in 2022 | R33: =R32*1000/R31 -> 4784.4013
A34: 3 | B34: KLBF:IJ | C34: Kalbe Farma Tbk PT | D34: Indonesia | E34: 0.0771 | F34: 0.4419 | G34: 0.62 | H34: 13.92 | I34: 2.7926 | J34: =I34/H34 -> 0.20061782 | K34: 3.131 | L34: 2.749 | M34: 2.898 | N34: 2.482 | O34: 2.16 | Q34: Mean P/S | R34: =MEDIAN(K42:O42) -> 1.0350618
A35: 4 | B35: 600833 CH Equity | C35: Shanghai No1 Pharmacy Co Ltd | D35: China | E35: 0.1 | F35: 0.1852 | G35: 1.14 | H35: 12.34 | I35: 1.45 | J35: =I35/H35 -> 0.11750405 | K35: 1.99 | L35: 1.73 | M35: 1.69 | N35: 1.37 | O35: 1.49 | Q35: P/S FW | R35: =R34 -> 1.0350618
A36: 5 | B36: 600713 CH Equity | C36: NanJing Pharmaceutical Co Ltd | D36: China | E36: 0.14 | F36: 0.0649 | G36: 1.05 | H36: 12.34 | I36: 0.11 | J36: =I36/H36 -> 0.0089141005 | K36: 0.19 | L36: 0.14 | M36: 0.13 | N36: 0.12 | O36: 0.11 | Q36: Price | R36: =R33*R34 -> 4952.1508
C37: Industry average | E37: =AVERAGE(E32:E36) -> 0.09484 | F37: =AVERAGE(F32:F36) -> 0.25692 | G37: =AVERAGE(G32:G36) -> 0.566 | J37: =AVERAGE(J32:J36) -> 0.079315802 | K37: =AVERAGE(K32/$H$32,K33/$H$33,K34/$H$34,K35/$H$35,K36/$H$36) -> 0.12583473 | L37: =AVERAGE(L32/$H$32,L33/$H$33,L34/$H$34,L35/$H$35,L36/$H$36) -> 0.10184402 | M37: =AVERAGE(M32/$H$32,M33/$H$33,M34/$H$34,M35/$H$35,M36/$H$36) -> 0.088615172 | N37: =AVERAGE(N32/$H$32,N33/$H$33,N34/$H$34,N35/$H$35,N36/$H$36) -> 0.099765206 | O37: =AVERAGE(O32/$H$32,O33/$H$33,O34/$H$34,O35/$H$35,O36/$H$36) -> 0.077832965
C38: Comparison with industry peers | D38: =(PRODUCT(E38:F38)^(1/2))/PRODUCT(G38) -> 0.74909585 | E38: =(1+E37)/(1+E39) -> 1.09484 | F38: =(1+F37)/(1+F39) -> 1.25692 | G38: =(1+G37)/(1+G39) -> 1.566 | I38: P/E VN | J38: 13.85 | Q38: MWG's price per share | R38: =R36+R28+R11 -> 220128.78
C39: An Khang Pharmaceutical | E39: 0 | F39: 0 | G39: 0
C40: Market-adjusted target P/S ratio | K40: =$J$38*K37 -> 1.742811 | L40: =$J$38*L37 -> 1.4105397 | M40: =$J$38*M37 -> 1.2273201 | N40: =$J$38*N37 -> 1.3817481 | O40: =$J$38*O37 -> 1.0779866
C41: Relative adjustment | J41: =D38 -> 0.74909585
C42: Target P/E adjusted from operational performance | K42: =K40*$J$41 -> 1.3055325 | L42: =L40*$J$41 -> 1.0566294 | M42: =M40*$J$41 -> 0.91938041 | N42: =N40*$J$41 -> 1.0350618 | O42: =O40*$J$41 -> 0.80751526

Sheet Beta
A3: DD/MM/YYYY | B3: VN-Index | C3: MWG | D3: Change in VN-Index | E3: Change in MWG
A4: 44626 | B4: 1287.98 | C4: 153200
A5: 44598 | B5: 1288.62 | C5: 147700 | D5: =(B5/B4)-1 -> 0.00049690213 | E5: =(C5/C4)-1 -> -0.035900783 | H5: Beta L | I5: =SLOPE($E$5:$E$252,$D$5:$D$252) -> 1.1015464
A6: 44567 | B6: 1299.52 | C6: 145500 | D6: =(B6/B5)-1 -> 0.0084586612 | E6: =(C6/C5)-1 -> -0.014895058 | H6: D/E | I6: =(BS!G75+BS!G86)/BS!G93 -> 1.2094993
A7: 31/05/2022 | B7: 1292.68 | C7: 144900 | D7: =(B7/B6)-1 -> -0.0052634819 | E7: =(C7/C6)-1 -> -0.0041237113 | H7: Tax rate | I7: =IS!G41 -> 0.013408104
A8: 30/05/2022 | B8: 1293.92 | C8: 145200 | D8: =(B8/B7)-1 -> 0.00095924745 | E8: =(C8/C7)-1 -> 0.0020703934 | H8: Beta U | I8: =I5/(1+(1-I7)*I6) -> 0.50223651
A9: 27/05/2022 | B9: 1285.45 | C9: 146700 | D9: =(B9/B8)-1 -> -0.0065459998 | E9: =(C9/C8)-1 -> 0.010330579
A10: 26/05/2022 | B10: 1268.57 | C10: 139000 | D10: =(B10/B9)-1 -> -0.013131588 | E10: =(C10/C9)-1 -> -0.052488071
A11: 25/05/2022 | B11: 1268.43 | C11: 139000 | D11: =(B11/B10)-1 -> -0.00011036048 | E11: =(C11/C10)-1 -> 0
A12: 24/05/2022 | B12: 1233.38 | C12: 133000 | D12: =(B12/B11)-1 -> -0.027632585 | E12: =(C12/C11)-1 -> -0.043165468
A13: 23/05/2022 | B13: 1218.81 | C13: 130800 | D13: =(B13/B12)-1 -> -0.011813067 | E13: =(C13/C12)-1 -> -0.016541353
A14: 20/05/2022 | B14: 1240.71 | C14: 134000 | D14: =(B14/B13)-1 -> 0.017968346 | E14: =(C14/C13)-1 -> 0.024464832
A15: 19/05/2022 | B15: 1241.64 | C15: 133000 | D15: =(B15/B14)-1 -> 0.00074957081 | E15: =(C15/C14)-1 -> -0.0074626866
A16: 18/05/2022 | B16: 1240.76 | C16: 133500 | D16: =(B16/B15)-1 -> -0.00070874005 | E16: =(C16/C15)-1 -> 0.0037593985
A17: 17/05/2022 | B17: 1228.37 | C17: 131600 | D17: =(B17/B16)-1 -> -0.0099858151 | E17: =(C17/C16)-1 -> -0.01423221
A18: 16/05/2022 | B18: 1171.95 | C18: 123000 | D18: =(B18/B17)-1 -> -0.045930786 | E18: =(C18/C17)-1 -> -0.065349544
A19: 13/05/2022 | B19: 1182.77 | C19: 125100 | D19: =(B19/B18)-1 -> 0.0092324758 | E19: =(C19/C18)-1 -> 0.017073171
A20: 44900 | B20: 1238.84 | C20: 134400 | D20: =(B20/B19)-1 -> 0.047405666 | E20: =(C20/C19)-1 -> 0.074340528
A21: 44870 | B21: 1301.53 | C21: 141000 | D21: =(B21/B20)-1 -> 0.050603791 | E21: =(C21/C20)-1 -> 0.049107143
A22: 44839 | B22: 1293.56 | C22: 140100 | D22: =(B22/B21)-1 -> -0.0061235623 | E22: =(C22/C21)-1 -> -0.0063829787
A23: 44809 | B23: 1269.62 | C23: 136400 | D23: =(B23/B22)-1 -> -0.018507066 | E23: =(C23/C22)-1 -> -0.026409707
A24: 44717 | B24: 1329.26 | C24: 146600 | D24: =(B24/B23)-1 -> 0.046974685 | E24: =(C24/C23)-1 -> 0.074780059
A25: 44686 | B25: 1360.68 | C25: 149400 | D25: =(B25/B24)-1 -> 0.023637212 | E25: =(C25/C24)-1 -> 0.019099591
A26: 44656 | B26: 1348.68 | C26: 149500 | D26: =(B26/B25)-1 -> -0.0088191199 | E26: =(C26/C25)-1 -> 0.00066934404
A27: 29/04/2022 | B27: 1366.8 | C27: 149200 | D27: =(B27/B26)-1 -> 0.013435359 | E27: =(C27/C26)-1 -> -0.002006689
A28: 28/04/2022 | B28: 1350.99 | C28: 145000 | D28: =(B28/B27)-1 -> -0.011567164 | E28: =(C28/C27)-1 -> -0.028150134
A29: 27/04/2022 | B29: 1353.77 | C29: 147200 | D29: =(B29/B28)-1 -> 0.0020577502 | E29: =(C29/C28)-1 -> 0.015172414
A30: 26/04/2022 | B30: 1341.34 | C30: 148800 | D30: =(B30/B29)-1 -> -0.0091817665 | E30: =(C30/C29)-1 -> 0.010869565
A31: 25/04/2022 | B31: 1310.92 | C31: 144900 | D31: =(B31/B30)-1 -> -0.022678814 | E31: =(C31/C30)-1 -> -0.026209677
A32: 22/04/2022 | B32: 1379.23 | C32: 155800 | D32: =(B32/B31)-1 -> 0.052108443 | E32: =(C32/C31)-1 -> 0.075224293
A33: 21/04/2022 | B33: 1370.21 | C33: 155500 | D33: =(B33/B32)-1 -> -0.0065398809 | E33: =(C33/C32)-1 -> -0.0019255456
A34: 20/04/2022 | B34: 1384.72 | C34: 156000 | D34: =(B34/B33)-1 -> 0.010589618 | E34: =(C34/C33)-1 -> 0.0032154341
A35: 19/04/2022 | B35: 1406.45 | C35: 156000 | D35: =(B35/B34)-1 -> 0.015692703 | E35: =(C35/C34)-1 -> 0
A36: 18/04/2022 | B36: 1432.6 | C36: 160200 | D36: =(B36/B35)-1 -> 0.018592911 | E36: =(C36/C35)-1 -> 0.026923077
A37: 15/04/2022 | B37: 1458.56 | C37: 160200 | D37: =(B37/B36)-1 -> 0.018120899 | E37: =(C37/C36)-1 -> 0
A38: 14/04/2022 | B38: 1472.12 | C38: 159500 | D38: =(B38/B37)-1 -> 0.0092968407 | E38: =(C38/C37)-1 -> -0.0043695381
A39: 13/04/2022 | B39: 1477.2 | C39: 156200 | D39: =(B39/B38)-1 -> 0.0034508056 | E39: =(C39/C38)-1 -> -0.020689655
A40: 44899 | B40: 1455.25 | C40: 152700 | D40: =(B40/B39)-1 -> -0.014859193 | E40: =(C40/C39)-1 -> -0.02240717
A41: 44777 | B41: 1482 | C41: 150000 | D41: =(B41/B40)-1 -> 0.018381721 | E41: =(C41/C40)-1 -> -0.017681729
A42: 44746 | B42: 1502.35 | C42: 155000 | D42: =(B42/B41)-1 -> 0.013731444 | E42: =(C42/C41)-1 -> 0.033333333
A43: 44716 | B43: 1522.9 | C43: 158800 | D43: =(B43/B42)-1 -> 0.01367857 | E43: =(C43/C42)-1 -> 0.024516129
A44: 44685 | B44: 1520.03 | C44: 155200 | D44: =(B44/B43)-1 -> -0.0018845623 | E44: =(C44/C43)-1 -> -0.022670025
A45: 44655 | B45: 1524.7 | C45: 155000 | D45: =(B45/B44)-1 -> 0.0030723078 | E45: =(C45/C44)-1 -> -0.0012886598
A46: 44565 | B46: 1516.44 | C46: 156000 | D46: =(B46/B45)-1 -> -0.0054174592 | E46: =(C46/C45)-1 -> 0.0064516129
A47: 31/03/2022 | B47: 1492.15 | C47: 145800 | D47: =(B47/B46)-1 -> -0.016017778 | E47: =(C47/C46)-1 -> -0.065384615
A48: 30/03/2022 | B48: 1490.51 | C48: 144400 | D48: =(B48/B47)-1 -> -0.0010990852 | E48: =(C48/C47)-1 -> -0.0096021948
A49: 29/03/2022 | B49: 1497.76 | C49: 146500 | D49: =(B49/B48)-1 -> 0.0048641069 | E49: =(C49/C48)-1 -> 0.014542936
A50: 28/03/2022 | B50: 1483.18 | C50: 144000 | D50: =(B50/B49)-1 -> -0.0097345369 | E50: =(C50/C49)-1 -> -0.017064846
A51: 25/03/2022 | B51: 1498.5 | C51: 138900 | D51: =(B51/B50)-1 -> 0.010329158 | E51: =(C51/C50)-1 -> -0.035416667
A52: 24/03/2022 | B52: 1498.26 | C52: 134000 | D52: =(B52/B51)-1 -> -0.00016016016 | E52: =(C52/C51)-1 -> -0.035277178
A53: 23/03/2022 | B53: 1502.34 | C53: 135000 | D53: =(B53/B52)-1 -> 0.0027231589 | E53: =(C53/C52)-1 -> 0.0074626866
A54: 22/03/2022 | B54: 1503.78 | C54: 135200 | D54: =(B54/B53)-1 -> 0.00095850473 | E54: =(C54/C53)-1 -> 0.0014814815
A55: 21/03/2022 | B55: 1494.95 | C55: 134900 | D55: =(B55/B54)-1 -> -0.0058718696 | E55: =(C55/C54)-1 -> -0.0022189349
A56: 18/03/2022 | B56: 1469.1 | C56: 131600 | D56: =(B56/B55)-1 -> -0.017291548 | E56: =(C56/C55)-1 -> -0.024462565
A57: 17/03/2022 | B57: 1461.34 | C57: 130800 | D57: =(B57/B56)-1 -> -0.0052821455 | E57: =(C57/C56)-1 -> -0.0060790274
A58: 16/03/2022 | B58: 1459.33 | C58: 131400 | D58: =(B58/B57)-1 -> -0.0013754499 | E58: =(C58/C57)-1 -> 0.004587156
... A60: 14/03/2022 | B60: 1446.25 | C60: 131700 | D60: =(B60/B59)-1 -> -0.0044674202 | E60: =(C60/C59)-1 -> 0.002283105
A61: 44868 | B61: 1466.54 | C61: 133000 | D61: =(B61/B60)-1 -> 0.014029386 | E61: =(C61/C60)-1 -> 0.0098709188
A62: 44837 | B62: 1479.08 | C62: 133500 | D62: =(B62/B61)-1 -> 0.0085507385 | E62: =(C62/C61)-1 -> 0.0037593985
A63: 44807 | B63: 1473.74 | C63: 133800 | D63: =(B63/B62)-1 -> -0.0036103524 | E63: =(C63/C62)-1 -> 0.002247191
A64: 44776 | B64: 1473.71 | C64: 134200 | D64: =(B64/B63)-1 -> -2.0356372e-05 | E64: =(C64/C63)-1 -> 0.0029895366
A65: 44745 | B65: 1499.05 | C65: 134200 | D65: =(B65/B64)-1 -> 0.017194699 | E65: =(C65/C64)-1 -> 0
A66: 44654 | B66: 1505.33 | C66: 135800 | D66: =(B66/B65)-1 -> 0.0041893199 | E66: =(C66/C65)-1 -> 0.011922504
A67: 44623 | B67: 1505 | C67: 136500 | D67: =(B67/B66)-1 -> -0.00021922103 | E67: =(C67/C66)-1 -> 0.0051546392
A68: 44595 | B68: 1485.52 | C68: 134500 | D68: =(B68/B67)-1 -> -0.012943522 | E68: =(C68/C67)-1 -> -0.014652015
A69: 44564 | B69: 1498.78 | C69: 136000 | D69: =(B69/B68)-1 -> 0.0089261673 | E69: =(C69/C68)-1 -> 0.011152416
A70: 28/02/2022 | B70: 1490.13 | C70: 136000 | D70: =(B70/B69)-1 -> -0.0057713607 | E70: =(C70/C69)-1 -> 0
A71: 25/02/2022 | B71: 1498.89 | C71: 137600 | D71: =(B71/B70)-1 -> 0.0058786817 | E71: =(C71/C70)-1 -> 0.011764706
A72: 24/02/2022 | B72: 1494.85 | C72: 136800 | D72: =(B72/B71)-1 -> -0.0026953279 | E72: =(C72/C71)-1 -> -0.0058139535
A73: 23/02/2022 | B73: 1512.3 | C73: 137800 | D73: =(B73/B72)-1 -> 0.011673412 | E73: =(C73/C72)-1 -> 0.0073099415
A74: 22/02/2022 | B74: 1503.47 | C74: 137700 | D74: =(B74/B73)-1 -> -0.0058387886 | E74: =(C74/C73)-1 -> -0.0007256894
A75: 21/02/2022 | B75: 1510.84 | C75: 133900 | D75: =(B75/B74)-1 -> 0.0049019934 | E75: =(C75/C74)-1 -> -0.027596224
A76: 18/02/2022 | B76: 1504.84 | C76: 134000 | D76: =(B76/B75)-1 -> -0.0039713007 | E76: =(C76/C75)-1 -> 0.00074682599
A77: 17/02/2022 | B77: 1507.99 | C77: 134500 | D77: =(B77/B76)-1 -> 0.0020932458 | E77: =(C77/C76)-1 -> 0.0037313433
A78: 16/02/2022 | B78: 1492.1 | C78: 132900 | D78: =(B78/B77)-1 -> -0.010537205 | E78: =(C78/C77)-1 -> -0.011895911
A79: 15/02/2022 | B79: 1492.75 | C79: 133300 | D79: =(B79/B78)-1 -> 0.00043562764 | E79: =(C79/C78)-1 -> 0.0030097818
A80: 14/02/2022 | B80: 1471.96 | C80: 132000 | D80: =(B80/B79)-1 -> -0.013927315 | E80: =(C80/C79)-1 -> -0.0097524381
A81: 44867 | B81: 1501.71 | C81: 135300 | D81: =(B81/B80)-1 -> 0.020211147 | E81: =(C81/C80)-1 -> 0.025
A82: 44836 | B82: 1506.79 | C82: 136300 | D82: =(B82/B81)-1 -> 0.0033828103 | E82: =(C82/C81)-1 -> 0.007390983
A83: 44806 | B83: 1505.38 | C83: 137000 | D83: =(B83/B82)-1 -> -0.00093576411 | E83: =(C83/C82)-1 -> 0.00513573
A84: 44775 | B84: 1500.99 | C84: 136300 | D84: =(B84/B83)-1 -> -0.0029162072 | E84: =(C84/C83)-1 -> -0.0051094891
A85: 44744 | B85: 1497.66 | C85: 133900 | D85: =(B85/B84)-1 -> -0.0022185358 | E85: =(C85/C84)-1 -> -0.017608217
A86: 28/01/2022 | B86: 1478.96 | C86: 132500 | D86: =(B86/B85)-1 -> -0.012486145 | E86: =(C86/C85)-1 -> -0.010455564
A87: 27/01/2022 | B87: 1470.76 | C87: 131500 | D87: =(B87/B86)-1 -> -0.0055444366 | E87: =(C87/C86)-1 -> -0.0075471698
A88: 26/01/2022 | B88: 1481.58 | C88: 131900 | D88: =(B88/B87)-1 -> 0.0073567407 | E88: =(C88/C87)-1 -> 0.0030418251
A89: 25/01/2022 | B89: 1479.58 | C89: 131000 | D89: =(B89/B88)-1 -> -0.0013499102 | E89: =(C89/C88)-1 -> -0.006823351
A90: 24/01/2022 | B90: 1439.71 | C90: 129900 | D90: =(B90/B89)-1 -> -0.026946836 | E90: =(C90/C89)-1 -> -0.0083969466
A91: 21/01/2022 | B91: 1472.89 | C91: 133200 | D91: =(B91/B90)-1 -> 0.023046308 | E91: =(C91/C90)-1 -> 0.025404157
A92: 20/01/2022 | B92: 1465.3 | C92: 134000 | D92: =(B92/B91)-1 -> -0.0051531343 | E92: =(C92/C91)-1 -> 0.006006006
A93: 19/01/2022 | B93: 1442.79 | C93: 133500 | D93: =(B93/B92)-1 -> -0.015362042 | E93: =(C93/C92)-1 -> -0.0037313433
A94: 18/01/2022 | B94: 1438.94 | C94: 130100 | D94: =(B94/B93)-1 -> -0.002668441 | E94: =(C94/C93)-1 -> -0.025468165
A95: 17/01/2022 | B95: 1452.84 | C95: 130000 | D95: =(B95/B94)-1 -> 0.0096598885 | E95: =(C95/C94)-1 -> -0.00076863951
A96: 14/01/2022 | B96: 1496.02 | C96: 134000 | D96: =(B96/B95)-1 -> 0.029721098 | E96: =(C96/C95)-1 -> 0.030769231
A97: 13/01/2022 | B97: 1496.05 | C97: 135500 | D97: =(B97/B96)-1 -> 2.0053208e-05 | E97: =(C97/C96)-1 -> 0.01119403
A98: 44896 | B98: 1510.51 | C98: 136000 | D98: =(B98/B97)-1 -> 0.0096654524 | E98: =(C98/C97)-1 -> 0.0036900369
A99: 44866 | B99: 1492.31 | C99: 131800 | D99: =(B99/B98)-1 -> -0.012048911 | E99: =(C99/C98)-1 -> -0.030882353
A100: 44835 | B100: 1503.71 | C100: 133000 | D100: =(B100/B99)-1 -> 0.0076391634 | E100: =(C100/C99)-1 -> 0.0091047041
A101: 44743 | B101: 1528.48 | C101: 135500 | D101: =(B101/B100)-1 -> 0.016472591 | E101: =(C101/C100)-1 -> 0.018796992
A102: 44713 | B102: 1528.57 | C102: 137500 | D102: =(B102/B101)-1 -> 5.8882027e-05 | E102: =(C102/C101)-1 -> 0.014760148
A103: 44682 | B103: 1522.5 | C103: 137100 | D103: =(B103/B102)-1 -> -0.0039710317 | E103: =(C103/C102)-1 -> -0.0029090909
...

Sheet Sheet1
E1: (CAGR 2019-2021) | F1: (Average 2019-2021) | K1: Historical | L1: 2017 | M1: 2018 | N1: 2019 | O1: 2020 | P1: 2021
A2: ICT&CE | B2: Ticker | C2: Name | D2: Quốc gia | E2: Revenue growth | F2: GPM | G2: ROE | H2: Beta | I2: Market P/E | J2: P/E(LTM) | K2: Relative P/E (LTM) | L2: P/E 2017 | M2: P/E 2018 | N2: P/E 2019 | O2: P/E 2020 | P2: P/E 2021
A3: 1 | B3: DGW VN Equity | C3: Digiworld Corporation | D3: Vietnam | E3: 0.58 | F3: 0.0682 | G3: 0.2808 | H3: 1.08 | I3: 13.85 | J3: 15.58 | K3: 1.1249097 | L3: 10.58 | M3: 8.39 | N3: 5.81 | O3: 13.79 | P3: 16.56 | Q3: Mean | R3: 14.468848
A4: 2 | B4: FRT VN Equity | C4: FPT DIGITAL RETAIL JSC | D4: Vietnam | E4: 0.0648 | F4: 0.128 | G4: 0.1818 | H4: 1.77 | I4: 13.85 | J4: 20.86 | K4: 1.5061372 | L4: 0 | M4: 14.49 | N4: 8.06 | O4: 120.3 | P4: 17.84
A5: 3 | B5: COM7 TB Equity | C5: Com7 PCL | D5: Thailand | E5: 0.22 | F5: 0.131 | G5: 0.422 | H5: 1.32 | I5: 19.88 | J5: 36.2 | K5: 1.8209256 | L5: 31.96 | M5: 20.95 | N5: 26.24 | O5: 31.45 | P5: 37.33 | Q5: MWG | R5: 2022F
A6: 4 | B6: ERAA IJ Equity | C6: Erajaya Swasembada Tbk (ERAA) | D6: Indonesia | E6: 0.142 | F6: 0.1 | G6: 0.114 | H6: 1.67 | I6: 13.92 | J6: 8.31 | K6: 0.59698276 | L6: 6.28 | M6: 8.03 | N6: 19.51 | O6: 11.46 | P6: 9.38 | Q6: LNST MWG | R6: 6740.9
A7: 5 | B7: 1373 HK Equity | C7: International Housewares Retail Co Ltd | D7: HongKong | E7: 0.4715 | F7: 0.459 | G7: 0.218 | H7: 0.7 | I7: 10.93 | J7: 10.52 | K7: 0.96248856 | L7: 14.43 | M7: 10.89 | N7: 12.41 | O7: 9 | P7: 7.67 | Q7: LNST BHX&AK ước tính | R7: -2300
C8: Trung bình so sánh | E8: 0.29566 | F8: 0.17724 | G8: 0.24332 | H8: 1.308 | K8: 1.2022888 | L8: 0.82858276 | M8: 0.85580333 | N8: 0.97167023 | O8: 2.5820556 | P8: 1.147422 | Q8: LNST ICT&CE | R8: 9040.9
C9: Tương quan với cty cùng ngành | D9: 0.98597142 | E9: 1.2729248 | F9: 0.97158735 | G9: 0.97908897 | H9: 1.0810304 | I9: P/E VN | J9: 13.85 | Q9: SL cổ phiếu lưu hành | R9: 731854815
C10: ICT&CE | E10: 0.017860606 | F10: 0.21166667 | G10: 0.26987438 | H10: 0.95 | I10: Beta Ngành | J10: 1.32 | Q10: EPS Forward | R10: 12353.406
C11: Target P/E điều chỉnh từ thị trường | E11: P/E VN | F11: 13.85 | K11: 16.651699 | L11: 11.475871 | M11: 11.852876 | N11: 13.457633 | O11: 35.76147 | P11: 15.891795 | Q11: Gía trị trên cổ phần | R11: 178739.56
C12: Điều chỉnh tương quan | J12: 0.98597142
C13: Target P/E điều chỉnh từ thành quả HĐ | K13: 16.4181 | L13: 11.314881 | M13: 11.686597 | N13: 13.268841 | O13: 35.259787 | P13: 15.668855
A16: FMCG | B16: Ticker | C16: Name | D16: Quốc gia | E16: Revenue growth | F16: GPM | G16: Beta | H16: Market P/E | I16: P/S(LTM) | J16: Relative P/S (LTM) | K16: P/S 2017 | L16: P/S 2018 | M16: P/S 2019 | N16: P/S 2020 | O16: P/S 2021 | Q16: BETA (BHX)
A17: 1 | B17: MSN VN Equity | C17: Masan Group Corporation | D17: VietNam | E17: 0.5403 | F17: 0.2581 | G17: 0.8 | H17: 13.85 | I17: 1.97 | J17: 0.14223827 | K17: 2.14 | L17: 2.19 | M17: 1.76 | N17: 1.35 | O17: 2.27 | Q17: Beta L | R17: 0.5475
A18: 2 | B18: VNM VN Equity | C18: Vietnam Dairy Products JSC | D18: VietNam | E18: 0.04 | F18: 0.4557 | G18: 0.7 | H18: 13.85 | I18: 2.38 | J18: 0.17184116 | K18: 5.93 | L18: 3.98 | M18: 3.6 | N18: 3.81 | O18: 2.96 | Q18: D/E | R18: 0
A19: 3 | B19: AMRT IJ | C19: Sumber Alfaria Trijaya Tbk PT | D19: Indonesia | E19: 0.0787 | F19: 0.2036 | G19: 0.38 | H19: 13.92 | I19: 0.87 | J19: 0.0625 | K19: 0.41 | L19: 0.58 | M19: 0.5 | N19: 0.44 | O19: 0.59 | Q19: Thuế suất | R19: 0
A20: 4 | B20: 5903 TT | C20: Taiwan FamilyMart Co Ltd | D20: Taiwan | E20: 0.0374 | F20: 0.3642 | G20: 0.31 | H20: 11.96 | I20: 0.51 | J20: 0.04264214 | K20: 0.62 | L20: 0.66 | M20: 0.63 | N20: 0.69 | O20: 0.66 | Q20: Beta U | R20: 0.5475
C21: Trung bình so sánh | E21: 0.1741 | F21: 0.3204 | G21: 0.5475 | H21: 13.395 | J21: 0.10480539 | K21: 0.16599124 | L21: 0.13558449 | M21: 0.11889968 | N21: 0.11546617 | O21: 0.11879658 | Q21: Adjusted Beta | R21: 0.696825
C22: Tương quan với cty cùng ngành | D22: 0.96690555 | E22: 0.72396813 | F22: 1.0740781 | G22: 0.91199741 | I22: P/E VN | J22: 13.85
C23: Bách Hóa Xanh | E23: 0.62175646 | F23: 0.22933333 | G23: 0.696825 | Q23: Doanh thu 12m Forward | R23: 31981296
C24: Target P/S điều chỉnh từ thị trường | K24: 2.2989787 | L24: 1.8778452 | M24: 1.6467606 | N24: 1.5992065 | O24: 1.6453327 | Q24: SL CP LL | R24: 731854815
C25: Điều chỉnh tương quan | J25: 0.96690555 | Q25: Mean | R25: 1.592262
C26: Target P/S điều chỉnh từ thành quả HĐ | K26: 2.2228953 | L26: 1.815699 | M26: 1.592262 | N26: 1.5462816 | O26: 1.5908813 | Q26: Doanh thu / CP năm 2022 | R26: 22883.839
Q27: P/S FW | R27: 1.592262
Q28: Giá cổ phiếu | R28: 36437.066
A31: Pharaceutical retail | B31: Ticker | C31: Name | D31: Quốc gia | E31: Revenue growth | F31: GPM | G31: Beta | H31: Market P/E | I31: P/S(LTM) | J31: Relative P/S (LTM) | K31: P/S 2017 | L31: P/S 2018 | M31: P/S 2019 | N31: P/S 2020 | O31: P/S 2021 | Q31: Doanh thu 12m Forward | R31: 1.5296685e+08
A32: 1 | B32: KAEF IJ Equity | C32: Kimia Farma Persero Tbk | D32: Indonesia | E32: 0.1627 | F32: 0.3673 | G32: -0.48 | H32: 13.92 | I32: 0.64 | J32: 0.045977011 | K32: 2.45 | L32: 1.71 | M32: 0.74 | N32: 2.36 | O32: 1.05 | Q32: SL CP LL | R32: 731854815
A33: 2 | B33: RRHI:PM | C33: Robinsons Retail Holdings Inc | D33: Philippines | E33: -0.0056 | F33: 0.2253 | G33: 0.5 | H33: 22.49 | I33: 0.53 | J33: 0.023566029 | K33: 1.16 | L33: 0.84 | M33: 0.77 | N33: 0.68 | O33: 0.65 | Q33: Doanh thu / CP năm 2022 | R33: 4784.4013
A34: 3 | B34: KLBF:IJ | C34: Kalbe Farma Tbk PT | D34: Indonesia | E34: 0.0771 | F34: 0.4419 | G34: 0.62 | H34: 13.92 | I34: 2.7926 | J34: 0.20061782 | K34: 3.131 | L34: 2.749 | M34: 2.898 | N34: 2.482 | O34: 2.16 | Q34: Mean P/S | R34: 1.0350618
A35: 4 | B35: 600833 CH Equity | C35: Shanghai No1 Pharmacy Co Ltd | D35: China | E35: 0.1 | F35: 0.1852 | G35: 1.14 | H35: 12.34 | I35: 1.45 | J35: 0.11750405 | K35: 1.99 | L35: 1.73 | M35: 1.69 | N35: 1.37 | O35: 1.49 | Q35: P/S FW | R35: 1.0350618
A36: 5 | B36: 600713 CH Equity | C36: NanJing Pharmaceutical Co Ltd | D36: China | E36: 0.14 | F36: 0.0649 | G36: 1.05 | H36: 12.34 | I36: 0.11 | J36: 0.0089141005 | K36: 0.19 | L36: 0.14 | M36: 0.13 | N36: 0.12 | O36: 0.11 | Q36: Gía cổ phiếu | R36: 4952.1508
C37: Trung bình so sánh | E37: 0.09484 | F37: 0.25692 | G37: 0.566 | J37: 0.079315802 | K37: 0.12583473 | L37: 0.10184402 | M37: 0.088615172 | N37: 0.099765206 | O37: 0.077832965
C38: Tương quan với cty cùng ngành | D38: 0.74909585 | E38: 1.09484 | F38: 1.25692 | G38: 1.566 | I38: P/E VN | J38: 13.85 | Q38: Giá Cổ phiếu MWG | R38: 220128.78
C39: An Khang | E39: 0 | F39: 0 | G39: 0
C40: Target P/S điều chỉnh từ thị trường | K40: 1.742811 | L40: 1.4105397 | M40: 1.2273201 | N40: 1.3817481 | O40: 1.0779866
C41: Điều chỉnh tương quan | J41: 0.74909585
C42: Target P/S điều chỉnh từ thành quả HĐ | K42: 1.3055325 | L42: 1.0566294 | M42: 0.91938041 | N42: 1.0350618 | O42: 0.80751526
